{
  "type": "Feature",
  "properties": {
    "gn:admin1_code":"8.0",
    "gn:asciiname":"Makuuni",
    "gn:country_code":"SO",
    "gn:dem":23,
    "gn:feature_class":"P",
    "gn:feature_code":"PPL",
    "gn:name":"Makuuni",
    "gn:population":0,
    "gn:timezone":"Africa/Mogadishu",
    "iso:country":"SO",
    "wof:name":"Makuuni",
    "wof:placetype":"locality"
},
  "geometry": {"coordinates":[42.71221,0.47763],"type":"Point"}
}