{
  "type": "Feature",
  "properties": {
    "gn:admin1_code":"03",
    "gn:asciiname":"El Medo",
    "gn:cc2":"SO",
    "gn:country_code":"SO",
    "gn:dem":750,
    "gn:feature_class":"P",
    "gn:feature_code":"PPL",
    "gn:name":"El Medo",
    "gn:population":0,
    "gn:timezone":"Africa/Mogadishu",
    "iso:country":"SO",
    "name:und_x_variant":[
        "El Meddo",
        "El Medo"
    ],
    "wof:name":"El Medo",
    "wof:placetype":"locality"
},
  "geometry": {"coordinates":[49.21667,10.25],"type":"Point"}
}