{
  "type": "Feature",
  "properties": {
    "gn:admin1_code":"9.0",
    "gn:asciiname":"Toro",
    "gn:country_code":"SO",
    "gn:dem":14,
    "gn:feature_class":"P",
    "gn:feature_code":"PPL",
    "gn:name":"Toro",
    "gn:population":0,
    "gn:timezone":"Africa/Mogadishu",
    "iso:country":"SO",
    "wof:name":"Toro",
    "wof:placetype":"locality"
},
  "geometry": {"coordinates":[42.76667,0.25],"type":"Point"}
}