{
  "type": "Feature",
  "properties": {
    "gn:admin1_code":"09",
    "gn:asciiname":"Kobon",
    "gn:country_code":"SO",
    "gn:dem":9,
    "gn:feature_class":"P",
    "gn:feature_code":"PPL",
    "gn:name":"Kobon",
    "gn:population":0,
    "gn:timezone":"Africa/Mogadishu",
    "iso:country":"SO",
    "name:und_x_variant":[
        "Covon",
        "Kobon"
    ],
    "wof:name":"Kobon",
    "wof:placetype":"locality"
},
  "geometry": {"coordinates":[42.70911,0.03563],"type":"Point"}
}