{
  "type": "Feature",
  "properties": {
    "gn:admin1_code":"4.0",
    "gn:asciiname":"Wagalow",
    "gn:country_code":"SO",
    "gn:dem":290,
    "gn:feature_class":"P",
    "gn:feature_code":"PPL",
    "gn:name":"Wagalow",
    "gn:population":0,
    "gn:timezone":"Africa/Mogadishu",
    "iso:country":"SO",
    "name:som_x_preferred":[
        "Wagalow"
    ],
    "wof:name":"Wagalow",
    "wof:placetype":"locality"
},
  "geometry": {"coordinates":[44.1561,3.0782],"type":"Point"}
}