{
  "type": "Feature",
  "properties": {
    "gn:admin1_code":"04",
    "gn:asciiname":"Gawaanka",
    "gn:country_code":"SO",
    "gn:dem":223,
    "gn:feature_class":"P",
    "gn:feature_code":"PPL",
    "gn:name":"Gawaanka",
    "gn:population":0,
    "gn:timezone":"Africa/Mogadishu",
    "iso:country":"SO",
    "name:som_x_preferred":[
        "Gawaanka"
    ],
    "wof:name":"Gawaanka",
    "wof:placetype":"locality"
},
  "geometry": {"coordinates":[44.32105,2.97999],"type":"Point"}
}