{
  "type": "Feature",
  "properties": {
    "gn:admin1_code":"06",
    "gn:asciiname":"Dhas",
    "gn:cc2":"SO",
    "gn:country_code":"SO",
    "gn:dem":348,
    "gn:feature_class":"P",
    "gn:feature_code":"PPL",
    "gn:name":"Dhas",
    "gn:population":0,
    "gn:timezone":"Africa/Mogadishu",
    "iso:country":"SO",
    "name:und_x_variant":[
        "Dhoze",
        "Dhaz\u00e8",
        "Dhas"
    ],
    "wof:name":"Dhas",
    "wof:placetype":"locality"
},
  "geometry": {"coordinates":[41.46667,2.86667],"type":"Point"}
}