{
  "type": "Feature",
  "properties": {
    "gn:admin1_code":"20",
    "gn:asciiname":"Waraabaley",
    "gn:country_code":"SO",
    "gn:dem":1506,
    "gn:feature_class":"P",
    "gn:feature_code":"PPL",
    "gn:name":"Waraabaley",
    "gn:population":0,
    "gn:timezone":"Africa/Mogadishu",
    "iso:country":"SO",
    "wof:name":"Waraabaley",
    "wof:placetype":"locality"
},
  "geometry": {"coordinates":[43.80099000000001,9.57882],"type":"Point"}
}