{
  "type": "Feature",
  "properties": {
    "gn:admin1_code":"14",
    "gn:asciiname":"Ceel Wareegow",
    "gn:country_code":"SO",
    "gn:dem":74,
    "gn:feature_class":"P",
    "gn:feature_code":"PPL",
    "gn:name":"Ceel Wareegow",
    "gn:population":0,
    "gn:timezone":"Africa/Mogadishu",
    "iso:country":"SO",
    "name:som_x_preferred":[
        "Ceel Wareegow"
    ],
    "wof:name":"Ceel Wareegow",
    "wof:placetype":"locality"
},
  "geometry": {"coordinates":[44.7856,1.8081],"type":"Point"}
}