{
  "type": "Feature",
  "properties": {
    "gn:admin1_code":"07",
    "gn:asciiname":"Kali Dheenle",
    "gn:country_code":"SO",
    "gn:dem":171,
    "gn:feature_class":"P",
    "gn:feature_code":"PPL",
    "gn:name":"Kali Dheenle",
    "gn:population":0,
    "gn:timezone":"Africa/Mogadishu",
    "iso:country":"SO",
    "name:som_x_preferred":[
        "Kali Dheenle"
    ],
    "wof:name":"Kali Dheenle",
    "wof:placetype":"locality"
},
  "geometry": {"coordinates":[45.33018,4.44472],"type":"Point"}
}