{
  "type": "Feature",
  "properties": {
    "gn:admin1_code":"08",
    "gn:asciiname":"Ghesso",
    "gn:country_code":"SO",
    "gn:dem":144,
    "gn:feature_class":"P",
    "gn:feature_code":"PPL",
    "gn:name":"Ghesso",
    "gn:population":0,
    "gn:timezone":"Africa/Mogadishu",
    "iso:country":"SO",
    "wof:name":"Ghesso",
    "wof:placetype":"locality"
},
  "geometry": {"coordinates":[41.98333,1.66667],"type":"Point"}
}