{
  "type": "Feature",
  "properties": {
    "gn:admin1_code":"01",
    "gn:asciiname":"El Dego Gos",
    "gn:country_code":"SO",
    "gn:dem":430,
    "gn:feature_class":"P",
    "gn:feature_code":"PPL",
    "gn:name":"El Dego Gos",
    "gn:population":0,
    "gn:timezone":"Africa/Mogadishu",
    "iso:country":"SO",
    "wof:name":"El Dego Gos",
    "wof:placetype":"locality"
},
  "geometry": {"coordinates":[43.43333,4.61667],"type":"Point"}
}