{
  "type": "Feature",
  "properties": {
    "gn:admin1_code":"14.0",
    "gn:asciiname":"Meeyd",
    "gn:country_code":"SO",
    "gn:dem":75,
    "gn:feature_class":"P",
    "gn:feature_code":"PPL",
    "gn:name":"Meeyd",
    "gn:population":0,
    "gn:timezone":"Africa/Mogadishu",
    "iso:country":"SO",
    "name:som_x_preferred":[
        "Meeyd"
    ],
    "wof:name":"Meeyd",
    "wof:placetype":"locality"
},
  "geometry": {"coordinates":[44.5568,2.1394],"type":"Point"}
}