{
  "type": "Feature",
  "properties": {
    "gn:admin1_code":"20",
    "gn:asciiname":"Cumar Aadan",
    "gn:country_code":"SO",
    "gn:dem":1458,
    "gn:feature_class":"P",
    "gn:feature_code":"PPL",
    "gn:name":"Cumar Aadan",
    "gn:population":0,
    "gn:timezone":"Africa/Mogadishu",
    "iso:country":"SO",
    "wof:name":"Cumar Aadan",
    "wof:placetype":"locality"
},
  "geometry": {"coordinates":[43.64676,9.69913],"type":"Point"}
}