{
  "type": "Feature",
  "properties": {
    "gn:admin1_code":"04",
    "gn:asciiname":"Abdurug",
    "gn:country_code":"SO",
    "gn:dem":483,
    "gn:feature_class":"P",
    "gn:feature_code":"PPL",
    "gn:name":"Abdurug",
    "gn:population":0,
    "gn:timezone":"Africa/Mogadishu",
    "iso:country":"SO",
    "name:som_x_preferred":[
        "Abdurug"
    ],
    "wof:name":"Abdurug",
    "wof:placetype":"locality"
},
  "geometry": {"coordinates":[43.48823,3.02004],"type":"Point"}
}