{
  "type": "Feature",
  "properties": {
    "gn:admin1_code":"06",
    "gn:asciiname":"Giumea Sce Maio",
    "gn:country_code":"SO",
    "gn:dem":100,
    "gn:feature_class":"P",
    "gn:feature_code":"PPL",
    "gn:name":"Giumea Sce Maio",
    "gn:population":0,
    "gn:timezone":"Africa/Mogadishu",
    "iso:country":"SO",
    "name:und_x_variant":[
        "Giumea Sciek Mai\u00f2",
        "Giumea Sce Maio"
    ],
    "wof:name":"Giumea Sce Maio",
    "wof:placetype":"locality"
},
  "geometry": {"coordinates":[42.31504,2.45019],"type":"Point"}
}