{
  "type": "Feature",
  "properties": {
    "gn:admin1_code":"03",
    "gn:asciiname":"Bur Mahago",
    "gn:country_code":"SO",
    "gn:dem":109,
    "gn:feature_class":"P",
    "gn:feature_code":"PPL",
    "gn:name":"Bur Mahago",
    "gn:population":0,
    "gn:timezone":"Africa/Mogadishu",
    "iso:country":"SO",
    "wof:name":"Bur Mahago",
    "wof:placetype":"locality"
},
  "geometry": {"coordinates":[50.63333,10.38333],"type":"Point"}
}