{
  "type": "Feature",
  "properties": {
    "gn:admin1_code":"21",
    "gn:asciiname":"Haren",
    "gn:country_code":"SO",
    "gn:dem":193,
    "gn:feature_class":"P",
    "gn:feature_code":"PPL",
    "gn:name":"Haren",
    "gn:population":0,
    "gn:timezone":"Africa/Mogadishu",
    "iso:country":"SO",
    "name:und_x_variant":[
        "Harre",
        "Harren",
        "Harreh",
        "Haren"
    ],
    "wof:name":"Haren",
    "wof:placetype":"locality"
},
  "geometry": {"coordinates":[43.28333,10.88333],"type":"Point"}
}