{
  "type": "Feature",
  "properties": {
    "gn:admin1_code":"21",
    "gn:asciiname":"Haren",
    "gn:country_code":"SO",
    "gn:dem":193,
    "gn:feature_class":"P",
    "gn:feature_code":"PPL",
    "gn:name":"Haren",
    "gn:population":0,
    "gn:timezone":"Africa/Mogadishu",
    "iso:country":"SO",
    "name:ceb_x_preferred":[
        "Haren"
    ],
    "name:ces_x_preferred":[
        "Haren"
    ],
    "name:dan_x_preferred":[
        "Haren"
    ],
    "name:deu_x_preferred":[
        "Haren"
    ],
    "name:epo_x_preferred":[
        "Haren"
    ],
    "name:fra_x_preferred":[
        "Haren"
    ],
    "name:nld_x_preferred":[
        "Haren"
    ],
    "name:pol_x_preferred":[
        "Haren"
    ],
    "name:ron_x_preferred":[
        "Haren"
    ],
    "name:rus_x_preferred":[
        "\u0425\u0430\u0440\u0435\u043d"
    ],
    "name:stq_x_preferred":[
        "Haren"
    ],
    "name:swe_x_preferred":[
        "Haren"
    ],
    "name:und_x_variant":[
        "Harre",
        "Harren",
        "Harreh",
        "Haren"
    ],
    "wof:name":"Haren",
    "wof:placetype":"locality"
},
  "geometry": {"coordinates":[43.28333,10.88333],"type":"Point"}
}