{
  "type": "Feature",
  "properties": {
    "gn:admin1_code":"04",
    "gn:asciiname":"Hemin Gurei",
    "gn:country_code":"SO",
    "gn:dem":180,
    "gn:feature_class":"P",
    "gn:feature_code":"PPL",
    "gn:name":"Hemin Gurei",
    "gn:population":0,
    "gn:timezone":"Africa/Mogadishu",
    "iso:country":"SO",
    "wof:name":"Hemin Gurei",
    "wof:placetype":"locality"
},
  "geometry": {"coordinates":[43.11667,1.88333],"type":"Point"}
}