{
  "type": "Feature",
  "properties": {
    "gn:admin1_code":"06",
    "gn:asciiname":"Corfon",
    "gn:country_code":"SO",
    "gn:dem":419,
    "gn:feature_class":"P",
    "gn:feature_code":"PPL",
    "gn:name":"Corfon",
    "gn:population":0,
    "gn:timezone":"Africa/Mogadishu",
    "iso:country":"SO",
    "wof:name":"Corfon",
    "wof:placetype":"locality"
},
  "geometry": {"coordinates":[42.03333,3.15],"type":"Point"}
}