{
  "type": "Feature",
  "properties": {
    "gn:admin1_code":"05",
    "gn:asciiname":"Garsala Avascia",
    "gn:country_code":"SO",
    "gn:dem":110,
    "gn:feature_class":"P",
    "gn:feature_code":"PPL",
    "gn:name":"Garsala Avascia",
    "gn:population":0,
    "gn:timezone":"Africa/Mogadishu",
    "iso:country":"SO",
    "wof:name":"Garsala Avascia",
    "wof:placetype":"locality"
},
  "geometry": {"coordinates":[46.75,4.08333],"type":"Point"}
}