{
  "type": "Feature",
  "properties": {
    "gn:admin1_code":"18",
    "gn:asciiname":"Dighelli",
    "gn:country_code":"SO",
    "gn:dem":262,
    "gn:feature_class":"P",
    "gn:feature_code":"PPL",
    "gn:name":"Dighelli",
    "gn:population":0,
    "gn:timezone":"Africa/Mogadishu",
    "iso:country":"SO",
    "wof:name":"Dighelli",
    "wof:placetype":"locality"
},
  "geometry": {"coordinates":[49.48333,7.83333],"type":"Point"}
}