{
  "type": "Feature",
  "properties": {
    "gn:admin1_code":"05",
    "gn:asciiname":"Garable",
    "gn:country_code":"SO",
    "gn:dem":168,
    "gn:feature_class":"P",
    "gn:feature_code":"PPL",
    "gn:name":"Garable",
    "gn:population":0,
    "gn:timezone":"Africa/Mogadishu",
    "iso:country":"SO",
    "name:som_x_preferred":[
        "Garable"
    ],
    "wof:name":"Garable",
    "wof:placetype":"locality"
},
  "geometry": {"coordinates":[47.16104,4.67724],"type":"Point"}
}