{
  "type": "Feature",
  "properties": {
    "gn:admin1_code":"04",
    "gn:asciiname":"Hobishole",
    "gn:country_code":"SO",
    "gn:dem":490,
    "gn:feature_class":"P",
    "gn:feature_code":"PPL",
    "gn:name":"Hobishole",
    "gn:population":0,
    "gn:timezone":"Africa/Mogadishu",
    "iso:country":"SO",
    "name:som_x_preferred":[
        "Hobishole"
    ],
    "wof:name":"Hobishole",
    "wof:placetype":"locality"
},
  "geometry": {"coordinates":[43.34913,2.9876],"type":"Point"}
}