{
  "type": "Feature",
  "properties": {
    "gn:admin1_code":"08",
    "gn:asciiname":"Cabdi Cali",
    "gn:country_code":"SO",
    "gn:dem":32,
    "gn:feature_class":"P",
    "gn:feature_code":"PPL",
    "gn:name":"Cabdi Cali",
    "gn:population":0,
    "gn:timezone":"Africa/Mogadishu",
    "iso:country":"SO",
    "wof:name":"Cabdi Cali",
    "wof:placetype":"locality"
},
  "geometry": {"coordinates":[42.64573,0.74119],"type":"Point"}
}