{
  "type": "Feature",
  "properties": {
    "gn:admin1_code":"04",
    "gn:asciiname":"Boonka",
    "gn:country_code":"SO",
    "gn:dem":219,
    "gn:feature_class":"P",
    "gn:feature_code":"PPL",
    "gn:name":"Boonka",
    "gn:population":0,
    "gn:timezone":"Africa/Mogadishu",
    "iso:country":"SO",
    "name:som_x_preferred":[
        "Boonka"
    ],
    "wof:name":"Boonka",
    "wof:placetype":"locality"
},
  "geometry": {"coordinates":[44.08039,2.91581],"type":"Point"}
}