{
  "type": "Feature",
  "properties": {
    "gn:admin1_code":"19",
    "gn:asciiname":"Gedeys",
    "gn:country_code":"SO",
    "gn:dem":1310,
    "gn:feature_class":"P",
    "gn:feature_code":"PPL",
    "gn:name":"Gedeys",
    "gn:population":0,
    "gn:timezone":"Africa/Mogadishu",
    "iso:country":"SO",
    "name:som_x_preferred":[
        "Gedeys"
    ],
    "name:und_x_variant":[
        "Gedeis",
        "Gudais"
    ],
    "wof:name":"Gedeys",
    "wof:placetype":"locality"
},
  "geometry": {"coordinates":[45.4603,9.94857],"type":"Point"}
}