{
  "type": "Feature",
  "properties": {
    "gn:admin1_code":"04",
    "gn:asciiname":"Goloonle",
    "gn:country_code":"SO",
    "gn:dem":239,
    "gn:feature_class":"P",
    "gn:feature_code":"PPL",
    "gn:name":"Goloonle",
    "gn:population":0,
    "gn:timezone":"Africa/Mogadishu",
    "iso:country":"SO",
    "name:som_x_preferred":[
        "Goloonle"
    ],
    "wof:name":"Goloonle",
    "wof:placetype":"locality"
},
  "geometry": {"coordinates":[43.8877,2.8142],"type":"Point"}
}