{
  "type": "Feature",
  "properties": {
    "gn:admin1_code":"14.0",
    "gn:asciiname":"Suleymaan",
    "gn:country_code":"SO",
    "gn:dem":72,
    "gn:feature_class":"P",
    "gn:feature_code":"PPL",
    "gn:name":"Suleymaan",
    "gn:population":0,
    "gn:timezone":"Africa/Mogadishu",
    "iso:country":"SO",
    "name:som_x_preferred":[
        "Suleymaan"
    ],
    "name:und_x_variant":[
        "Busley",
        "Suleymaan"
    ],
    "wof:name":"Suleymaan",
    "wof:placetype":"locality"
},
  "geometry": {"coordinates":[44.70141,1.89416],"type":"Point"}
}