{
  "type": "Feature",
  "properties": {
    "gn:admin1_code":"10",
    "gn:asciiname":"Garacad",
    "gn:country_code":"SO",
    "gn:dem":3,
    "gn:feature_class":"P",
    "gn:feature_code":"PPL",
    "gn:name":"Garacad",
    "gn:population":0,
    "gn:timezone":"Africa/Mogadishu",
    "iso:country":"SO",
    "name:und_x_variant":[
        "Garad",
        "Garda",
        "Gara\u2018\u00e1d",
        "Garacad"
    ],
    "wof:name":"Garacad",
    "wof:placetype":"locality"
},
  "geometry": {"coordinates":[49.32608,6.9429],"type":"Point"}
}