{
  "type": "Feature",
  "properties": {
    "gn:admin1_code":"10",
    "gn:asciiname":"Goble Hodan",
    "gn:country_code":"SO",
    "gn:dem":133,
    "gn:feature_class":"P",
    "gn:feature_code":"PPL",
    "gn:name":"Goble Hodan",
    "gn:population":0,
    "gn:timezone":"Africa/Mogadishu",
    "iso:country":"SO",
    "wof:name":"Goble Hodan",
    "wof:placetype":"locality"
},
  "geometry": {"coordinates":[47.56667,5.28333],"type":"Point"}
}