{
  "type": "Feature",
  "properties": {
    "gn:admin1_code":"13",
    "gn:asciiname":"Dermodo",
    "gn:country_code":"SO",
    "gn:dem":7,
    "gn:feature_class":"P",
    "gn:feature_code":"PPL",
    "gn:name":"Dermodo",
    "gn:population":0,
    "gn:timezone":"Africa/Mogadishu",
    "iso:country":"SO",
    "wof:name":"Dermodo",
    "wof:placetype":"locality"
},
  "geometry": {"coordinates":[46.21667,2.66667],"type":"Point"}
}