{
  "type": "Feature",
  "properties": {
    "gn:admin1_code":"03",
    "gn:asciiname":"Avarfaro",
    "gn:country_code":"SO",
    "gn:dem":207,
    "gn:feature_class":"P",
    "gn:feature_code":"PPL",
    "gn:name":"Avarfaro",
    "gn:population":0,
    "gn:timezone":"Africa/Mogadishu",
    "iso:country":"SO",
    "wof:name":"Avarfaro",
    "wof:placetype":"locality"
},
  "geometry": {"coordinates":[50.88333,10.98333],"type":"Point"}
}