{
  "type": "Feature",
  "properties": {
    "iso:country":"SO",
    "name:deu_x_preferred":[
        "Wanlaweyne"
    ],
    "name:eng_x_preferred":[
        "Wanlaweyn"
    ],
    "name:ita_x_preferred":[
        "Uanle Uen"
    ],
    "name:jpn_x_preferred":[
        "\u30ef\u30f3\u30e9\u30a6\u30a7\u30a4\u30f3"
    ],
    "name:nld_x_preferred":[
        "Wanlaweyn"
    ],
    "name:pol_x_preferred":[
        "Wanlaweyn"
    ],
    "name:som_x_preferred":[
        "Wanlaweyn"
    ],
    "name:unk_x_variant":[
        "Bahle Dogli"
    ],
    "name:urd_x_preferred":[
        "\u0648\u0627\u0646\u0644\u0627\u0648\u06cc\u0646"
    ],
    "name:zho_x_preferred":[
        "\u842c\u840a\u6587"
    ],
    "qs:gn_country":"SO",
    "qs:gn_fcode":"PPL",
    "qs:gn_pop":22022,
    "qs:name":"Wanlaweyn",
    "qs:name_adm0":"Somalia",
    "qs:name_adm1":"Shabeellaha Hoose",
    "qs:photos":0,
    "qs:photos_1k":0,
    "qs:photos_9k":1,
    "qs:photos_9r":1,
    "qs:photos_all":1,
    "qs:photos_sr":0,
    "qs:placetype":"Town",
    "qs:pop_sr":"7",
    "qs:woe_adm0":23424949,
    "wd:wordcount":90,
    "wof:name":"Wanlaweyn",
    "wof:placetype":"locality",
    "wof:population":22022
},
  "geometry": {"coordinates":[44.8938,2.6185],"type":"Point"}
}