{
  "type": "Feature",
  "properties": {
    "gn:admin1_code":"14",
    "gn:asciiname":"Deg Jannaay",
    "gn:country_code":"SO",
    "gn:dem":70,
    "gn:feature_class":"P",
    "gn:feature_code":"PPL",
    "gn:name":"Deg Jannaay",
    "gn:population":0,
    "gn:timezone":"Africa/Mogadishu",
    "iso:country":"SO",
    "name:som_x_preferred":[
        "Deg Jannaay"
    ],
    "wof:name":"Deg Jannaay",
    "wof:placetype":"locality"
},
  "geometry": {"coordinates":[44.608,1.7062],"type":"Point"}
}