{
  "type": "Feature",
  "properties": {
    "gn:admin1_code":"4.0",
    "gn:asciiname":"Tugeer",
    "gn:country_code":"SO",
    "gn:dem":485,
    "gn:feature_class":"P",
    "gn:feature_code":"PPL",
    "gn:name":"Tugeer",
    "gn:population":0,
    "gn:timezone":"Africa/Mogadishu",
    "iso:country":"SO",
    "name:som_x_preferred":[
        "Tugeer"
    ],
    "wof:name":"Tugeer",
    "wof:placetype":"locality"
},
  "geometry": {"coordinates":[43.4892,2.99247],"type":"Point"}
}