{
  "type": "Feature",
  "properties": {
    "gn:admin1_code":"05",
    "gn:asciiname":"Bargaan",
    "gn:country_code":"SO",
    "gn:dem":134,
    "gn:feature_class":"P",
    "gn:feature_code":"PPL",
    "gn:name":"Bargaan",
    "gn:population":0,
    "gn:timezone":"Africa/Mogadishu",
    "iso:country":"SO",
    "name:som_x_preferred":[
        "Bargaan"
    ],
    "wof:name":"Bargaan",
    "wof:placetype":"locality"
},
  "geometry": {"coordinates":[47.04662,4.36543],"type":"Point"}
}