{
  "type": "Feature",
  "properties": {
    "gn:admin1_code":"14",
    "gn:asciiname":"Adale",
    "gn:cc2":"SO",
    "gn:country_code":"SO",
    "gn:dem":93,
    "gn:feature_class":"P",
    "gn:feature_code":"PPL",
    "gn:name":"Adale",
    "gn:population":0,
    "gn:timezone":"Africa/Mogadishu",
    "iso:country":"SO",
    "name:ceb_x_preferred":[
        "Cadale"
    ],
    "name:deu_x_preferred":[
        "Adale"
    ],
    "name:fas_x_preferred":[
        "\u0627\u062f\u0627\u0644"
    ],
    "name:ita_x_preferred":[
        "Adale"
    ],
    "name:rus_x_preferred":[
        "\u0410\u0434\u0430\u043b\u0435"
    ],
    "name:som_x_preferred":[
        "Cadale"
    ],
    "name:und_x_variant":[
        "Adalei"
    ],
    "name:urd_x_preferred":[
        "\u0627\u062f\u0627\u0644"
    ],
    "wof:name":"Adale",
    "wof:placetype":"locality"
},
  "geometry": {"coordinates":[45.21667,2.48333],"type":"Point"}
}