{
  "type": "Feature",
  "properties": {
    "gn:admin1_code":"14",
    "gn:asciiname":"Adale",
    "gn:cc2":"SO",
    "gn:country_code":"SO",
    "gn:dem":93,
    "gn:feature_class":"P",
    "gn:feature_code":"PPL",
    "gn:name":"Adale",
    "gn:population":0,
    "gn:timezone":"Africa/Mogadishu",
    "iso:country":"SO",
    "name:und_x_variant":[
        "Adalei",
        "Adale"
    ],
    "wof:name":"Adale",
    "wof:placetype":"locality"
},
  "geometry": {"coordinates":[45.21667,2.48333],"type":"Point"}
}