{
  "type": "Feature",
  "properties": {
    "gn:admin1_code":"14",
    "gn:asciiname":"Dood",
    "gn:country_code":"SO",
    "gn:dem":98,
    "gn:feature_class":"P",
    "gn:feature_code":"PPL",
    "gn:name":"Dood",
    "gn:population":0,
    "gn:timezone":"Africa/Mogadishu",
    "iso:country":"SO",
    "name:som_x_preferred":[
        "Dood"
    ],
    "wof:name":"Dood",
    "wof:placetype":"locality"
},
  "geometry": {"coordinates":[45.16019,2.7536],"type":"Point"}
}