{
  "type": "Feature",
  "properties": {
    "gn:admin1_code":"03",
    "gn:asciiname":"Gammedin",
    "gn:country_code":"SO",
    "gn:dem":641,
    "gn:feature_class":"P",
    "gn:feature_code":"PPL",
    "gn:name":"Gammedin",
    "gn:population":0,
    "gn:timezone":"Africa/Mogadishu",
    "iso:country":"SO",
    "wof:name":"Gammedin",
    "wof:placetype":"locality"
},
  "geometry": {"coordinates":[50.01667,11.28333],"type":"Point"}
}