{
  "type": "Feature",
  "properties": {
    "gn:admin1_code":"14",
    "gn:asciiname":"Buur Fuule",
    "gn:country_code":"SO",
    "gn:dem":71,
    "gn:feature_class":"P",
    "gn:feature_code":"PPL",
    "gn:name":"Buur Fuule",
    "gn:population":0,
    "gn:timezone":"Africa/Mogadishu",
    "iso:country":"SO",
    "name:som_x_preferred":[
        "Buur Fuule"
    ],
    "wof:name":"Buur Fuule",
    "wof:placetype":"locality"
},
  "geometry": {"coordinates":[44.70668,1.77727],"type":"Point"}
}