{
  "type": "Feature",
  "properties": {
    "gn:admin1_code":"14.0",
    "gn:asciiname":"Malable",
    "gn:country_code":"SO",
    "gn:dem":82,
    "gn:feature_class":"P",
    "gn:feature_code":"PPL",
    "gn:name":"Malable",
    "gn:population":0,
    "gn:timezone":"Africa/Mogadishu",
    "iso:country":"SO",
    "name:som_x_preferred":[
        "Malable"
    ],
    "name:und_x_variant":[
        "Mallable"
    ],
    "wof:name":"Malable",
    "wof:placetype":"locality"
},
  "geometry": {"coordinates":[44.83349000000001,1.98419],"type":"Point"}
}