{
  "type": "Feature",
  "properties": {
    "gn:admin1_code":"06",
    "gn:asciiname":"Guduud",
    "gn:country_code":"SO",
    "gn:dem":106,
    "gn:feature_class":"P",
    "gn:feature_code":"PPL",
    "gn:name":"Guduud",
    "gn:population":0,
    "gn:timezone":"Africa/Mogadishu",
    "iso:country":"SO",
    "wof:name":"Guduud",
    "wof:placetype":"locality"
},
  "geometry": {"coordinates":[42.23403,2.13431],"type":"Point"}
}