{
  "type": "Feature",
  "properties": {
    "gn:admin1_code":"13",
    "gn:asciiname":"Hidweyne",
    "gn:country_code":"SO",
    "gn:dem":125,
    "gn:feature_class":"P",
    "gn:feature_code":"PPL",
    "gn:name":"Hidweyne",
    "gn:population":0,
    "gn:timezone":"Africa/Mogadishu",
    "iso:country":"SO",
    "name:som_x_preferred":[
        "Hidweyne"
    ],
    "wof:name":"Hidweyne",
    "wof:placetype":"locality"
},
  "geometry": {"coordinates":[45.385,2.2898],"type":"Point"}
}