{
  "type": "Feature",
  "properties": {
    "gn:admin1_code":"3.0",
    "gn:asciiname":"Scillale Hodmane",
    "gn:country_code":"SO",
    "gn:dem":405,
    "gn:feature_class":"P",
    "gn:feature_code":"PPL",
    "gn:name":"Scillale Hodmane",
    "gn:population":0,
    "gn:timezone":"Africa/Mogadishu",
    "iso:country":"SO",
    "wof:name":"Scillale Hodmane",
    "wof:placetype":"locality"
},
  "geometry": {"coordinates":[49.71667,10.46667],"type":"Point"}
}