{
  "type": "Feature",
  "properties": {
    "gn:admin1_code":"19",
    "gn:asciiname":"Ilma Shiikh",
    "gn:country_code":"SO",
    "gn:dem":1099,
    "gn:feature_class":"P",
    "gn:feature_code":"PPL",
    "gn:name":"Ilma Shiikh",
    "gn:population":0,
    "gn:timezone":"Africa/Mogadishu",
    "iso:country":"SO",
    "name:som_x_preferred":[
        "Ilma Shiikh"
    ],
    "name:und_x_variant":[
        "Aroori"
    ],
    "wof:name":"Ilma Shiikh",
    "wof:placetype":"locality"
},
  "geometry": {"coordinates":[45.47074,9.35014],"type":"Point"}
}