{
  "type": "Feature",
  "properties": {
    "gn:admin1_code":"21.0",
    "gn:asciiname":"Walaalgo",
    "gn:country_code":"SO",
    "gn:dem":1615,
    "gn:feature_class":"P",
    "gn:feature_code":"PPL",
    "gn:name":"Walaalgo",
    "gn:population":0,
    "gn:timezone":"Africa/Mogadishu",
    "iso:country":"SO",
    "name:und_x_variant":[
        "Ualal\u2019go",
        "Walaalgo"
    ],
    "wof:name":"Walaalgo",
    "wof:placetype":"locality"
},
  "geometry": {"coordinates":[43.28746,9.84296],"type":"Point"}
}