{
  "type": "Feature",
  "properties": {
    "gn:admin1_code":"08",
    "gn:asciiname":"Balley",
    "gn:country_code":"SO",
    "gn:dem":31,
    "gn:feature_class":"P",
    "gn:feature_code":"PPL",
    "gn:name":"Balley",
    "gn:population":0,
    "gn:timezone":"Africa/Mogadishu",
    "iso:country":"SO",
    "name:und_x_variant":[
        "Gallou",
        "Baljey",
        "Ballei",
        "Balley"
    ],
    "wof:name":"Balley",
    "wof:placetype":"locality"
},
  "geometry": {"coordinates":[42.74727,0.60955],"type":"Point"}
}