{
  "type": "Feature",
  "properties": {
    "gn:admin1_code":"8.0",
    "gn:asciiname":"Qardhaale",
    "gn:country_code":"SO",
    "gn:dem":48,
    "gn:feature_class":"P",
    "gn:feature_code":"PPL",
    "gn:name":"Qardhaale",
    "gn:population":0,
    "gn:timezone":"Africa/Mogadishu",
    "iso:country":"SO",
    "name:und_x_variant":[
        "Cardale",
        "Gardale",
        "Qardhaale"
    ],
    "wof:name":"Qardhaale",
    "wof:placetype":"locality"
},
  "geometry": {"coordinates":[42.59773,1.11367],"type":"Point"}
}