{
  "type": "Feature",
  "properties": {
    "gn:admin1_code":"04",
    "gn:asciiname":"Illow Antow",
    "gn:country_code":"SO",
    "gn:dem":485,
    "gn:feature_class":"P",
    "gn:feature_code":"PPL",
    "gn:name":"Illow Antow",
    "gn:population":0,
    "gn:timezone":"Africa/Mogadishu",
    "iso:country":"SO",
    "name:som_x_preferred":[
        "Illow Antow"
    ],
    "wof:name":"Illow Antow",
    "wof:placetype":"locality"
},
  "geometry": {"coordinates":[43.5424,3.1405],"type":"Point"}
}