{
  "type": "Feature",
  "properties": {
    "gn:admin1_code":"13",
    "gn:asciiname":"Buurfuule",
    "gn:country_code":"SO",
    "gn:dem":114,
    "gn:feature_class":"P",
    "gn:feature_code":"PPL",
    "gn:name":"Buurfuule",
    "gn:population":0,
    "gn:timezone":"Africa/Mogadishu",
    "iso:country":"SO",
    "name:som_x_preferred":[
        "Buurfuule"
    ],
    "name:und_x_variant":[
        "Burfule",
        "Buurfuule"
    ],
    "wof:name":"Buurfuule",
    "wof:placetype":"locality"
},
  "geometry": {"coordinates":[45.5293,2.9315],"type":"Point"}
}