{
  "type": "Feature",
  "properties": {
    "gn:admin1_code":"14",
    "gn:asciiname":"Jilyaale",
    "gn:country_code":"SO",
    "gn:dem":104,
    "gn:feature_class":"P",
    "gn:feature_code":"PPL",
    "gn:name":"Jilyaale",
    "gn:population":0,
    "gn:timezone":"Africa/Mogadishu",
    "iso:country":"SO",
    "name:ara_x_preferred":[
        "\u062c\u0644\u064a\u0627\u0644\u064a"
    ],
    "name:som_x_preferred":[
        "Jilyaale"
    ],
    "wof:name":"Jilyaale",
    "wof:placetype":"locality"
},
  "geometry": {"coordinates":[45.13763,2.84836],"type":"Point"}
}