{
  "type": "Feature",
  "properties": {
    "gn:admin1_code":"06",
    "gn:asciiname":"Agghini",
    "gn:country_code":"SO",
    "gn:dem":127,
    "gn:feature_class":"P",
    "gn:feature_code":"PPL",
    "gn:name":"Agghini",
    "gn:population":0,
    "gn:timezone":"Africa/Mogadishu",
    "iso:country":"SO",
    "wof:name":"Agghini",
    "wof:placetype":"locality"
},
  "geometry": {"coordinates":[42.43636,2.41468],"type":"Point"}
}