{
  "type": "Feature",
  "properties": {
    "gn:admin1_code":"4.0",
    "gn:asciiname":"War Hawen",
    "gn:country_code":"SO",
    "gn:dem":492,
    "gn:feature_class":"P",
    "gn:feature_code":"PPL",
    "gn:name":"War Hawen",
    "gn:population":0,
    "gn:timezone":"Africa/Mogadishu",
    "iso:country":"SO",
    "name:som_x_preferred":[
        "War Hawen"
    ],
    "name:und_x_variant":[
        "Bulo Hauen",
        "War Hawen"
    ],
    "wof:name":"War Hawen",
    "wof:placetype":"locality"
},
  "geometry": {"coordinates":[43.5318,3.2501],"type":"Point"}
}