{
  "type": "Feature",
  "properties": {
    "gn:admin1_code":"9.0",
    "gn:asciiname":"Xaaji Cali",
    "gn:country_code":"SO",
    "gn:dem":7,
    "gn:feature_class":"P",
    "gn:feature_code":"PPL",
    "gn:name":"Xaaji Cali",
    "gn:population":0,
    "gn:timezone":"Africa/Mogadishu",
    "iso:country":"SO",
    "name:und_x_variant":[
        "Yoontoy",
        "Xaaji Cah",
        "Xaaji Cali"
    ],
    "wof:name":"Xaaji Cali",
    "wof:placetype":"locality"
},
  "geometry": {"coordinates":[42.6003,-0.16396],"type":"Point"}
}