{
  "type": "Feature",
  "properties": {
    "gn:admin1_code":"4.0",
    "gn:asciiname":"Samakaya",
    "gn:country_code":"SO",
    "gn:dem":273,
    "gn:feature_class":"P",
    "gn:feature_code":"PPLL",
    "gn:name":"Samakaya",
    "gn:population":0,
    "gn:timezone":"Africa/Mogadishu",
    "iso:country":"SO",
    "name:som_x_preferred":[
        "Samakaya"
    ],
    "wof:name":"Samakaya",
    "wof:placetype":"locality"
},
  "geometry": {"coordinates":[43.92272,3.02976],"type":"Point"}
}