{
  "type": "Feature",
  "properties": {
    "gn:admin1_code":"14.0",
    "gn:asciiname":"Maquudaale",
    "gn:country_code":"SO",
    "gn:dem":92,
    "gn:feature_class":"P",
    "gn:feature_code":"PPL",
    "gn:name":"Maquudaale",
    "gn:population":0,
    "gn:timezone":"Africa/Mogadishu",
    "iso:country":"SO",
    "name:som_x_preferred":[
        "Maquudaale"
    ],
    "wof:name":"Maquudaale",
    "wof:placetype":"locality"
},
  "geometry": {"coordinates":[44.96324,2.59306],"type":"Point"}
}