{
  "type": "Feature",
  "properties": {
    "gn:admin1_code":"14",
    "gn:asciiname":"Dhumayle",
    "gn:country_code":"SO",
    "gn:dem":94,
    "gn:feature_class":"P",
    "gn:feature_code":"PPL",
    "gn:name":"Dhumayle",
    "gn:population":0,
    "gn:timezone":"Africa/Mogadishu",
    "iso:country":"SO",
    "name:som_x_preferred":[
        "Dhumayle"
    ],
    "name:und_x_variant":[
        "Samasaydhe"
    ],
    "wof:name":"Dhumayle",
    "wof:placetype":"locality"
},
  "geometry": {"coordinates":[45.09505,2.61572],"type":"Point"}
}