{
  "type": "Feature",
  "properties": {
    "gn:admin1_code":"05",
    "gn:asciiname":"Gadoon",
    "gn:country_code":"SO",
    "gn:dem":253,
    "gn:feature_class":"P",
    "gn:feature_code":"PPL",
    "gn:name":"Gadoon",
    "gn:population":0,
    "gn:timezone":"Africa/Mogadishu",
    "iso:country":"SO",
    "name:som_x_preferred":[
        "Gadoon"
    ],
    "name:und_x_variant":[
        "God\u00f2n",
        "Gadoon"
    ],
    "wof:name":"Gadoon",
    "wof:placetype":"locality"
},
  "geometry": {"coordinates":[46.67639000000001,5.69201],"type":"Point"}
}