{
  "type": "Feature",
  "properties": {
    "gn:admin1_code":"03",
    "gn:asciiname":"Haluod",
    "gn:country_code":"SO",
    "gn:dem":16,
    "gn:feature_class":"P",
    "gn:feature_code":"PPL",
    "gn:name":"Haluod",
    "gn:population":0,
    "gn:timezone":"Africa/Mogadishu",
    "iso:country":"SO",
    "wof:name":"Haluod",
    "wof:placetype":"locality"
},
  "geometry": {"coordinates":[50.56667,11.76667],"type":"Point"}
}