{
  "type": "Feature",
  "properties": {
    "gn:admin1_code":"18",
    "gn:asciiname":"Arin Ragazz",
    "gn:cc2":"SO",
    "gn:country_code":"SO",
    "gn:dem":58,
    "gn:feature_class":"P",
    "gn:feature_code":"PPL",
    "gn:name":"Arin Ragazz",
    "gn:population":0,
    "gn:timezone":"Africa/Mogadishu",
    "iso:country":"SO",
    "name:und_x_variant":[
        "Arindirri",
        "Arin Ragazz"
    ],
    "wof:name":"Arin Ragazz",
    "wof:placetype":"locality"
},
  "geometry": {"coordinates":[49.86667,7.98333],"type":"Point"}
}