{
  "type": "Feature",
  "properties": {
    "gn:admin1_code":"14.0",
    "gn:asciiname":"Sarcade",
    "gn:country_code":"SO",
    "gn:dem":76,
    "gn:feature_class":"P",
    "gn:feature_code":"PPL",
    "gn:name":"Sarcade",
    "gn:population":0,
    "gn:timezone":"Africa/Mogadishu",
    "iso:country":"SO",
    "name:ron_x_preferred":[
        "Sarcade"
    ],
    "name:som_x_preferred":[
        "Sarcade"
    ],
    "wof:name":"Sarcade",
    "wof:placetype":"locality"
},
  "geometry": {"coordinates":[44.7055,1.8264],"type":"Point"}
}