{
  "type": "Feature",
  "properties": {
    "gn:admin1_code":"4.0",
    "gn:asciiname":"Rama Caddey",
    "gn:country_code":"SO",
    "gn:dem":204,
    "gn:feature_class":"P",
    "gn:feature_code":"PPL",
    "gn:name":"Rama Caddey",
    "gn:population":0,
    "gn:timezone":"Africa/Mogadishu",
    "iso:country":"SO",
    "wof:name":"Rama Caddey",
    "wof:placetype":"locality"
},
  "geometry": {"coordinates":[42.80069,1.99769],"type":"Point"}
}