{
  "type": "Feature",
  "properties": {
    "gn:admin1_code":"14",
    "gn:asciiname":"Fidlabey",
    "gn:country_code":"SO",
    "gn:dem":76,
    "gn:feature_class":"P",
    "gn:feature_code":"PPL",
    "gn:name":"Fidlabey",
    "gn:population":0,
    "gn:timezone":"Africa/Mogadishu",
    "iso:country":"SO",
    "name:som_x_preferred":[
        "Fidlabey"
    ],
    "wof:name":"Fidlabey",
    "wof:placetype":"locality"
},
  "geometry": {"coordinates":[44.7731,1.7712],"type":"Point"}
}