{
  "type": "Feature",
  "properties": {
    "gn:admin1_code":"22",
    "gn:admin2_code":"Laascaanood",
    "gn:asciiname":"Adhicadeeye",
    "gn:country_code":"SO",
    "gn:dem":643,
    "gn:feature_class":"P",
    "gn:feature_code":"PPL",
    "gn:name":"Adhicadeeye",
    "gn:population":0,
    "gn:timezone":"Africa/Mogadishu",
    "iso:country":"SO",
    "name:som_x_preferred":[
        "Adhicadeeye"
    ],
    "name:und_x_variant":[
        "Ade Adeye"
    ],
    "wof:name":"Adhicadeeye",
    "wof:placetype":"locality"
},
  "geometry": {"coordinates":[47.15852,8.67373],"type":"Point"}
}