{
  "type": "Feature",
  "properties": {
    "gn:admin1_code":"04",
    "gn:asciiname":"Golwiin",
    "gn:country_code":"SO",
    "gn:dem":187,
    "gn:feature_class":"P",
    "gn:feature_code":"PPL",
    "gn:name":"Golwiin",
    "gn:population":0,
    "gn:timezone":"Africa/Mogadishu",
    "iso:country":"SO",
    "name:som_x_preferred":[
        "Golwiin"
    ],
    "wof:name":"Golwiin",
    "wof:placetype":"locality"
},
  "geometry": {"coordinates":[44.02571,2.73302],"type":"Point"}
}