{
  "type": "Feature",
  "properties": {
    "gn:admin1_code":"03",
    "gn:asciiname":"Dancug",
    "gn:country_code":"SO",
    "gn:dem":585,
    "gn:feature_class":"P",
    "gn:feature_code":"PPL",
    "gn:name":"Dancug",
    "gn:population":0,
    "gn:timezone":"Africa/Mogadishu",
    "iso:country":"SO",
    "wof:name":"Dancug",
    "wof:placetype":"locality"
},
  "geometry": {"coordinates":[49.06667,10.96667],"type":"Point"}
}