{
  "type": "Feature",
  "properties": {
    "gn:admin1_code":"14",
    "gn:asciiname":"Buulallow",
    "gn:country_code":"SO",
    "gn:dem":88,
    "gn:feature_class":"P",
    "gn:feature_code":"PPL",
    "gn:name":"Buulallow",
    "gn:population":0,
    "gn:timezone":"Africa/Mogadishu",
    "iso:country":"SO",
    "name:som_x_preferred":[
        "Buulallow"
    ],
    "wof:name":"Buulallow",
    "wof:placetype":"locality"
},
  "geometry": {"coordinates":[45.0972,2.2193],"type":"Point"}
}