{
  "type": "Feature",
  "properties": {
    "gn:admin1_code":"6.0",
    "gn:asciiname":"Waamo Yarey",
    "gn:country_code":"SO",
    "gn:dem":259,
    "gn:feature_class":"P",
    "gn:feature_code":"PPL",
    "gn:name":"Waamo Yarey",
    "gn:population":0,
    "gn:timezone":"Africa/Mogadishu",
    "iso:country":"SO",
    "name:som_x_preferred":[
        "Waamo Yarey"
    ],
    "name:und_x_variant":[
        "Uama",
        "Uama Ierei",
        "Waamo Yarey"
    ],
    "wof:name":"Waamo Yarey",
    "wof:placetype":"locality"
},
  "geometry": {"coordinates":[42.2461,2.5136],"type":"Point"}
}