{
  "type": "Feature",
  "properties": {
    "gn:admin1_code":"14",
    "gn:asciiname":"Garab Ciise",
    "gn:country_code":"SO",
    "gn:dem":78,
    "gn:feature_class":"P",
    "gn:feature_code":"PPL",
    "gn:name":"Garab Ciise",
    "gn:population":0,
    "gn:timezone":"Africa/Mogadishu",
    "iso:country":"SO",
    "name:som_x_preferred":[
        "Garab Ciise"
    ],
    "wof:name":"Garab Ciise",
    "wof:placetype":"locality"
},
  "geometry": {"coordinates":[44.7279,1.8822],"type":"Point"}
}