{
  "type": "Feature",
  "properties": {
    "gn:admin1_code":"04",
    "gn:asciiname":"Godova Govede",
    "gn:country_code":"SO",
    "gn:dem":497,
    "gn:feature_class":"P",
    "gn:feature_code":"PPL",
    "gn:name":"Godova Govede",
    "gn:population":0,
    "gn:timezone":"Africa/Mogadishu",
    "iso:country":"SO",
    "wof:name":"Godova Govede",
    "wof:placetype":"locality"
},
  "geometry": {"coordinates":[43.56667,3.23333],"type":"Point"}
}