{
  "type": "Feature",
  "properties": {
    "gn:admin1_code":"04",
    "gn:asciiname":"Gawaan",
    "gn:country_code":"SO",
    "gn:dem":301,
    "gn:feature_class":"P",
    "gn:feature_code":"PPL",
    "gn:name":"Gawaan",
    "gn:population":0,
    "gn:timezone":"Africa/Mogadishu",
    "iso:country":"SO",
    "name:som_x_preferred":[
        "Gawaan"
    ],
    "wof:name":"Gawaan",
    "wof:placetype":"locality"
},
  "geometry": {"coordinates":[43.8746,3.0643],"type":"Point"}
}