{
  "type": "Feature",
  "properties": {
    "gn:admin1_code":"14.0",
    "gn:asciiname":"Riinow",
    "gn:country_code":"SO",
    "gn:dem":65,
    "gn:feature_class":"P",
    "gn:feature_code":"PPL",
    "gn:name":"Riinow",
    "gn:population":0,
    "gn:timezone":"Africa/Mogadishu",
    "iso:country":"SO",
    "name:som_x_preferred":[
        "Riinow"
    ],
    "wof:name":"Riinow",
    "wof:placetype":"locality"
},
  "geometry": {"coordinates":[44.40177,1.60996],"type":"Point"}
}