{
  "type": "Feature",
  "properties": {
    "gn:admin1_code":"22.0",
    "gn:asciiname":"Sahader",
    "gn:country_code":"SO",
    "gn:dem":625,
    "gn:feature_class":"P",
    "gn:feature_code":"PPL",
    "gn:name":"Sahader",
    "gn:population":0,
    "gn:timezone":"Africa/Mogadishu",
    "iso:country":"SO",
    "wof:name":"Sahader",
    "wof:placetype":"locality"
},
  "geometry": {"coordinates":[47.10472,8.00194],"type":"Point"}
}