{
  "type": "Feature",
  "properties": {
    "gn:admin1_code":"13",
    "gn:asciiname":"Durgaay",
    "gn:country_code":"SO",
    "gn:dem":52,
    "gn:feature_class":"P",
    "gn:feature_code":"PPL",
    "gn:name":"Durgaay",
    "gn:population":0,
    "gn:timezone":"Africa/Mogadishu",
    "iso:country":"SO",
    "name:som_x_preferred":[
        "Durgaay"
    ],
    "wof:name":"Durgaay",
    "wof:placetype":"locality"
},
  "geometry": {"coordinates":[45.9214,2.5616],"type":"Point"}
}