{
  "type": "Feature",
  "properties": {
    "gn:admin1_code":"14",
    "gn:asciiname":"Beerta Bisikrini",
    "gn:country_code":"SO",
    "gn:dem":86,
    "gn:feature_class":"P",
    "gn:feature_code":"PPL",
    "gn:name":"Beerta Bisikrini",
    "gn:population":0,
    "gn:timezone":"Africa/Mogadishu",
    "iso:country":"SO",
    "name:som_x_preferred":[
        "Beerta Bisikrini"
    ],
    "wof:name":"Beerta Bisikrini",
    "wof:placetype":"locality"
},
  "geometry": {"coordinates":[45.072,2.1289],"type":"Point"}
}