{
  "type": "Feature",
  "properties": {
    "gn:admin1_code":"07",
    "gn:asciiname":"Berdaale",
    "gn:country_code":"SO",
    "gn:dem":126,
    "gn:feature_class":"P",
    "gn:feature_code":"PPL",
    "gn:name":"Berdaale",
    "gn:population":0,
    "gn:timezone":"Africa/Mogadishu",
    "iso:country":"SO",
    "name:som_x_preferred":[
        "Berdaale"
    ],
    "wof:name":"Berdaale",
    "wof:placetype":"locality"
},
  "geometry": {"coordinates":[45.25919,3.27956],"type":"Point"}
}