{
  "type": "Feature",
  "properties": {
    "gn:admin1_code":"6.0",
    "gn:asciiname":"Qasalow",
    "gn:country_code":"SO",
    "gn:dem":91,
    "gn:feature_class":"P",
    "gn:feature_code":"PPL",
    "gn:name":"Qasalow",
    "gn:population":0,
    "gn:timezone":"Africa/Mogadishu",
    "iso:country":"SO",
    "wof:name":"Qasalow",
    "wof:placetype":"locality"
},
  "geometry": {"coordinates":[42.24781,1.99336],"type":"Point"}
}