{
  "type": "Feature",
  "properties": {
    "gn:admin1_code":"01",
    "gn:asciiname":"Bakar Weyn",
    "gn:country_code":"SO",
    "gn:dem":460,
    "gn:feature_class":"P",
    "gn:feature_code":"PPLL",
    "gn:name":"Bakar Weyn",
    "gn:population":0,
    "gn:timezone":"Africa/Mogadishu",
    "iso:country":"SO",
    "name:som_x_preferred":[
        "Bakar Weyn"
    ],
    "wof:name":"Bakar Weyn",
    "wof:placetype":"locality"
},
  "geometry": {"coordinates":[43.4567,3.6625],"type":"Point"}
}