{
  "type": "Feature",
  "properties": {
    "gn:admin1_code":"6.0",
    "gn:asciiname":"Mugdile",
    "gn:country_code":"SO",
    "gn:dem":108,
    "gn:feature_class":"P",
    "gn:feature_code":"PPL",
    "gn:name":"Mugdile",
    "gn:population":0,
    "gn:timezone":"Africa/Mogadishu",
    "iso:country":"SO",
    "wof:name":"Mugdile",
    "wof:placetype":"locality"
},
  "geometry": {"coordinates":[42.28977,2.50166],"type":"Point"}
}