{
  "type": "Feature",
  "properties": {
    "gn:admin1_code":"19",
    "gn:asciiname":"Gobdheere",
    "gn:country_code":"SO",
    "gn:dem":1173,
    "gn:feature_class":"P",
    "gn:feature_code":"PPL",
    "gn:name":"Gobdheere",
    "gn:population":0,
    "gn:timezone":"Africa/Mogadishu",
    "iso:country":"SO",
    "name:som_x_preferred":[
        "Gobdheere"
    ],
    "wof:name":"Gobdheere",
    "wof:placetype":"locality"
},
  "geometry": {"coordinates":[44.84338,9.52595],"type":"Point"}
}