{
  "type": "Feature",
  "properties": {
    "gn:admin1_code":"14.0",
    "gn:asciiname":"Sojilow",
    "gn:country_code":"SO",
    "gn:dem":53,
    "gn:feature_class":"P",
    "gn:feature_code":"PPL",
    "gn:name":"Sojilow",
    "gn:population":0,
    "gn:timezone":"Africa/Mogadishu",
    "iso:country":"SO",
    "name:som_x_preferred":[
        "Sojilow"
    ],
    "wof:name":"Sojilow",
    "wof:placetype":"locality"
},
  "geometry": {"coordinates":[43.9393,1.4448],"type":"Point"}
}