{
  "type": "Feature",
  "properties": {
    "gn:admin1_code":"14",
    "gn:asciiname":"Farkiyeerow",
    "gn:cc2":"SO",
    "gn:country_code":"SO",
    "gn:dem":63,
    "gn:feature_class":"P",
    "gn:feature_code":"PPL",
    "gn:name":"Farkiyeerow",
    "gn:population":0,
    "gn:timezone":"Africa/Mogadishu",
    "iso:country":"SO",
    "name:und_x_variant":[
        "Farkiero",
        "Farkiyeerow"
    ],
    "wof:name":"Farkiyeerow",
    "wof:placetype":"locality"
},
  "geometry": {"coordinates":[44.41667,1.66667],"type":"Point"}
}