{
  "type": "Feature",
  "properties": {
    "gn:admin1_code":"01",
    "gn:asciiname":"Eidarr Dabobe",
    "gn:cc2":"SO",
    "gn:country_code":"SO",
    "gn:dem":501,
    "gn:feature_class":"P",
    "gn:feature_code":"PPL",
    "gn:name":"Eidarr Dabobe",
    "gn:population":0,
    "gn:timezone":"Africa/Mogadishu",
    "iso:country":"SO",
    "name:und_x_variant":[
        "Eidar Dabobe",
        "Eidarr Dabobe"
    ],
    "wof:name":"Eidarr Dabobe",
    "wof:placetype":"locality"
},
  "geometry": {"coordinates":[43.55,4.35],"type":"Point"}
}