{
  "type": "Feature",
  "properties": {
    "gn:admin1_code":"04",
    "gn:asciiname":"Godobay",
    "gn:country_code":"SO",
    "gn:dem":209,
    "gn:feature_class":"P",
    "gn:feature_code":"PPL",
    "gn:name":"Godobay",
    "gn:population":0,
    "gn:timezone":"Africa/Mogadishu",
    "iso:country":"SO",
    "name:som_x_preferred":[
        "Godobay"
    ],
    "name:und_x_variant":[
        "Godovei",
        "Godobay"
    ],
    "wof:name":"Godobay",
    "wof:placetype":"locality"
},
  "geometry": {"coordinates":[44.0687,2.86339],"type":"Point"}
}