{
  "type": "Feature",
  "properties": {
    "gn:admin1_code":"14.0",
    "gn:asciiname":"Ubbuli",
    "gn:country_code":"SO",
    "gn:dem":101,
    "gn:feature_class":"P",
    "gn:feature_code":"PPL",
    "gn:name":"Ubbuli",
    "gn:population":0,
    "gn:timezone":"Africa/Mogadishu",
    "iso:country":"SO",
    "name:som_x_preferred":[
        "Ubbuli"
    ],
    "wof:name":"Ubbuli",
    "wof:placetype":"locality"
},
  "geometry": {"coordinates":[45.18429,2.78919],"type":"Point"}
}