{
  "type": "Feature",
  "properties": {
    "gn:admin1_code":"04",
    "gn:asciiname":"Adegow",
    "gn:country_code":"SO",
    "gn:dem":439,
    "gn:feature_class":"P",
    "gn:feature_code":"PPL",
    "gn:name":"Adegow",
    "gn:population":0,
    "gn:timezone":"Africa/Mogadishu",
    "iso:country":"SO",
    "name:som_x_preferred":[
        "Adegow"
    ],
    "wof:name":"Adegow",
    "wof:placetype":"locality"
},
  "geometry": {"coordinates":[43.4001,3.4254],"type":"Point"}
}