{
  "type": "Feature",
  "properties": {
    "gn:admin1_code":"13.0",
    "gn:asciiname":"Sakhiiro",
    "gn:country_code":"SO",
    "gn:dem":103,
    "gn:feature_class":"P",
    "gn:feature_code":"PPL",
    "gn:name":"Sakhiiro",
    "gn:population":0,
    "gn:timezone":"Africa/Mogadishu",
    "iso:country":"SO",
    "name:som_x_preferred":[
        "Sakhiiro"
    ],
    "wof:name":"Sakhiiro",
    "wof:placetype":"locality"
},
  "geometry": {"coordinates":[45.6724,2.7574],"type":"Point"}
}