{
  "type": "Feature",
  "properties": {
    "gn:admin1_code":"19",
    "gn:asciiname":"Bixinduule",
    "gn:country_code":"SO",
    "gn:dem":576,
    "gn:feature_class":"P",
    "gn:feature_code":"PPL",
    "gn:name":"Bixinduule",
    "gn:population":0,
    "gn:timezone":"Africa/Mogadishu",
    "iso:country":"SO",
    "name:som_x_preferred":[
        "Bixinduule"
    ],
    "wof:name":"Bixinduule",
    "wof:placetype":"locality"
},
  "geometry": {"coordinates":[45.10599000000001,10.16139],"type":"Point"}
}