{
  "type": "Feature",
  "properties": {
    "gn:admin1_code":"20",
    "gn:asciiname":"Daragodle",
    "gn:country_code":"SO",
    "gn:dem":467,
    "gn:feature_class":"P",
    "gn:feature_code":"PPL",
    "gn:name":"Daragodle",
    "gn:population":0,
    "gn:timezone":"Africa/Mogadishu",
    "iso:country":"SO",
    "name:som_x_preferred":[
        "Daragodle"
    ],
    "name:und_x_variant":[
        "Daragoldeh"
    ],
    "wof:name":"Daragodle",
    "wof:placetype":"locality"
},
  "geometry": {"coordinates":[44.84802,10.17068],"type":"Point"}
}