{
  "type": "Feature",
  "properties": {
    "gn:admin1_code":"14",
    "gn:asciiname":"Buulo Kuraari",
    "gn:country_code":"SO",
    "gn:dem":88,
    "gn:feature_class":"P",
    "gn:feature_code":"PPL",
    "gn:name":"Buulo Kuraari",
    "gn:population":0,
    "gn:timezone":"Africa/Mogadishu",
    "iso:country":"SO",
    "name:som_x_preferred":[
        "Buulo Kuraari"
    ],
    "name:und_x_variant":[
        "Curare",
        "Buulo Kuraari"
    ],
    "wof:name":"Buulo Kuraari",
    "wof:placetype":"locality"
},
  "geometry": {"coordinates":[45.1717,2.1616],"type":"Point"}
}