{
  "type": "Feature",
  "properties": {
    "gn:admin1_code":"13.0",
    "gn:asciiname":"Raqayle",
    "gn:country_code":"SO",
    "gn:dem":110,
    "gn:feature_class":"P",
    "gn:feature_code":"PPL",
    "gn:name":"Raqayle",
    "gn:population":0,
    "gn:timezone":"Africa/Mogadishu",
    "iso:country":"SO",
    "name:som_x_preferred":[
        "Raqayle"
    ],
    "wof:name":"Raqayle",
    "wof:placetype":"locality"
},
  "geometry": {"coordinates":[45.5175,2.7065],"type":"Point"}
}