{
  "type": "Feature",
  "properties": {
    "gn:admin1_code":"04",
    "gn:asciiname":"Garba Dheer",
    "gn:country_code":"SO",
    "gn:dem":181,
    "gn:feature_class":"P",
    "gn:feature_code":"PPL",
    "gn:name":"Garba Dheer",
    "gn:population":0,
    "gn:timezone":"Africa/Mogadishu",
    "iso:country":"SO",
    "name:som_x_preferred":[
        "Garba Dheer"
    ],
    "wof:name":"Garba Dheer",
    "wof:placetype":"locality"
},
  "geometry": {"coordinates":[44.01884,2.60792],"type":"Point"}
}