{
  "type": "Feature",
  "properties": {
    "gn:admin1_code":"03",
    "gn:asciiname":"Balli Scillin",
    "gn:country_code":"SO",
    "gn:dem":397,
    "gn:feature_class":"P",
    "gn:feature_code":"PPL",
    "gn:name":"Balli Scillin",
    "gn:population":0,
    "gn:timezone":"Africa/Mogadishu",
    "iso:country":"SO",
    "wof:name":"Balli Scillin",
    "wof:placetype":"locality"
},
  "geometry": {"coordinates":[50.05,8.65],"type":"Point"}
}