{
  "type": "Feature",
  "properties": {
    "gn:admin1_code":"08",
    "gn:asciiname":"Bandar Jadiid",
    "gn:country_code":"SO",
    "gn:dem":16,
    "gn:feature_class":"P",
    "gn:feature_code":"PPL",
    "gn:name":"Bandar Jadiid",
    "gn:population":0,
    "gn:timezone":"Africa/Mogadishu",
    "iso:country":"SO",
    "wof:name":"Bandar Jadiid",
    "wof:placetype":"locality"
},
  "geometry": {"coordinates":[42.74564,0.32129],"type":"Point"}
}