{
  "type": "Feature",
  "properties": {
    "gn:admin1_code":"14",
    "gn:asciiname":"Garas Moqorrey",
    "gn:country_code":"SO",
    "gn:dem":100,
    "gn:feature_class":"P",
    "gn:feature_code":"PPL",
    "gn:name":"Garas Moqorrey",
    "gn:population":0,
    "gn:timezone":"Africa/Mogadishu",
    "iso:country":"SO",
    "name:som_x_preferred":[
        "Garas Moqorrey"
    ],
    "wof:name":"Garas Moqorrey",
    "wof:placetype":"locality"
},
  "geometry": {"coordinates":[45.1444,2.7936],"type":"Point"}
}