{
  "type": "Feature",
  "properties": {
    "gn:admin1_code":"12",
    "gn:asciiname":"Hiil Buraan",
    "gn:country_code":"SO",
    "gn:dem":1061,
    "gn:feature_class":"P",
    "gn:feature_code":"PPL",
    "gn:name":"Hiil Buraan",
    "gn:population":0,
    "gn:timezone":"Africa/Mogadishu",
    "iso:country":"SO",
    "wof:name":"Hiil Buraan",
    "wof:placetype":"locality"
},
  "geometry": {"coordinates":[48.69786,10.21173],"type":"Point"}
}