{
  "type": "Feature",
  "properties": {
    "gn:admin1_code":"03",
    "gn:asciiname":"Bio Gudud",
    "gn:country_code":"SO",
    "gn:dem":805,
    "gn:feature_class":"P",
    "gn:feature_code":"PPL",
    "gn:name":"Bio Gudud",
    "gn:population":0,
    "gn:timezone":"Africa/Mogadishu",
    "iso:country":"SO",
    "wof:name":"Bio Gudud",
    "wof:placetype":"locality"
},
  "geometry": {"coordinates":[49.53333,9.95],"type":"Point"}
}