{
  "type": "Feature",
  "properties": {
    "gn:admin1_code":"4.0",
    "gn:asciiname":"Orostolo",
    "gn:country_code":"SO",
    "gn:dem":189,
    "gn:feature_class":"P",
    "gn:feature_code":"PPL",
    "gn:name":"Orostolo",
    "gn:population":0,
    "gn:timezone":"Africa/Mogadishu",
    "iso:country":"SO",
    "name:som_x_preferred":[
        "Orostolo"
    ],
    "wof:name":"Orostolo",
    "wof:placetype":"locality"
},
  "geometry": {"coordinates":[44.21404,2.80909],"type":"Point"}
}