{
  "type": "Feature",
  "properties": {
    "gn:admin1_code":"03",
    "gn:asciiname":"Buur Gaaban",
    "gn:country_code":"SO",
    "gn:dem":5,
    "gn:feature_class":"P",
    "gn:feature_code":"PPL",
    "gn:name":"Buur Gaaban",
    "gn:population":0,
    "gn:timezone":"Africa/Mogadishu",
    "iso:country":"SO",
    "name:som_x_preferred":[
        "Buur Gaaban"
    ],
    "name:und_x_variant":[
        "Bur Gaban"
    ],
    "wof:name":"Buur Gaaban",
    "wof:placetype":"locality"
},
  "geometry": {"coordinates":[49.46934,11.36116],"type":"Point"}
}