{
  "type": "Feature",
  "properties": {
    "gn:admin1_code":"03",
    "gn:asciiname":"Cajin",
    "gn:country_code":"SO",
    "gn:dem":360,
    "gn:feature_class":"P",
    "gn:feature_code":"PPL",
    "gn:name":"Cajin",
    "gn:population":0,
    "gn:timezone":"Africa/Mogadishu",
    "iso:country":"SO",
    "name:und_x_variant":[
        "\u2018Ajin",
        "Agin",
        "Cajin"
    ],
    "wof:name":"Cajin",
    "wof:placetype":"locality"
},
  "geometry": {"coordinates":[49.88333,8.41667],"type":"Point"}
}