{
  "type": "Feature",
  "properties": {
    "gn:admin1_code":"04",
    "gn:asciiname":"Gorey",
    "gn:country_code":"SO",
    "gn:dem":495,
    "gn:feature_class":"P",
    "gn:feature_code":"PPLL",
    "gn:name":"Gorey",
    "gn:population":0,
    "gn:timezone":"Africa/Mogadishu",
    "iso:country":"SO",
    "name:bul_x_preferred":[
        "\u0413\u043e\u0440\u0438"
    ],
    "name:cat_x_preferred":[
        "Gorey"
    ],
    "name:ceb_x_preferred":[
        "Gorey"
    ],
    "name:dan_x_preferred":[
        "Gorey"
    ],
    "name:deu_x_preferred":[
        "Gorey"
    ],
    "name:epo_x_preferred":[
        "Gorey"
    ],
    "name:eus_x_preferred":[
        "Gorey"
    ],
    "name:fra_x_preferred":[
        "Gorey"
    ],
    "name:gle_x_preferred":[
        "Guaire"
    ],
    "name:ind_x_preferred":[
        "Gorey"
    ],
    "name:ita_x_preferred":[
        "Gorey"
    ],
    "name:kat_x_preferred":[
        "\u10d2\u10dd\u10e0\u10d8"
    ],
    "name:nld_x_preferred":[
        "Gorey"
    ],
    "name:nor_x_preferred":[
        "Gorey"
    ],
    "name:pol_x_preferred":[
        "Gorey"
    ],
    "name:rus_x_preferred":[
        "\u0413\u043e\u0440\u0438"
    ],
    "name:som_x_preferred":[
        "Gorey"
    ],
    "name:spa_x_preferred":[
        "Gorey"
    ],
    "name:srp_x_preferred":[
        "\u0413\u043e\u0440\u0438"
    ],
    "name:swe_x_preferred":[
        "Gorey"
    ],
    "name:und_x_variant":[
        "Ori",
        "Gorey"
    ],
    "name:urd_x_preferred":[
        "\u06af\u0624\u0631\u06cc"
    ],
    "wof:name":"Gorey",
    "wof:placetype":"locality"
},
  "geometry": {"coordinates":[43.6287,3.2169],"type":"Point"}
}