{
  "type": "Feature",
  "properties": {
    "gn:admin1_code":"12.0",
    "gn:asciiname":"Waaciye",
    "gn:country_code":"SO",
    "gn:dem":932,
    "gn:feature_class":"P",
    "gn:feature_code":"PPL",
    "gn:name":"Waaciye",
    "gn:population":0,
    "gn:timezone":"Africa/Mogadishu",
    "iso:country":"SO",
    "name:som_x_preferred":[
        "Waaciye"
    ],
    "name:und_x_variant":[
        "Uahie",
        "Waaciye"
    ],
    "wof:name":"Waaciye",
    "wof:placetype":"locality"
},
  "geometry": {"coordinates":[49.04422,10.01139],"type":"Point"}
}