{
  "type": "Feature",
  "properties": {
    "gn:admin1_code":"09",
    "gn:asciiname":"Dubri",
    "gn:country_code":"SO",
    "gn:dem":55,
    "gn:feature_class":"P",
    "gn:feature_code":"PPL",
    "gn:name":"Dubri",
    "gn:population":0,
    "gn:timezone":"Africa/Mogadishu",
    "iso:country":"SO",
    "wof:name":"Dubri",
    "wof:placetype":"locality"
},
  "geometry": {"coordinates":[41.21667,-0.31667],"type":"Point"}
}