{
  "type": "Feature",
  "properties": {
    "gn:admin1_code":"05",
    "gn:asciiname":"El Avor",
    "gn:country_code":"SO",
    "gn:dem":408,
    "gn:feature_class":"P",
    "gn:feature_code":"PPL",
    "gn:name":"El Avor",
    "gn:population":0,
    "gn:timezone":"Africa/Mogadishu",
    "iso:country":"SO",
    "wof:name":"El Avor",
    "wof:placetype":"locality"
},
  "geometry": {"coordinates":[45.58333,5.38333],"type":"Point"}
}