{
  "type": "Feature",
  "properties": {
    "gn:admin1_code":"20",
    "gn:asciiname":"Darburruk",
    "gn:country_code":"SO",
    "gn:dem":1208,
    "gn:feature_class":"P",
    "gn:feature_code":"PPL",
    "gn:name":"Darburruk",
    "gn:population":0,
    "gn:timezone":"Africa/Mogadishu",
    "iso:country":"SO",
    "wof:name":"Darburruk",
    "wof:placetype":"locality"
},
  "geometry": {"coordinates":[44.51667,9.73333],"type":"Point"}
}