{
  "type": "Feature",
  "properties": {
    "gn:admin1_code":"22",
    "gn:asciiname":"Jable",
    "gn:country_code":"SO",
    "gn:dem":1181,
    "gn:feature_class":"P",
    "gn:feature_code":"PPL",
    "gn:name":"Jable",
    "gn:population":0,
    "gn:timezone":"Africa/Mogadishu",
    "iso:country":"SO",
    "name:som_x_preferred":[
        "Jable"
    ],
    "wof:name":"Jable",
    "wof:placetype":"locality"
},
  "geometry": {"coordinates":[46.10918,9.97514],"type":"Point"}
}