{
  "type": "Feature",
  "properties": {
    "gn:admin1_code":"04",
    "gn:asciiname":"Dodole",
    "gn:country_code":"SO",
    "gn:dem":200,
    "gn:feature_class":"P",
    "gn:feature_code":"PPL",
    "gn:name":"Dodole",
    "gn:population":0,
    "gn:timezone":"Africa/Mogadishu",
    "iso:country":"SO",
    "name:som_x_preferred":[
        "Dodole"
    ],
    "name:und_x_variant":[
        "Dodol"
    ],
    "wof:name":"Dodole",
    "wof:placetype":"locality"
},
  "geometry": {"coordinates":[43.56876,2.31949],"type":"Point"}
}