{
  "type": "Feature",
  "properties": {
    "gn:admin1_code":"04",
    "gn:asciiname":"Hoogey",
    "gn:country_code":"SO",
    "gn:dem":210,
    "gn:feature_class":"P",
    "gn:feature_code":"PPLL",
    "gn:name":"Hoogey",
    "gn:population":0,
    "gn:timezone":"Africa/Mogadishu",
    "iso:country":"SO",
    "name:som_x_preferred":[
        "Hoogey"
    ],
    "name:und_x_variant":[
        "Hoghei",
        "Hoogey"
    ],
    "wof:name":"Hoogey",
    "wof:placetype":"locality"
},
  "geometry": {"coordinates":[44.23094,2.90928],"type":"Point"}
}