{
  "type": "Feature",
  "properties": {
    "gn:admin1_code":"07",
    "gn:asciiname":"El Edat",
    "gn:country_code":"SO",
    "gn:dem":288,
    "gn:feature_class":"P",
    "gn:feature_code":"PPL",
    "gn:name":"El Edat",
    "gn:population":0,
    "gn:timezone":"Africa/Mogadishu",
    "iso:country":"SO",
    "wof:name":"El Edat",
    "wof:placetype":"locality"
},
  "geometry": {"coordinates":[44.91942,4.7053],"type":"Point"}
}