{
  "type": "Feature",
  "properties": {
    "gn:admin1_code":"04",
    "gn:asciiname":"Biyooley",
    "gn:country_code":"SO",
    "gn:dem":223,
    "gn:feature_class":"P",
    "gn:feature_code":"PPL",
    "gn:name":"Biyooley",
    "gn:population":0,
    "gn:timezone":"Africa/Mogadishu",
    "iso:country":"SO",
    "name:som_x_preferred":[
        "Biyooley"
    ],
    "wof:name":"Biyooley",
    "wof:placetype":"locality"
},
  "geometry": {"coordinates":[44.23391,2.95788],"type":"Point"}
}