{
  "type": "Feature",
  "properties": {
    "gn:admin1_code":"14",
    "gn:asciiname":"Banyaale",
    "gn:country_code":"SO",
    "gn:dem":92,
    "gn:feature_class":"P",
    "gn:feature_code":"PPL",
    "gn:name":"Banyaale",
    "gn:population":0,
    "gn:timezone":"Africa/Mogadishu",
    "iso:country":"SO",
    "name:som_x_preferred":[
        "Banyaale"
    ],
    "wof:name":"Banyaale",
    "wof:placetype":"locality"
},
  "geometry": {"coordinates":[45.14454,2.45257],"type":"Point"}
}