{
  "type": "Feature",
  "properties": {
    "gn:admin1_code":"14",
    "gn:asciiname":"Gubi Coude",
    "gn:cc2":"SO",
    "gn:country_code":"SO",
    "gn:dem":61,
    "gn:feature_class":"P",
    "gn:feature_code":"PPL",
    "gn:name":"Gubi Coude",
    "gn:population":0,
    "gn:timezone":"Africa/Mogadishu",
    "iso:country":"SO",
    "name:und_x_variant":[
        "Cubi Coude",
        "Gubet",
        "Gubi Coude"
    ],
    "wof:name":"Gubi Coude",
    "wof:placetype":"locality"
},
  "geometry": {"coordinates":[43.55,1.55],"type":"Point"}
}