{
  "type": "Feature",
  "properties": {
    "gn:admin1_code":"14.0",
    "gn:asciiname":"Teesiyow",
    "gn:country_code":"SO",
    "gn:dem":68,
    "gn:feature_class":"P",
    "gn:feature_code":"PPL",
    "gn:name":"Teesiyow",
    "gn:population":0,
    "gn:timezone":"Africa/Mogadishu",
    "iso:country":"SO",
    "name:som_x_preferred":[
        "Teesiyow"
    ],
    "wof:name":"Teesiyow",
    "wof:placetype":"locality"
},
  "geometry": {"coordinates":[44.5988,1.6828],"type":"Point"}
}