{
  "type": "Feature",
  "properties": {
    "gn:admin1_code":"08",
    "gn:asciiname":"Galaame",
    "gn:country_code":"SO",
    "gn:dem":25,
    "gn:feature_class":"P",
    "gn:feature_code":"PPL",
    "gn:name":"Galaame",
    "gn:population":0,
    "gn:timezone":"Africa/Mogadishu",
    "iso:country":"SO",
    "wof:name":"Galaame",
    "wof:placetype":"locality"
},
  "geometry": {"coordinates":[42.69004,0.58188],"type":"Point"}
}