{
  "type": "Feature",
  "properties": {
    "gn:admin1_code":"4.0",
    "gn:asciiname":"Lo Gaduud",
    "gn:country_code":"SO",
    "gn:dem":315,
    "gn:feature_class":"P",
    "gn:feature_code":"PPL",
    "gn:name":"Lo Gaduud",
    "gn:population":0,
    "gn:timezone":"Africa/Mogadishu",
    "iso:country":"SO",
    "name:som_x_preferred":[
        "Lo Gaduud"
    ],
    "wof:name":"Lo Gaduud",
    "wof:placetype":"locality"
},
  "geometry": {"coordinates":[43.69187,2.94883],"type":"Point"}
}