{
  "type": "Feature",
  "properties": {
    "gn:admin1_code":"14",
    "gn:asciiname":"Doon Yare",
    "gn:country_code":"SO",
    "gn:dem":86,
    "gn:feature_class":"P",
    "gn:feature_code":"PPL",
    "gn:name":"Doon Yare",
    "gn:population":0,
    "gn:timezone":"Africa/Mogadishu",
    "iso:country":"SO",
    "name:som_x_preferred":[
        "Doon Yare"
    ],
    "wof:name":"Doon Yare",
    "wof:placetype":"locality"
},
  "geometry": {"coordinates":[45.1055,2.263],"type":"Point"}
}