{
  "type": "Feature",
  "properties": {
    "gn:admin1_code":"04",
    "gn:asciiname":"Danab Qoy",
    "gn:country_code":"SO",
    "gn:dem":215,
    "gn:feature_class":"P",
    "gn:feature_code":"PPL",
    "gn:name":"Danab Qoy",
    "gn:population":0,
    "gn:timezone":"Africa/Mogadishu",
    "iso:country":"SO",
    "name:som_x_preferred":[
        "Danab Qoy"
    ],
    "wof:name":"Danab Qoy",
    "wof:placetype":"locality"
},
  "geometry": {"coordinates":[43.93064,2.72737],"type":"Point"}
}