{
  "type": "Feature",
  "properties": {
    "gn:admin1_code":"14.0",
    "gn:asciiname":"Uacavo Bilal",
    "gn:country_code":"SO",
    "gn:dem":52,
    "gn:feature_class":"P",
    "gn:feature_code":"PPL",
    "gn:name":"Uacavo Bilal",
    "gn:population":0,
    "gn:timezone":"Africa/Mogadishu",
    "iso:country":"SO",
    "wof:name":"Uacavo Bilal",
    "wof:placetype":"locality"
},
  "geometry": {"coordinates":[43.75,0.95],"type":"Point"}
}