{
  "type": "Feature",
  "properties": {
    "gn:admin1_code":"14",
    "gn:asciiname":"Aw Dheegle",
    "gn:country_code":"SO",
    "gn:dem":77,
    "gn:feature_class":"P",
    "gn:feature_code":"PPL",
    "gn:name":"Aw Dheegle",
    "gn:population":0,
    "gn:timezone":"Africa/Mogadishu",
    "iso:country":"SO",
    "name:som_x_preferred":[
        "Aw Dheegle"
    ],
    "name:und_x_variant":[
        "Audegle"
    ],
    "wof:name":"Aw Dheegle",
    "wof:placetype":"locality"
},
  "geometry": {"coordinates":[44.83249,1.97753],"type":"Point"}
}