{
  "type": "Feature",
  "properties": {
    "gn:admin1_code":"8.0",
    "gn:asciiname":"Wagadey",
    "gn:country_code":"SO",
    "gn:dem":34,
    "gn:feature_class":"P",
    "gn:feature_code":"PPL",
    "gn:name":"Wagadey",
    "gn:population":0,
    "gn:timezone":"Africa/Mogadishu",
    "iso:country":"SO",
    "name:und_x_variant":[
        "Uagadi",
        "Wagadey"
    ],
    "wof:name":"Wagadey",
    "wof:placetype":"locality"
},
  "geometry": {"coordinates":[42.70574000000001,0.68371],"type":"Point"}
}