{
  "type": "Feature",
  "properties": {
    "gn:admin1_code":"01",
    "gn:asciiname":"Hobinshe",
    "gn:country_code":"SO",
    "gn:dem":464,
    "gn:feature_class":"P",
    "gn:feature_code":"PPLL",
    "gn:name":"Hobinshe",
    "gn:population":0,
    "gn:timezone":"Africa/Mogadishu",
    "iso:country":"SO",
    "name:som_x_preferred":[
        "Hobinshe"
    ],
    "wof:name":"Hobinshe",
    "wof:placetype":"locality"
},
  "geometry": {"coordinates":[44.3095,3.9173],"type":"Point"}
}