{
  "type": "Feature",
  "properties": {
    "gn:admin1_code":"06",
    "gn:asciiname":"Ceel Dheere",
    "gn:country_code":"SO",
    "gn:dem":370,
    "gn:feature_class":"P",
    "gn:feature_code":"PPL",
    "gn:name":"Ceel Dheere",
    "gn:population":0,
    "gn:timezone":"Africa/Mogadishu",
    "iso:country":"SO",
    "name:som_x_preferred":[
        "Ceel Dheere"
    ],
    "wof:name":"Ceel Dheere",
    "wof:placetype":"locality"
},
  "geometry": {"coordinates":[43.0714,3.28693],"type":"Point"}
}