{
  "type": "Feature",
  "properties": {
    "gn:admin1_code":"14",
    "gn:asciiname":"Ibrahim Haafo",
    "gn:country_code":"SO",
    "gn:dem":51,
    "gn:feature_class":"P",
    "gn:feature_code":"PPLL",
    "gn:name":"Ibrahim Haafo",
    "gn:population":0,
    "gn:timezone":"Africa/Mogadishu",
    "iso:country":"SO",
    "name:som_x_preferred":[
        "Ibrahim Haafo"
    ],
    "wof:name":"Ibrahim Haafo",
    "wof:placetype":"locality"
},
  "geometry": {"coordinates":[43.9503,1.4383],"type":"Point"}
}