{
  "type": "Feature",
  "properties": {
    "gn:admin1_code":"9.0",
    "gn:asciiname":"Meama",
    "gn:country_code":"SO",
    "gn:dem":15,
    "gn:feature_class":"P",
    "gn:feature_code":"PPL",
    "gn:name":"Meama",
    "gn:population":0,
    "gn:timezone":"Africa/Mogadishu",
    "iso:country":"SO",
    "wof:name":"Meama",
    "wof:placetype":"locality"
},
  "geometry": {"coordinates":[42.76667,0.26667],"type":"Point"}
}