{
  "type": "Feature",
  "properties": {
    "gn:admin1_code":"08",
    "gn:asciiname":"Dhokay",
    "gn:country_code":"SO",
    "gn:dem":70,
    "gn:feature_class":"P",
    "gn:feature_code":"PPL",
    "gn:name":"Dhokay",
    "gn:population":0,
    "gn:timezone":"Africa/Mogadishu",
    "iso:country":"SO",
    "wof:name":"Dhokay",
    "wof:placetype":"locality"
},
  "geometry": {"coordinates":[42.39001,1.67051],"type":"Point"}
}