{
  "type": "Feature",
  "properties": {
    "gn:admin1_code":"20.0",
    "gn:asciiname":"Sanlaawaha",
    "gn:country_code":"SO",
    "gn:dem":1582,
    "gn:feature_class":"P",
    "gn:feature_code":"PPLL",
    "gn:name":"Sanlaawaha",
    "gn:population":0,
    "gn:timezone":"Africa/Mogadishu",
    "iso:country":"SO",
    "wof:name":"Sanlaawaha",
    "wof:placetype":"locality"
},
  "geometry": {"coordinates":[43.52266,9.67524],"type":"Point"}
}