{
  "type": "Feature",
  "properties": {
    "gn:admin1_code":"01",
    "gn:asciiname":"Garas Weyne",
    "gn:country_code":"SO",
    "gn:dem":457,
    "gn:feature_class":"P",
    "gn:feature_code":"PPL",
    "gn:name":"Garas Weyne",
    "gn:population":0,
    "gn:timezone":"Africa/Mogadishu",
    "iso:country":"SO",
    "name:som_x_preferred":[
        "Garas Weyne"
    ],
    "wof:name":"Garas Weyne",
    "wof:placetype":"locality"
},
  "geometry": {"coordinates":[43.484,4.2642],"type":"Point"}
}