{
  "type": "Feature",
  "properties": {
    "gn:admin1_code":"03",
    "gn:asciiname":"Fangarar",
    "gn:country_code":"SO",
    "gn:dem":284,
    "gn:feature_class":"P",
    "gn:feature_code":"PPL",
    "gn:name":"Fangarar",
    "gn:population":0,
    "gn:timezone":"Africa/Mogadishu",
    "iso:country":"SO",
    "wof:name":"Fangarar",
    "wof:placetype":"locality"
},
  "geometry": {"coordinates":[49.66667,11.45],"type":"Point"}
}