{
  "type": "Feature",
  "properties": {
    "gn:admin1_code":"12.0",
    "gn:asciiname":"Gal Shiikh",
    "gn:country_code":"SO",
    "gn:dem":1258,
    "gn:feature_class":"P",
    "gn:feature_code":"PPL",
    "gn:name":"Gal Shiikh",
    "gn:population":0,
    "gn:timezone":"Africa/Mogadishu",
    "iso:country":"SO",
    "name:som_x_preferred":[
        "Gal Shiikh"
    ],
    "name:und_x_variant":[
        "Kalsheik",
        "Kal Sheihk",
        "Kalsheikh",
        "Gal Shiikh"
    ],
    "wof:name":"Gal Shiikh",
    "wof:placetype":"locality"
},
  "geometry": {"coordinates":[47.2052,10.0679],"type":"Point"}
}