{
  "type": "Feature",
  "properties": {
    "gn:admin1_code":"03",
    "gn:asciiname":"Ceel Carab",
    "gn:cc2":"SO",
    "gn:country_code":"SO",
    "gn:dem":37,
    "gn:feature_class":"P",
    "gn:feature_code":"PPL",
    "gn:name":"Ceel Carab",
    "gn:population":0,
    "gn:timezone":"Africa/Mogadishu",
    "iso:country":"SO",
    "name:und_x_variant":[
        "El Arab",
        "Ceel Carab"
    ],
    "wof:name":"Ceel Carab",
    "wof:placetype":"locality"
},
  "geometry": {"coordinates":[50.56667,11.73333],"type":"Point"}
}