{
  "type": "Feature",
  "properties": {
    "gn:admin1_code":"04",
    "gn:asciiname":"Galool Oomane",
    "gn:country_code":"SO",
    "gn:dem":220,
    "gn:feature_class":"P",
    "gn:feature_code":"PPL",
    "gn:name":"Galool Oomane",
    "gn:population":0,
    "gn:timezone":"Africa/Mogadishu",
    "iso:country":"SO",
    "name:som_x_preferred":[
        "Galool Oomane"
    ],
    "wof:name":"Galool Oomane",
    "wof:placetype":"locality"
},
  "geometry": {"coordinates":[44.28629,2.95459],"type":"Point"}
}