{
  "type": "Feature",
  "properties": {
    "gn:admin1_code":"6.0",
    "gn:asciiname":"Toorey",
    "gn:country_code":"SO",
    "gn:dem":135,
    "gn:feature_class":"P",
    "gn:feature_code":"PPL",
    "gn:name":"Toorey",
    "gn:population":0,
    "gn:timezone":"Africa/Mogadishu",
    "iso:country":"SO",
    "wof:name":"Toorey",
    "wof:placetype":"locality"
},
  "geometry": {"coordinates":[42.35524,2.25947],"type":"Point"}
}