{
  "type": "Feature",
  "properties": {
    "gn:admin1_code":"10.0",
    "gn:asciiname":"Qaidarre",
    "gn:cc2":"SO",
    "gn:country_code":"SO",
    "gn:dem":154,
    "gn:feature_class":"P",
    "gn:feature_code":"PPL",
    "gn:name":"Qaidarre",
    "gn:population":0,
    "gn:timezone":"Africa/Mogadishu",
    "iso:country":"SO",
    "name:und_x_variant":[
        "Gaider\u00f2",
        "Qaidarre"
    ],
    "wof:name":"Qaidarre",
    "wof:placetype":"locality"
},
  "geometry": {"coordinates":[48.31667,6.75],"type":"Point"}
}