{
  "type": "Feature",
  "properties": {
    "gn:admin1_code":"13",
    "gn:asciiname":"Bulo Sehia",
    "gn:country_code":"SO",
    "gn:dem":108,
    "gn:feature_class":"P",
    "gn:feature_code":"PPL",
    "gn:name":"Bulo Sehia",
    "gn:population":0,
    "gn:timezone":"Africa/Mogadishu",
    "iso:country":"SO",
    "wof:name":"Bulo Sehia",
    "wof:placetype":"locality"
},
  "geometry": {"coordinates":[45.56667,2.91667],"type":"Point"}
}