{
  "type": "Feature",
  "properties": {
    "gn:admin1_code":"19",
    "gn:asciiname":"Haqayo Malaasle",
    "gn:country_code":"SO",
    "gn:dem":1281,
    "gn:feature_class":"P",
    "gn:feature_code":"PPL",
    "gn:name":"Haqayo Malaasle",
    "gn:population":0,
    "gn:timezone":"Africa/Mogadishu",
    "iso:country":"SO",
    "name:som_x_preferred":[
        "Haqayo Malaasle"
    ],
    "name:und_x_variant":[
        "Haqi Malasleh"
    ],
    "wof:name":"Haqayo Malaasle",
    "wof:placetype":"locality"
},
  "geometry": {"coordinates":[45.12748,9.6205],"type":"Point"}
}