{
  "type": "Feature",
  "properties": {
    "gn:admin1_code":"13.0",
    "gn:asciiname":"Makaraan Muudey",
    "gn:country_code":"SO",
    "gn:dem":105,
    "gn:feature_class":"P",
    "gn:feature_code":"PPL",
    "gn:name":"Makaraan Muudey",
    "gn:population":0,
    "gn:timezone":"Africa/Mogadishu",
    "iso:country":"SO",
    "name:som_x_preferred":[
        "Makaraan Muudey"
    ],
    "wof:name":"Makaraan Muudey",
    "wof:placetype":"locality"
},
  "geometry": {"coordinates":[45.6075,2.716],"type":"Point"}
}