{
  "type": "Feature",
  "properties": {
    "gn:admin1_code":"03",
    "gn:asciiname":"El Harre",
    "gn:country_code":"SO",
    "gn:dem":741,
    "gn:feature_class":"P",
    "gn:feature_code":"PPL",
    "gn:name":"El Harre",
    "gn:population":0,
    "gn:timezone":"Africa/Mogadishu",
    "iso:country":"SO",
    "wof:name":"El Harre",
    "wof:placetype":"locality"
},
  "geometry": {"coordinates":[49.08333,9.61667],"type":"Point"}
}