{
  "type": "Feature",
  "properties": {
    "gn:admin1_code":"04",
    "gn:asciiname":"Bulo Gasei",
    "gn:cc2":"SO",
    "gn:country_code":"SO",
    "gn:dem":292,
    "gn:feature_class":"P",
    "gn:feature_code":"PPL",
    "gn:name":"Bulo Gasei",
    "gn:population":0,
    "gn:timezone":"Africa/Mogadishu",
    "iso:country":"SO",
    "wof:name":"Bulo Gasei",
    "wof:placetype":"locality"
},
  "geometry": {"coordinates":[43.81667,2.98333],"type":"Point"}
}