{
  "type": "Feature",
  "properties": {
    "gn:admin1_code":"09",
    "gn:asciiname":"Caw",
    "gn:cc2":"SO",
    "gn:country_code":"SO",
    "gn:dem":49,
    "gn:feature_class":"P",
    "gn:feature_code":"PPL",
    "gn:name":"Caw",
    "gn:population":0,
    "gn:timezone":"Africa/Mogadishu",
    "iso:country":"SO",
    "name:und_x_variant":[
        "Au",
        "Caw"
    ],
    "wof:name":"Caw",
    "wof:placetype":"locality"
},
  "geometry": {"coordinates":[41.41667,0.55],"type":"Point"}
}