{
  "type": "Feature",
  "properties": {
    "gn:admin1_code":"09",
    "gn:asciiname":"Beey",
    "gn:country_code":"SO",
    "gn:dem":5,
    "gn:feature_class":"P",
    "gn:feature_code":"PPL",
    "gn:name":"Beey",
    "gn:population":0,
    "gn:timezone":"Africa/Mogadishu",
    "iso:country":"SO",
    "wof:name":"Beey",
    "wof:placetype":"locality"
},
  "geometry": {"coordinates":[42.72101,-0.06238],"type":"Point"}
}