{
  "type": "Feature",
  "properties": {
    "gn:admin1_code":"14.0",
    "gn:asciiname":"Lugnale",
    "gn:country_code":"SO",
    "gn:dem":49,
    "gn:feature_class":"P",
    "gn:feature_code":"PPL",
    "gn:name":"Lugnale",
    "gn:population":0,
    "gn:timezone":"Africa/Mogadishu",
    "iso:country":"SO",
    "wof:name":"Lugnale",
    "wof:placetype":"locality"
},
  "geometry": {"coordinates":[43.86667,1.21667],"type":"Point"}
}