{
  "type": "Feature",
  "properties": {
    "gn:admin1_code":"4.0",
    "gn:asciiname":"Miidaay",
    "gn:country_code":"SO",
    "gn:dem":480,
    "gn:feature_class":"P",
    "gn:feature_code":"PPLL",
    "gn:name":"Miidaay",
    "gn:population":0,
    "gn:timezone":"Africa/Mogadishu",
    "iso:country":"SO",
    "name:som_x_preferred":[
        "Miidaay"
    ],
    "name:und_x_variant":[
        "Bulo Moddei"
    ],
    "wof:name":"Miidaay",
    "wof:placetype":"locality"
},
  "geometry": {"coordinates":[43.514,3.0359],"type":"Point"}
}