{
  "type": "Feature",
  "properties": {
    "gn:admin1_code":"08",
    "gn:asciiname":"Anduuma",
    "gn:country_code":"SO",
    "gn:dem":32,
    "gn:feature_class":"P",
    "gn:feature_code":"PPL",
    "gn:name":"Anduuma",
    "gn:population":0,
    "gn:timezone":"Africa/Mogadishu",
    "iso:country":"SO",
    "name:und_x_variant":[
        "Addom\u00f2",
        "Anduuma"
    ],
    "wof:name":"Anduuma",
    "wof:placetype":"locality"
},
  "geometry": {"coordinates":[42.73773,0.62738],"type":"Point"}
}