{
  "type": "Feature",
  "properties": {
    "gn:admin1_code":"21.0",
    "gn:asciiname":"Xoorey",
    "gn:country_code":"SO",
    "gn:dem":828,
    "gn:feature_class":"P",
    "gn:feature_code":"PPL",
    "gn:name":"Xoorey",
    "gn:population":0,
    "gn:timezone":"Africa/Mogadishu",
    "iso:country":"SO",
    "name:som_x_preferred":[
        "Xoorey"
    ],
    "wof:name":"Xoorey",
    "wof:placetype":"locality"
},
  "geometry": {"coordinates":[43.36742,10.18],"type":"Point"}
}