{
  "type": "Feature",
  "properties": {
    "gn:admin1_code":"12.0",
    "gn:asciiname":"Lo'aneba",
    "gn:country_code":"SO",
    "gn:dem":451,
    "gn:feature_class":"P",
    "gn:feature_code":"PPL",
    "gn:name":"Lo\u2019aneba",
    "gn:population":0,
    "gn:timezone":"Africa/Mogadishu",
    "iso:country":"SO",
    "name:som_x_preferred":[
        "Lo\u2019aneba"
    ],
    "wof:name":"Lo'aneba",
    "wof:placetype":"locality"
},
  "geometry": {"coordinates":[47.1273,10.8009],"type":"Point"}
}