{
  "type": "Feature",
  "properties": {
    "gn:admin1_code":"04",
    "gn:asciiname":"Aw Yaale",
    "gn:country_code":"SO",
    "gn:dem":193,
    "gn:feature_class":"P",
    "gn:feature_code":"PPL",
    "gn:name":"Aw Yaale",
    "gn:population":0,
    "gn:timezone":"Africa/Mogadishu",
    "iso:country":"SO",
    "name:som_x_preferred":[
        "Aw Yaale"
    ],
    "wof:name":"Aw Yaale",
    "wof:placetype":"locality"
},
  "geometry": {"coordinates":[44.2622,2.8547],"type":"Point"}
}