{
  "type": "Feature",
  "properties": {
    "gn:admin1_code":"09",
    "gn:asciiname":"Fiirfiirisa",
    "gn:cc2":"SO",
    "gn:country_code":"SO",
    "gn:dem":26,
    "gn:feature_class":"P",
    "gn:feature_code":"PPL",
    "gn:name":"Fiirfiirisa",
    "gn:population":0,
    "gn:timezone":"Africa/Mogadishu",
    "iso:country":"SO",
    "name:und_x_variant":[
        "Fur Fursa",
        "Fiirfiirisa"
    ],
    "wof:name":"Fiirfiirisa",
    "wof:placetype":"locality"
},
  "geometry": {"coordinates":[41.91028,0.66139],"type":"Point"}
}