{
  "type": "Feature",
  "properties": {
    "gn:admin1_code":"13.0",
    "gn:asciiname":"Qurunlow",
    "gn:country_code":"SO",
    "gn:dem":46,
    "gn:feature_class":"P",
    "gn:feature_code":"PPL",
    "gn:name":"Qurunlow",
    "gn:population":0,
    "gn:timezone":"Africa/Mogadishu",
    "iso:country":"SO",
    "name:som_x_preferred":[
        "Qurunlow"
    ],
    "wof:name":"Qurunlow",
    "wof:placetype":"locality"
},
  "geometry": {"coordinates":[45.7348,2.3523],"type":"Point"}
}