{
  "type": "Feature",
  "properties": {
    "gn:admin1_code":"1.0",
    "gn:asciiname":"Sciaule Ali Mai",
    "gn:country_code":"SO",
    "gn:dem":371,
    "gn:feature_class":"P",
    "gn:feature_code":"PPL",
    "gn:name":"Sciaule Ali Mai",
    "gn:population":0,
    "gn:timezone":"Africa/Mogadishu",
    "iso:country":"SO",
    "name:und_x_variant":[
        "Scianle Ali Mai",
        "Sciaule Ali Mai"
    ],
    "wof:name":"Sciaule Ali Mai",
    "wof:placetype":"locality"
},
  "geometry": {"coordinates":[44.68333,3.73333],"type":"Point"}
}