{
  "type": "Feature",
  "properties": {
    "gn:admin1_code":"08",
    "gn:asciiname":"Kolonyaale",
    "gn:country_code":"SO",
    "gn:dem":23,
    "gn:feature_class":"P",
    "gn:feature_code":"PPL",
    "gn:name":"Kolonyaale",
    "gn:population":0,
    "gn:timezone":"Africa/Mogadishu",
    "iso:country":"SO",
    "wof:name":"Kolonyaale",
    "wof:placetype":"locality"
},
  "geometry": {"coordinates":[42.92556,0.64364],"type":"Point"}
}