{
  "type": "Feature",
  "properties": {
    "gn:admin1_code":"14",
    "gn:asciiname":"Beynax Barre",
    "gn:country_code":"SO",
    "gn:dem":63,
    "gn:feature_class":"P",
    "gn:feature_code":"PPLL",
    "gn:name":"Beynax Barre",
    "gn:population":0,
    "gn:timezone":"Africa/Mogadishu",
    "iso:country":"SO",
    "name:som_x_preferred":[
        "Beynax Barre"
    ],
    "wof:name":"Beynax Barre",
    "wof:placetype":"locality"
},
  "geometry": {"coordinates":[44.5167,1.6022],"type":"Point"}
}