{
  "type": "Feature",
  "properties": {
    "gn:admin1_code":"01",
    "gn:asciiname":"Dugsamey",
    "gn:country_code":"SO",
    "gn:dem":451,
    "gn:feature_class":"P",
    "gn:feature_code":"PPL",
    "gn:name":"Dugsamey",
    "gn:population":0,
    "gn:timezone":"Africa/Mogadishu",
    "iso:country":"SO",
    "wof:name":"Dugsamey",
    "wof:placetype":"locality"
},
  "geometry": {"coordinates":[43.48034000000001,3.70305],"type":"Point"}
}