{
  "type": "Feature",
  "properties": {
    "gn:admin1_code":"05",
    "gn:asciiname":"Gidhees",
    "gn:country_code":"SO",
    "gn:dem":291,
    "gn:feature_class":"P",
    "gn:feature_code":"PPL",
    "gn:name":"Gidhees",
    "gn:population":0,
    "gn:timezone":"Africa/Mogadishu",
    "iso:country":"SO",
    "name:und_x_variant":[
        "Ghedeis",
        "Gidhees"
    ],
    "wof:name":"Gidhees",
    "wof:placetype":"locality"
},
  "geometry": {"coordinates":[46.68158,6.01962],"type":"Point"}
}