{
  "type": "Feature",
  "properties": {
    "gn:admin1_code":"06",
    "gn:asciiname":"Labiileey",
    "gn:country_code":"SO",
    "gn:dem":104,
    "gn:feature_class":"P",
    "gn:feature_code":"PPL",
    "gn:name":"Labiileey",
    "gn:population":0,
    "gn:timezone":"Africa/Mogadishu",
    "iso:country":"SO",
    "wof:name":"Labiileey",
    "wof:placetype":"locality"
},
  "geometry": {"coordinates":[42.30084,2.13384],"type":"Point"}
}