{
  "type": "Feature",
  "properties": {
    "gn:admin1_code":"21",
    "gn:asciiname":"Hadeytaweyne",
    "gn:country_code":"SO",
    "gn:dem":6,
    "gn:feature_class":"P",
    "gn:feature_code":"PPL",
    "gn:name":"Hadeytaweyne",
    "gn:population":0,
    "gn:timezone":"Africa/Mogadishu",
    "iso:country":"SO",
    "name:som_x_preferred":[
        "Hadeytaweyne"
    ],
    "wof:name":"Hadeytaweyne",
    "wof:placetype":"locality"
},
  "geometry": {"coordinates":[44.09238,10.57212],"type":"Point"}
}