{
  "type": "Feature",
  "properties": {
    "gn:admin1_code":"06",
    "gn:asciiname":"Ceel Cad",
    "gn:country_code":"SO",
    "gn:dem":423,
    "gn:feature_class":"P",
    "gn:feature_code":"PPL",
    "gn:name":"Ceel Cad",
    "gn:population":0,
    "gn:timezone":"Africa/Mogadishu",
    "iso:country":"SO",
    "name:som_x_preferred":[
        "Ceel Cad"
    ],
    "wof:name":"Ceel Cad",
    "wof:placetype":"locality"
},
  "geometry": {"coordinates":[41.86744,3.03676],"type":"Point"}
}