{
  "type": "Feature",
  "properties": {
    "gn:admin1_code":"14",
    "gn:asciiname":"Dhegari",
    "gn:country_code":"SO",
    "gn:dem":63,
    "gn:feature_class":"P",
    "gn:feature_code":"PPL",
    "gn:name":"Dhegari",
    "gn:population":0,
    "gn:timezone":"Africa/Mogadishu",
    "iso:country":"SO",
    "name:und_x_variant":[
        "Degh Ari",
        "Deg\u00e1ri",
        "Deg Eri",
        "Dhegari"
    ],
    "wof:name":"Dhegari",
    "wof:placetype":"locality"
},
  "geometry": {"coordinates":[44.13333,1.86667],"type":"Point"}
}