{
  "type": "Feature",
  "properties": {
    "gn:admin1_code":"08",
    "gn:asciiname":"Jirma",
    "gn:country_code":"SO",
    "gn:dem":57,
    "gn:feature_class":"P",
    "gn:feature_code":"PPL",
    "gn:name":"Jirma",
    "gn:population":0,
    "gn:timezone":"Africa/Mogadishu",
    "iso:country":"SO",
    "wof:name":"Jirma",
    "wof:placetype":"locality"
},
  "geometry": {"coordinates":[42.38306,1.4904],"type":"Point"}
}