{
  "type": "Feature",
  "properties": {
    "gn:admin1_code":"14",
    "gn:asciiname":"Caanooley \"A\"",
    "gn:country_code":"SO",
    "gn:dem":66,
    "gn:feature_class":"P",
    "gn:feature_code":"PPL",
    "gn:name":"Caanooley \u201dA\u201d",
    "gn:population":0,
    "gn:timezone":"Africa/Mogadishu",
    "iso:country":"SO",
    "name:som_x_preferred":[
        "Caanooley \u201dA\u201d"
    ],
    "wof:name":"Caanooley \"A\"",
    "wof:placetype":"locality"
},
  "geometry": {"coordinates":[44.49791,1.74973],"type":"Point"}
}