{
  "type": "Feature",
  "properties": {
    "gn:admin1_code":"19",
    "gn:asciiname":"Kundulah",
    "gn:cc2":"SO",
    "gn:country_code":"SO",
    "gn:dem":992,
    "gn:feature_class":"P",
    "gn:feature_code":"PPL",
    "gn:name":"Kundulah",
    "gn:population":0,
    "gn:timezone":"Africa/Mogadishu",
    "iso:country":"SO",
    "name:und_x_variant":[
        "Cundulah",
        "Kundule",
        "Kundulah"
    ],
    "wof:name":"Kundulah",
    "wof:placetype":"locality"
},
  "geometry": {"coordinates":[45.55,9.03333],"type":"Point"}
}