{
  "type": "Feature",
  "properties": {
    "gn:admin1_code":"09",
    "gn:asciiname":"Far Waamo",
    "gn:country_code":"SO",
    "gn:dem":5,
    "gn:feature_class":"P",
    "gn:feature_code":"PPL",
    "gn:name":"Far Waamo",
    "gn:population":0,
    "gn:timezone":"Africa/Mogadishu",
    "iso:country":"SO",
    "wof:name":"Far Waamo",
    "wof:placetype":"locality"
},
  "geometry": {"coordinates":[42.58295,-0.04851],"type":"Point"}
}