{
  "type": "Feature",
  "properties": {
    "gn:admin1_code":"04",
    "gn:asciiname":"Aabow",
    "gn:country_code":"SO",
    "gn:dem":266,
    "gn:feature_class":"P",
    "gn:feature_code":"PPLL",
    "gn:name":"Aabow",
    "gn:population":0,
    "gn:timezone":"Africa/Mogadishu",
    "iso:country":"SO",
    "name:som_x_preferred":[
        "Aabow"
    ],
    "wof:name":"Aabow",
    "wof:placetype":"locality"
},
  "geometry": {"coordinates":[44.1629,3.0295],"type":"Point"}
}