{
  "type": "Feature",
  "properties": {
    "gn:admin1_code":"06",
    "gn:asciiname":"Bilcisha",
    "gn:country_code":"SO",
    "gn:dem":127,
    "gn:feature_class":"P",
    "gn:feature_code":"PPLL",
    "gn:name":"Bilcisha",
    "gn:population":0,
    "gn:timezone":"Africa/Mogadishu",
    "iso:country":"SO",
    "name:som_x_preferred":[
        "Bilcisha"
    ],
    "wof:name":"Bilcisha",
    "wof:placetype":"locality"
},
  "geometry": {"coordinates":[42.35202,2.04549],"type":"Point"}
}