{
  "type": "Feature",
  "properties": {
    "gn:admin1_code":"08",
    "gn:asciiname":"Fanoole No. 1",
    "gn:country_code":"SO",
    "gn:dem":32,
    "gn:feature_class":"P",
    "gn:feature_code":"PPL",
    "gn:name":"Fanoole No. 1",
    "gn:population":0,
    "gn:timezone":"Africa/Mogadishu",
    "iso:country":"SO",
    "wof:name":"Fanoole No. 1",
    "wof:placetype":"locality"
},
  "geometry": {"coordinates":[42.66906,0.74734],"type":"Point"}
}