{
  "type": "Feature",
  "properties": {
    "gn:admin1_code":"12",
    "gn:asciiname":"Jidbaale",
    "gn:cc2":"SO",
    "gn:country_code":"SO",
    "gn:dem":1226,
    "gn:feature_class":"P",
    "gn:feature_code":"PPL",
    "gn:name":"Jidbaale",
    "gn:population":0,
    "gn:timezone":"Africa/Mogadishu",
    "iso:country":"SO",
    "name:und_x_variant":[
        "Jidb\u0101le",
        "Jidbali",
        "Jidbaale"
    ],
    "wof:name":"Jidbaale",
    "wof:placetype":"locality"
},
  "geometry": {"coordinates":[47.16667,9.98333],"type":"Point"}
}