{
  "type": "Feature",
  "properties": {
    "gn:admin1_code":"14",
    "gn:asciiname":"Labagaras",
    "gn:country_code":"SO",
    "gn:dem":95,
    "gn:feature_class":"P",
    "gn:feature_code":"PPL",
    "gn:name":"Labagaras",
    "gn:population":0,
    "gn:timezone":"Africa/Mogadishu",
    "iso:country":"SO",
    "name:som_x_preferred":[
        "Labagaras"
    ],
    "wof:name":"Labagaras",
    "wof:placetype":"locality"
},
  "geometry": {"coordinates":[44.90495,2.696],"type":"Point"}
}