{
  "type": "Feature",
  "properties": {
    "gn:admin1_code":"06",
    "gn:asciiname":"Bakal",
    "gn:country_code":"SO",
    "gn:dem":114,
    "gn:feature_class":"P",
    "gn:feature_code":"PPLL",
    "gn:name":"Bakal",
    "gn:population":0,
    "gn:timezone":"Africa/Mogadishu",
    "iso:country":"SO",
    "name:ben_x_preferred":[
        "\u09ac\u09be\u0995\u09be\u09b2"
    ],
    "name:ceb_x_preferred":[
        "Bakal"
    ],
    "name:ell_x_preferred":[
        "\u039c\u03c0\u03b1\u03ba\u03ac\u03bb"
    ],
    "name:heb_x_preferred":[
        "\u05d1\u05d0\u05e7\u05dc"
    ],
    "name:hin_x_preferred":[
        "\u092c\u0915\u093e\u0932"
    ],
    "name:hun_x_preferred":[
        "Bakal"
    ],
    "name:ind_x_preferred":[
        "Bakal"
    ],
    "name:jpn_x_preferred":[
        "\u30d0\u30ab\u30eb"
    ],
    "name:por_x_preferred":[
        "Bakal"
    ],
    "name:som_x_preferred":[
        "Bakal"
    ],
    "name:spa_x_preferred":[
        "Bakal"
    ],
    "name:swe_x_preferred":[
        "Bakal"
    ],
    "name:tgl_x_preferred":[
        "Bakal"
    ],
    "name:und_x_variant":[
        "Bulo Baccal"
    ],
    "name:urd_x_preferred":[
        "\u0628\u0627\u06a9\u0627\u0644"
    ],
    "name:vie_x_preferred":[
        "Bakal"
    ],
    "wof:name":"Bakal",
    "wof:placetype":"locality"
},
  "geometry": {"coordinates":[42.3542,2.3542],"type":"Point"}
}