{
  "type": "Feature",
  "properties": {
    "gn:admin1_code":"06",
    "gn:asciiname":"Bakal",
    "gn:country_code":"SO",
    "gn:dem":114,
    "gn:feature_class":"P",
    "gn:feature_code":"PPLL",
    "gn:name":"Bakal",
    "gn:population":0,
    "gn:timezone":"Africa/Mogadishu",
    "iso:country":"SO",
    "name:ceb_x_preferred":[
        "Bakal"
    ],
    "name:som_x_preferred":[
        "Bakal"
    ],
    "name:spa_x_preferred":[
        "Bakal"
    ],
    "name:swe_x_preferred":[
        "Bakal"
    ],
    "name:tgl_x_preferred":[
        "Bakal"
    ],
    "name:und_x_variant":[
        "Bulo Baccal",
        "Bakal"
    ],
    "wof:name":"Bakal",
    "wof:placetype":"locality"
},
  "geometry": {"coordinates":[42.3542,2.3542],"type":"Point"}
}