{
  "type": "Feature",
  "properties": {
    "gn:admin1_code":"05",
    "gn:asciiname":"Ceel Ableey",
    "gn:cc2":"SO",
    "gn:country_code":"SO",
    "gn:dem":342,
    "gn:feature_class":"P",
    "gn:feature_code":"PPL",
    "gn:name":"Ceel Ableey",
    "gn:population":0,
    "gn:timezone":"Africa/Mogadishu",
    "iso:country":"SO",
    "name:und_x_variant":[
        "\u2018El Abl\u0113y",
        "Ceel Ableey"
    ],
    "wof:name":"Ceel Ableey",
    "wof:placetype":"locality"
},
  "geometry": {"coordinates":[47.33333,4.41667],"type":"Point"}
}