{
  "type": "Feature",
  "properties": {
    "gn:admin1_code":"04",
    "gn:asciiname":"Buur Dhijis",
    "gn:country_code":"SO",
    "gn:dem":253,
    "gn:feature_class":"P",
    "gn:feature_code":"PPLL",
    "gn:name":"Buur Dhijis",
    "gn:population":0,
    "gn:timezone":"Africa/Mogadishu",
    "iso:country":"SO",
    "name:som_x_preferred":[
        "Buur Dhijis"
    ],
    "wof:name":"Buur Dhijis",
    "wof:placetype":"locality"
},
  "geometry": {"coordinates":[44.162,3.0008],"type":"Point"}
}