{
  "type": "Feature",
  "properties": {
    "gn:admin1_code":"4.0",
    "gn:asciiname":"Munyow",
    "gn:country_code":"SO",
    "gn:dem":255,
    "gn:feature_class":"P",
    "gn:feature_code":"PPL",
    "gn:name":"Munyow",
    "gn:population":0,
    "gn:timezone":"Africa/Mogadishu",
    "iso:country":"SO",
    "name:som_x_preferred":[
        "Munyow"
    ],
    "wof:name":"Munyow",
    "wof:placetype":"locality"
},
  "geometry": {"coordinates":[44.0099,3.0188],"type":"Point"}
}