{
  "type": "Feature",
  "properties": {
    "gn:admin1_code":"04",
    "gn:asciiname":"Gamber",
    "gn:country_code":"SO",
    "gn:dem":264,
    "gn:feature_class":"P",
    "gn:feature_code":"PPL",
    "gn:name":"Gamber",
    "gn:population":0,
    "gn:timezone":"Africa/Mogadishu",
    "iso:country":"SO",
    "name:som_x_preferred":[
        "Gamber"
    ],
    "wof:name":"Gamber",
    "wof:placetype":"locality"
},
  "geometry": {"coordinates":[43.9921,3.0264],"type":"Point"}
}