{
  "type": "Feature",
  "properties": {
    "gn:admin1_code":"6.0",
    "gn:asciiname":"Rabanaggi",
    "gn:country_code":"SO",
    "gn:dem":211,
    "gn:feature_class":"P",
    "gn:feature_code":"PPL",
    "gn:name":"Rabanaggi",
    "gn:population":0,
    "gn:timezone":"Africa/Mogadishu",
    "iso:country":"SO",
    "wof:name":"Rabanaggi",
    "wof:placetype":"locality"
},
  "geometry": {"coordinates":[42.65,3.23333],"type":"Point"}
}