{
  "type": "Feature",
  "properties": {
    "gn:admin1_code":"04",
    "gn:asciiname":"Ban-chi Surta",
    "gn:country_code":"SO",
    "gn:dem":424,
    "gn:feature_class":"P",
    "gn:feature_code":"PPL",
    "gn:name":"Ban-chi Surta",
    "gn:population":0,
    "gn:timezone":"Africa/Mogadishu",
    "iso:country":"SO",
    "wof:name":"Ban-chi Surta",
    "wof:placetype":"locality"
},
  "geometry": {"coordinates":[44.18333,3.26667],"type":"Point"}
}