{
  "type": "Feature",
  "properties": {
    "gn:admin1_code":"01",
    "gn:asciiname":"Galol",
    "gn:country_code":"SO",
    "gn:dem":527,
    "gn:feature_class":"P",
    "gn:feature_code":"PPL",
    "gn:name":"Galol",
    "gn:population":0,
    "gn:timezone":"Africa/Mogadishu",
    "iso:country":"SO",
    "name:som_x_preferred":[
        "Galol"
    ],
    "wof:name":"Galol",
    "wof:placetype":"locality"
},
  "geometry": {"coordinates":[44.04768,3.92968],"type":"Point"}
}