{
  "type": "Feature",
  "properties": {
    "gn:admin1_code":"5.0",
    "gn:asciiname":"Nooleeye",
    "gn:country_code":"SO",
    "gn:dem":133,
    "gn:feature_class":"P",
    "gn:feature_code":"PPL",
    "gn:name":"Nooleeye",
    "gn:population":0,
    "gn:timezone":"Africa/Mogadishu",
    "iso:country":"SO",
    "name:som_x_preferred":[
        "Nooleeye"
    ],
    "wof:name":"Nooleeye",
    "wof:placetype":"locality"
},
  "geometry": {"coordinates":[46.91273,4.16209],"type":"Point"}
}