{
  "type": "Feature",
  "properties": {
    "gn:admin1_code":"05",
    "gn:asciiname":"Bar Ujeed",
    "gn:country_code":"SO",
    "gn:dem":211,
    "gn:feature_class":"P",
    "gn:feature_code":"PPL",
    "gn:name":"Bar Ujeed",
    "gn:population":0,
    "gn:timezone":"Africa/Mogadishu",
    "iso:country":"SO",
    "name:und_x_variant":[
        "Beruged"
    ],
    "wof:name":"Bar Ujeed",
    "wof:placetype":"locality"
},
  "geometry": {"coordinates":[46.25,4.95],"type":"Point"}
}