{
  "type": "Feature",
  "properties": {
    "gn:admin1_code":"3.0",
    "gn:asciiname":"Meeladeen",
    "gn:country_code":"SO",
    "gn:dem":385,
    "gn:feature_class":"P",
    "gn:feature_code":"PPL",
    "gn:name":"Meeladeen",
    "gn:population":0,
    "gn:timezone":"Africa/Mogadishu",
    "iso:country":"SO",
    "name:som_x_preferred":[
        "Meeladeen"
    ],
    "name:und_x_variant":[
        "Meledin",
        "M\u0113lad\u0113n",
        "Meleden",
        "Meeladeen"
    ],
    "wof:name":"Meeladeen",
    "wof:placetype":"locality"
},
  "geometry": {"coordinates":[49.8107,10.4332],"type":"Point"}
}