{
  "type": "Feature",
  "properties": {
    "gn:admin1_code":"09",
    "gn:asciiname":"Hoosingo",
    "gn:country_code":"SO",
    "gn:dem":48,
    "gn:feature_class":"P",
    "gn:feature_code":"PPL",
    "gn:name":"Hoosingo",
    "gn:population":0,
    "gn:timezone":"Africa/Mogadishu",
    "iso:country":"SO",
    "name:nld_x_preferred":[
        "Hoosingo"
    ],
    "name:som_x_preferred":[
        "Hoosingo"
    ],
    "name:som_x_variant":[
        "Hoosingow"
    ],
    "wof:name":"Hoosingo",
    "wof:placetype":"locality"
},
  "geometry": {"coordinates":[41.2699,-0.1754],"type":"Point"}
}