{
  "type": "Feature",
  "properties": {
    "gn:admin1_code":"04",
    "gn:asciiname":"Areeg",
    "gn:country_code":"SO",
    "gn:dem":424,
    "gn:feature_class":"P",
    "gn:feature_code":"PPL",
    "gn:name":"Areeg",
    "gn:population":0,
    "gn:timezone":"Africa/Mogadishu",
    "iso:country":"SO",
    "name:som_x_preferred":[
        "Areeg"
    ],
    "name:und_x_variant":[
        "Arec",
        "Areeg"
    ],
    "wof:name":"Areeg",
    "wof:placetype":"locality"
},
  "geometry": {"coordinates":[43.7611,3.182],"type":"Point"}
}