{
  "type": "Feature",
  "properties": {
    "gn:admin1_code":"14",
    "gn:asciiname":"Al Medou",
    "gn:country_code":"SO",
    "gn:dem":44,
    "gn:feature_class":"P",
    "gn:feature_code":"PPL",
    "gn:name":"Al Medou",
    "gn:population":0,
    "gn:timezone":"Africa/Mogadishu",
    "iso:country":"SO",
    "wof:name":"Al Medou",
    "wof:placetype":"locality"
},
  "geometry": {"coordinates":[43.65,0.86667],"type":"Point"}
}