{
  "type": "Feature",
  "properties": {
    "gn:admin1_code":"07",
    "gn:asciiname":"Gabaariyole",
    "gn:country_code":"SO",
    "gn:dem":134,
    "gn:feature_class":"P",
    "gn:feature_code":"PPL",
    "gn:name":"Gabaariyole",
    "gn:population":0,
    "gn:timezone":"Africa/Mogadishu",
    "iso:country":"SO",
    "name:som_x_preferred":[
        "Gabaariyole"
    ],
    "wof:name":"Gabaariyole",
    "wof:placetype":"locality"
},
  "geometry": {"coordinates":[45.5123,3.4996],"type":"Point"}
}