{
  "type": "Feature",
  "properties": {
    "gn:admin1_code":"06",
    "gn:asciiname":"Koreey",
    "gn:country_code":"SO",
    "gn:dem":126,
    "gn:feature_class":"P",
    "gn:feature_code":"PPL",
    "gn:name":"Koreey",
    "gn:population":0,
    "gn:timezone":"Africa/Mogadishu",
    "iso:country":"SO",
    "name:som_x_preferred":[
        "Koreey"
    ],
    "wof:name":"Koreey",
    "wof:placetype":"locality"
},
  "geometry": {"coordinates":[42.31038,2.23864],"type":"Point"}
}