{
  "type": "Feature",
  "properties": {
    "gn:admin1_code":"07",
    "gn:asciiname":"Gadoon",
    "gn:country_code":"SO",
    "gn:dem":239,
    "gn:feature_class":"P",
    "gn:feature_code":"PPL",
    "gn:name":"Gadoon",
    "gn:population":0,
    "gn:timezone":"Africa/Mogadishu",
    "iso:country":"SO",
    "name:som_x_preferred":[
        "Gadoon"
    ],
    "wof:name":"Gadoon",
    "wof:placetype":"locality"
},
  "geometry": {"coordinates":[45.61882,4.30944],"type":"Point"}
}