{
  "type": "Feature",
  "properties": {
    "gn:admin1_code":"14.0",
    "gn:asciiname":"Xaaji Faarax",
    "gn:country_code":"SO",
    "gn:dem":67,
    "gn:feature_class":"P",
    "gn:feature_code":"PPL",
    "gn:name":"Xaaji Faarax",
    "gn:population":0,
    "gn:timezone":"Africa/Mogadishu",
    "iso:country":"SO",
    "name:som_x_preferred":[
        "Xaaji Faarax"
    ],
    "wof:name":"Xaaji Faarax",
    "wof:placetype":"locality"
},
  "geometry": {"coordinates":[44.5399,1.7072],"type":"Point"}
}