{
  "type": "Feature",
  "properties": {
    "gn:admin1_code":"14",
    "gn:asciiname":"Haaway",
    "gn:country_code":"SO",
    "gn:dem":46,
    "gn:feature_class":"P",
    "gn:feature_code":"PPL",
    "gn:name":"Haaway",
    "gn:population":0,
    "gn:timezone":"Africa/Mogadishu",
    "iso:country":"SO",
    "name:som_x_preferred":[
        "Haaway"
    ],
    "name:und_x_variant":[
        "Avai",
        "Hawaay",
        "H\u00e1bay",
        "Haaway"
    ],
    "wof:name":"Haaway",
    "wof:placetype":"locality"
},
  "geometry": {"coordinates":[43.71425,1.16849],"type":"Point"}
}