{
  "type": "Feature",
  "properties": {
    "gn:admin1_code":"05",
    "gn:asciiname":"Gellinsoor",
    "gn:country_code":"SO",
    "gn:dem":333,
    "gn:feature_class":"P",
    "gn:feature_code":"PPL",
    "gn:name":"Gellinsoor",
    "gn:population":0,
    "gn:timezone":"Africa/Mogadishu",
    "iso:country":"SO",
    "name:deu_x_preferred":[
        "Galinsoor"
    ],
    "name:fas_x_preferred":[
        "\u067e\u0627\u0644\u06cc\u0646\u0633\u0648\u0631"
    ],
    "name:fra_x_preferred":[
        "Galinsoor"
    ],
    "name:por_x_preferred":[
        "Galinsoor"
    ],
    "name:ron_x_preferred":[
        "Galinsoor"
    ],
    "name:som_x_preferred":[
        "Galinsoor"
    ],
    "name:und_x_variant":[
        "Gallinsor",
        "Galinsoor",
        "Gh\u00e8linsor",
        "Gellinsn\u0308r",
        "Gelinsor",
        "Gellinsoor"
    ],
    "wof:name":"Gellinsoor",
    "wof:placetype":"locality"
},
  "geometry": {"coordinates":[46.71,6.42972],"type":"Point"}
}