{
  "type": "Feature",
  "properties": {
    "gn:admin1_code":"09",
    "gn:asciiname":"Booka",
    "gn:country_code":"SO",
    "gn:dem":11,
    "gn:feature_class":"P",
    "gn:feature_code":"PPL",
    "gn:name":"Booka",
    "gn:population":0,
    "gn:timezone":"Africa/Mogadishu",
    "iso:country":"SO",
    "wof:name":"Booka",
    "wof:placetype":"locality"
},
  "geometry": {"coordinates":[42.41015,0.07771],"type":"Point"}
}