{
  "type": "Feature",
  "properties": {
    "gn:admin1_code":"14.0",
    "gn:asciiname":"Walamooy",
    "gn:country_code":"SO",
    "gn:dem":93,
    "gn:feature_class":"P",
    "gn:feature_code":"PPL",
    "gn:name":"Walamooy",
    "gn:population":0,
    "gn:timezone":"Africa/Mogadishu",
    "iso:country":"SO",
    "name:som_x_preferred":[
        "Walamooy"
    ],
    "name:und_x_variant":[
        "Ualamo Arac\u00f2",
        "Walamooy"
    ],
    "wof:name":"Walamooy",
    "wof:placetype":"locality"
},
  "geometry": {"coordinates":[45.3241,2.3031],"type":"Point"}
}