{
  "type": "Feature",
  "properties": {
    "gn:admin1_code":"03",
    "gn:asciiname":"Hagia El",
    "gn:country_code":"SO",
    "gn:dem":651,
    "gn:feature_class":"P",
    "gn:feature_code":"PPL",
    "gn:name":"Hagia El",
    "gn:population":0,
    "gn:timezone":"Africa/Mogadishu",
    "iso:country":"SO",
    "wof:name":"Hagia El",
    "wof:placetype":"locality"
},
  "geometry": {"coordinates":[50.06667,11.25],"type":"Point"}
}