{
  "type": "Feature",
  "properties": {
    "gn:admin1_code":"19.0",
    "gn:asciiname":"Xaydhducaale",
    "gn:country_code":"SO",
    "gn:dem":800,
    "gn:feature_class":"P",
    "gn:feature_code":"PPL",
    "gn:name":"Xaydhducaale",
    "gn:population":0,
    "gn:timezone":"Africa/Mogadishu",
    "iso:country":"SO",
    "wof:name":"Xaydhducaale",
    "wof:placetype":"locality"
},
  "geometry": {"coordinates":[45.7352,8.71716],"type":"Point"}
}