{
  "type": "Feature",
  "properties": {
    "gn:admin1_code":"4.0",
    "gn:asciiname":"Qasallow",
    "gn:country_code":"SO",
    "gn:dem":470,
    "gn:feature_class":"P",
    "gn:feature_code":"PPL",
    "gn:name":"Qasallow",
    "gn:population":0,
    "gn:timezone":"Africa/Mogadishu",
    "iso:country":"SO",
    "name:som_x_preferred":[
        "Qasallow"
    ],
    "wof:name":"Qasallow",
    "wof:placetype":"locality"
},
  "geometry": {"coordinates":[43.4297,3.0696],"type":"Point"}
}