{
  "type": "Feature",
  "properties": {
    "gn:admin1_code":"6.0",
    "gn:asciiname":"Waandhay",
    "gn:country_code":"SO",
    "gn:dem":254,
    "gn:feature_class":"P",
    "gn:feature_code":"PPL",
    "gn:name":"Waandhay",
    "gn:population":0,
    "gn:timezone":"Africa/Mogadishu",
    "iso:country":"SO",
    "wof:name":"Waandhay",
    "wof:placetype":"locality"
},
  "geometry": {"coordinates":[42.09919,3.31909],"type":"Point"}
}