{
  "type": "Feature",
  "properties": {
    "gn:admin1_code":"13",
    "gn:asciiname":"Axmed Cigoow",
    "gn:country_code":"SO",
    "gn:dem":109,
    "gn:feature_class":"P",
    "gn:feature_code":"PPL",
    "gn:name":"Axmed Cigoow",
    "gn:population":0,
    "gn:timezone":"Africa/Mogadishu",
    "iso:country":"SO",
    "name:som_x_preferred":[
        "Axmed Cigoow"
    ],
    "name:und_x_variant":[
        "Bulo Ahmed Igo"
    ],
    "wof:name":"Axmed Cigoow",
    "wof:placetype":"locality"
},
  "geometry": {"coordinates":[45.549,2.9091],"type":"Point"}
}