{
  "type": "Feature",
  "properties": {
    "gn:admin1_code":"20",
    "gn:asciiname":"Jaleelo",
    "gn:country_code":"SO",
    "gn:dem":998,
    "gn:feature_class":"P",
    "gn:feature_code":"PPL",
    "gn:name":"Jaleelo",
    "gn:population":0,
    "gn:timezone":"Africa/Mogadishu",
    "iso:country":"SO",
    "name:und_x_variant":[
        "Gumbur Jalelo",
        "Jaleelo"
    ],
    "wof:name":"Jaleelo",
    "wof:placetype":"locality"
},
  "geometry": {"coordinates":[44.29158,9.75195],"type":"Point"}
}