{
  "type": "Feature",
  "properties": {
    "gn:admin1_code":"9.0",
    "gn:asciiname":"Scidlei",
    "gn:country_code":"SO",
    "gn:dem":12,
    "gn:feature_class":"P",
    "gn:feature_code":"PPL",
    "gn:name":"Scidlei",
    "gn:population":0,
    "gn:timezone":"Africa/Mogadishu",
    "iso:country":"SO",
    "wof:name":"Scidlei",
    "wof:placetype":"locality"
},
  "geometry": {"coordinates":[41.88333,-1.13333],"type":"Point"}
}