{
  "type": "Feature",
  "properties": {
    "gn:admin1_code":"04",
    "gn:asciiname":"Ban Dhuub",
    "gn:country_code":"SO",
    "gn:dem":326,
    "gn:feature_class":"P",
    "gn:feature_code":"PPL",
    "gn:name":"Ban Dhuub",
    "gn:population":0,
    "gn:timezone":"Africa/Mogadishu",
    "iso:country":"SO",
    "name:som_x_preferred":[
        "Ban Dhuub"
    ],
    "wof:name":"Ban Dhuub",
    "wof:placetype":"locality"
},
  "geometry": {"coordinates":[42.8674,2.4172],"type":"Point"}
}