{
  "type": "Feature",
  "properties": {
    "gn:admin1_code":"14",
    "gn:asciiname":"Laab Mardha",
    "gn:country_code":"SO",
    "gn:dem":51,
    "gn:feature_class":"P",
    "gn:feature_code":"PPL",
    "gn:name":"Laab Mardha",
    "gn:population":0,
    "gn:timezone":"Africa/Mogadishu",
    "iso:country":"SO",
    "name:som_x_preferred":[
        "Laab Mardha"
    ],
    "wof:name":"Laab Mardha",
    "wof:placetype":"locality"
},
  "geometry": {"coordinates":[43.90134000000001,1.38727],"type":"Point"}
}