{
  "type": "Feature",
  "properties": {
    "gn:admin1_code":"08",
    "gn:asciiname":"Bashiir Malaambow",
    "gn:country_code":"SO",
    "gn:dem":15,
    "gn:feature_class":"P",
    "gn:feature_code":"PPL",
    "gn:name":"Bashiir Malaambow",
    "gn:population":0,
    "gn:timezone":"Africa/Mogadishu",
    "iso:country":"SO",
    "wof:name":"Bashiir Malaambow",
    "wof:placetype":"locality"
},
  "geometry": {"coordinates":[42.74596,0.31044],"type":"Point"}
}