{
  "type": "Feature",
  "properties": {
    "gn:admin1_code":"21",
    "gn:asciiname":"Karinkarin",
    "gn:country_code":"SO",
    "gn:dem":491,
    "gn:feature_class":"P",
    "gn:feature_code":"PPL",
    "gn:name":"Karinkarin",
    "gn:population":0,
    "gn:timezone":"Africa/Mogadishu",
    "iso:country":"SO",
    "wof:name":"Karinkarin",
    "wof:placetype":"locality"
},
  "geometry": {"coordinates":[43.63333,10.28333],"type":"Point"}
}