{
  "type": "Feature",
  "properties": {
    "gn:admin1_code":"19",
    "gn:asciiname":"Inadadan",
    "gn:country_code":"SO",
    "gn:dem":782,
    "gn:feature_class":"P",
    "gn:feature_code":"PPL",
    "gn:name":"Inadadan",
    "gn:population":0,
    "gn:timezone":"Africa/Mogadishu",
    "iso:country":"SO",
    "wof:name":"Inadadan",
    "wof:placetype":"locality"
},
  "geometry": {"coordinates":[45.91285,8.59565],"type":"Point"}
}