{
  "type": "Feature",
  "properties": {
    "gn:admin1_code":"9.0",
    "gn:asciiname":"Madero",
    "gn:country_code":"SO",
    "gn:dem":17,
    "gn:feature_class":"P",
    "gn:feature_code":"PPL",
    "gn:name":"Madero",
    "gn:population":0,
    "gn:timezone":"Africa/Mogadishu",
    "iso:country":"SO",
    "wof:name":"Madero",
    "wof:placetype":"locality"
},
  "geometry": {"coordinates":[41.66667,-1.36667],"type":"Point"}
}