{
  "type": "Feature",
  "properties": {
    "gn:admin1_code":"08",
    "gn:asciiname":"Bandar Salaam",
    "gn:country_code":"SO",
    "gn:dem":15,
    "gn:feature_class":"P",
    "gn:feature_code":"PPLL",
    "gn:name":"Bandar Salaam",
    "gn:population":0,
    "gn:timezone":"Africa/Mogadishu",
    "iso:country":"SO",
    "wof:name":"Bandar Salaam",
    "wof:placetype":"locality"
},
  "geometry": {"coordinates":[42.76472,0.34155],"type":"Point"}
}