{
  "type": "Feature",
  "properties": {
    "gn:admin1_code":"14",
    "gn:asciiname":"Bambaaso Mahdi",
    "gn:country_code":"SO",
    "gn:dem":64,
    "gn:feature_class":"P",
    "gn:feature_code":"PPL",
    "gn:name":"Bambaaso Mahdi",
    "gn:population":0,
    "gn:timezone":"Africa/Mogadishu",
    "iso:country":"SO",
    "name:som_x_preferred":[
        "Bambaaso Mahdi"
    ],
    "wof:name":"Bambaaso Mahdi",
    "wof:placetype":"locality"
},
  "geometry": {"coordinates":[44.4293,1.6952],"type":"Point"}
}