{
  "type": "Feature",
  "properties": {
    "gn:admin1_code":"03",
    "gn:asciiname":"Lava Rugodle",
    "gn:cc2":"SO",
    "gn:country_code":"SO",
    "gn:dem":248,
    "gn:feature_class":"P",
    "gn:feature_code":"PPL",
    "gn:name":"Lava Rugodle",
    "gn:population":0,
    "gn:timezone":"Africa/Mogadishu",
    "iso:country":"SO",
    "name:und_x_variant":[
        "Bulo",
        "Lava Rugodle"
    ],
    "wof:name":"Lava Rugodle",
    "wof:placetype":"locality"
},
  "geometry": {"coordinates":[50.83333,10.61667],"type":"Point"}
}