{
  "type": "Feature",
  "properties": {
    "gn:admin1_code":"04",
    "gn:asciiname":"Fulaayka",
    "gn:country_code":"SO",
    "gn:dem":236,
    "gn:feature_class":"P",
    "gn:feature_code":"PPL",
    "gn:name":"Fulaayka",
    "gn:population":0,
    "gn:timezone":"Africa/Mogadishu",
    "iso:country":"SO",
    "name:som_x_preferred":[
        "Fulaayka"
    ],
    "wof:name":"Fulaayka",
    "wof:placetype":"locality"
},
  "geometry": {"coordinates":[44.1495,2.95221],"type":"Point"}
}