{
  "type": "Feature",
  "properties": {
    "gn:admin1_code":"13",
    "gn:asciiname":"Gana Weyne",
    "gn:country_code":"SO",
    "gn:dem":119,
    "gn:feature_class":"P",
    "gn:feature_code":"PPL",
    "gn:name":"Gana Weyne",
    "gn:population":0,
    "gn:timezone":"Africa/Mogadishu",
    "iso:country":"SO",
    "name:som_x_preferred":[
        "Gana Weyne"
    ],
    "wof:name":"Gana Weyne",
    "wof:placetype":"locality"
},
  "geometry": {"coordinates":[45.6598,3.1952],"type":"Point"}
}