{
  "type": "Feature",
  "properties": {
    "iso:country":"SO",
    "name:unk_x_variant":[
        "Dujuma"
    ],
    "qs:gn_country":"SO",
    "qs:gn_fcode":"PPL",
    "qs:gn_pop":2432,
    "qs:name":"Dujuuma",
    "qs:name_adm0":"Somalia",
    "qs:name_adm1":"Jubbada Dhexe",
    "qs:photos":0,
    "qs:photos_1k":0,
    "qs:photos_9k":0,
    "qs:photos_9r":0,
    "qs:photos_all":0,
    "qs:photos_sr":0,
    "qs:placetype":"Town",
    "qs:pop_sr":"4",
    "qs:woe_adm0":23424949,
    "wof:name":"Dujuuma",
    "wof:placetype":"locality",
    "wof:population":2432
},
  "geometry": {"coordinates":[42.57377,1.25311],"type":"Point"}
}