{
  "type": "Feature",
  "properties": {
    "gn:admin1_code":"13.0",
    "gn:asciiname":"Mayoongaale",
    "gn:country_code":"SO",
    "gn:dem":108,
    "gn:feature_class":"P",
    "gn:feature_code":"PPL",
    "gn:name":"Mayoongaale",
    "gn:population":0,
    "gn:timezone":"Africa/Mogadishu",
    "iso:country":"SO",
    "name:som_x_preferred":[
        "Mayoongaale"
    ],
    "name:und_x_variant":[
        "Maniongale",
        "Mayoongaale"
    ],
    "wof:name":"Mayoongaale",
    "wof:placetype":"locality"
},
  "geometry": {"coordinates":[45.53354,2.77984],"type":"Point"}
}