{
  "type": "Feature",
  "properties": {
    "gn:admin1_code":"14.0",
    "gn:asciiname":"Magna Gab",
    "gn:country_code":"SO",
    "gn:dem":67,
    "gn:feature_class":"P",
    "gn:feature_code":"PPL",
    "gn:name":"Magna Gab",
    "gn:population":0,
    "gn:timezone":"Africa/Mogadishu",
    "iso:country":"SO",
    "wof:name":"Magna Gab",
    "wof:placetype":"locality"
},
  "geometry": {"coordinates":[44.46667,1.73333],"type":"Point"}
}