{
  "type": "Feature",
  "properties": {
    "gn:admin1_code":"20",
    "gn:asciiname":"Dhubbato",
    "gn:country_code":"SO",
    "gn:dem":1132,
    "gn:feature_class":"P",
    "gn:feature_code":"PPL",
    "gn:name":"Dhubbato",
    "gn:population":0,
    "gn:timezone":"Africa/Mogadishu",
    "iso:country":"SO",
    "name:und_x_variant":[
        "Dubato"
    ],
    "wof:name":"Dhubbato",
    "wof:placetype":"locality"
},
  "geometry": {"coordinates":[44.47456,9.73677],"type":"Point"}
}