{
  "type": "Feature",
  "properties": {
    "gn:admin1_code":"13.0",
    "gn:asciiname":"Raga Ceel",
    "gn:country_code":"SO",
    "gn:dem":35,
    "gn:feature_class":"P",
    "gn:feature_code":"PPL",
    "gn:name":"Raga Ceel",
    "gn:population":0,
    "gn:timezone":"Africa/Mogadishu",
    "iso:country":"SO",
    "name:som_x_preferred":[
        "Raga Ceel"
    ],
    "wof:name":"Raga Ceel",
    "wof:placetype":"locality"
},
  "geometry": {"coordinates":[46.0091,2.6557],"type":"Point"}
}