{
  "type": "Feature",
  "properties": {
    "gn:admin1_code":"04",
    "gn:asciiname":"Daauudow",
    "gn:country_code":"SO",
    "gn:dem":336,
    "gn:feature_class":"P",
    "gn:feature_code":"PPL",
    "gn:name":"Daauudow",
    "gn:population":0,
    "gn:timezone":"Africa/Mogadishu",
    "iso:country":"SO",
    "name:som_x_preferred":[
        "Daauudow"
    ],
    "wof:name":"Daauudow",
    "wof:placetype":"locality"
},
  "geometry": {"coordinates":[43.6844,2.9886],"type":"Point"}
}