{
  "type": "Feature",
  "properties": {
    "gn:admin1_code":"14",
    "gn:asciiname":"Alafuutow",
    "gn:country_code":"SO",
    "gn:dem":56,
    "gn:feature_class":"P",
    "gn:feature_code":"PPL",
    "gn:name":"Alafuutow",
    "gn:population":0,
    "gn:timezone":"Africa/Mogadishu",
    "iso:country":"SO",
    "name:som_x_preferred":[
        "Alafuutow"
    ],
    "wof:name":"Alafuutow",
    "wof:placetype":"locality"
},
  "geometry": {"coordinates":[44.10464,1.57181],"type":"Point"}
}