{
  "type": "Feature",
  "properties": {
    "gn:admin1_code":"4.0",
    "gn:asciiname":"Xabibayal",
    "gn:country_code":"SO",
    "gn:dem":291,
    "gn:feature_class":"P",
    "gn:feature_code":"PPL",
    "gn:name":"Xabibayal",
    "gn:population":0,
    "gn:timezone":"Africa/Mogadishu",
    "iso:country":"SO",
    "name:som_x_preferred":[
        "Xabibayal"
    ],
    "wof:name":"Xabibayal",
    "wof:placetype":"locality"
},
  "geometry": {"coordinates":[42.6649,2.3525],"type":"Point"}
}