{
  "type": "Feature",
  "properties": {
    "gn:admin1_code":"01",
    "gn:asciiname":"Ceel Ya",
    "gn:country_code":"SO",
    "gn:dem":470,
    "gn:feature_class":"P",
    "gn:feature_code":"PPL",
    "gn:name":"Ceel Ya",
    "gn:population":0,
    "gn:timezone":"Africa/Mogadishu",
    "iso:country":"SO",
    "name:und_x_variant":[
        "Iah",
        "Ceel Ya"
    ],
    "wof:name":"Ceel Ya",
    "wof:placetype":"locality"
},
  "geometry": {"coordinates":[44.16142,4.03156],"type":"Point"}
}