{
  "type": "Feature",
  "properties": {
    "gn:admin1_code":"05",
    "gn:asciiname":"Ceel Baxay",
    "gn:country_code":"SO",
    "gn:dem":204,
    "gn:feature_class":"P",
    "gn:feature_code":"PPL",
    "gn:name":"Ceel Baxay",
    "gn:population":0,
    "gn:timezone":"Africa/Mogadishu",
    "iso:country":"SO",
    "name:und_x_variant":[
        "El Bahi",
        "El Bahai",
        "\u2018\u0112lb\u00e1hay",
        "Ceel Baxay"
    ],
    "wof:name":"Ceel Baxay",
    "wof:placetype":"locality"
},
  "geometry": {"coordinates":[46.16163,4.79432],"type":"Point"}
}