{
  "type": "Feature",
  "properties": {
    "gn:admin1_code":"3.0",
    "gn:asciiname":"Tooxin",
    "gn:country_code":"SO",
    "gn:dem":6,
    "gn:feature_class":"P",
    "gn:feature_code":"PPL",
    "gn:name":"Tooxin",
    "gn:population":0,
    "gn:timezone":"Africa/Mogadishu",
    "iso:country":"SO",
    "name:ita_x_preferred":[
        "Tohen"
    ],
    "name:nld_x_preferred":[
        "Tooxin"
    ],
    "name:som_x_preferred":[
        "Tooxin"
    ],
    "name:und_x_variant":[
        "Bohin",
        "Toh\u00e8n",
        "Tooxin"
    ],
    "wof:name":"Tooxin",
    "wof:placetype":"locality"
},
  "geometry": {"coordinates":[51.2555,11.75062],"type":"Point"}
}