{
  "type": "Feature",
  "properties": {
    "gn:admin1_code":"9.0",
    "gn:asciiname":"Muryoole",
    "gn:country_code":"SO",
    "gn:dem":8,
    "gn:feature_class":"P",
    "gn:feature_code":"PPL",
    "gn:name":"Muryoole",
    "gn:population":0,
    "gn:timezone":"Africa/Mogadishu",
    "iso:country":"SO",
    "wof:name":"Muryoole",
    "wof:placetype":"locality"
},
  "geometry": {"coordinates":[42.76758,-0.03655],"type":"Point"}
}