{
  "type": "Feature",
  "properties": {
    "gn:admin1_code":"06",
    "gn:asciiname":"Iedo",
    "gn:country_code":"SO",
    "gn:dem":375,
    "gn:feature_class":"P",
    "gn:feature_code":"PPL",
    "gn:name":"Iedo",
    "gn:population":0,
    "gn:timezone":"Africa/Mogadishu",
    "iso:country":"SO",
    "name:und_x_variant":[
        "Tedo",
        "Iedo"
    ],
    "wof:name":"Iedo",
    "wof:placetype":"locality"
},
  "geometry": {"coordinates":[41.13347,2.94982],"type":"Point"}
}