{
  "type": "Feature",
  "properties": {
    "gn:admin1_code":"10",
    "gn:asciiname":"Dumaaye",
    "gn:country_code":"SO",
    "gn:dem":188,
    "gn:feature_class":"P",
    "gn:feature_code":"PPL",
    "gn:name":"Dumaaye",
    "gn:population":0,
    "gn:timezone":"Africa/Mogadishu",
    "iso:country":"SO",
    "name:som_x_preferred":[
        "Dumaaye"
    ],
    "wof:name":"Dumaaye",
    "wof:placetype":"locality"
},
  "geometry": {"coordinates":[47.61622,4.87762],"type":"Point"}
}