{
  "type": "Feature",
  "properties": {
    "gn:admin1_code":"04",
    "gn:asciiname":"Kadyow",
    "gn:country_code":"SO",
    "gn:dem":149,
    "gn:feature_class":"P",
    "gn:feature_code":"PPL",
    "gn:name":"Kadyow",
    "gn:population":0,
    "gn:timezone":"Africa/Mogadishu",
    "iso:country":"SO",
    "wof:name":"Kadyow",
    "wof:placetype":"locality"
},
  "geometry": {"coordinates":[43.11531,1.81582],"type":"Point"}
}