{
  "type": "Feature",
  "properties": {
    "gn:admin1_code":"10",
    "gn:asciiname":"Bagahar",
    "gn:country_code":"SO",
    "gn:dem":26,
    "gn:feature_class":"P",
    "gn:feature_code":"PPL",
    "gn:name":"Bagahar",
    "gn:population":0,
    "gn:timezone":"Africa/Mogadishu",
    "iso:country":"SO",
    "wof:name":"Bagahar",
    "wof:placetype":"locality"
},
  "geometry": {"coordinates":[48.83333,6.51667],"type":"Point"}
}