{
  "type": "Feature",
  "properties": {
    "gn:admin1_code":"22",
    "gn:asciiname":"Karingorfood",
    "gn:country_code":"SO",
    "gn:dem":730,
    "gn:feature_class":"P",
    "gn:feature_code":"PPL",
    "gn:name":"Karingorfood",
    "gn:population":0,
    "gn:timezone":"Africa/Mogadishu",
    "iso:country":"SO",
    "name:som_x_preferred":[
        "Karingorfood"
    ],
    "wof:name":"Karingorfood",
    "wof:placetype":"locality"
},
  "geometry": {"coordinates":[47.75709000000001,8.11943],"type":"Point"}
}