{
  "type": "Feature",
  "properties": {
    "gn:admin1_code":"10",
    "gn:asciiname":"Ceelgaalaad",
    "gn:cc2":"SO",
    "gn:country_code":"SO",
    "gn:dem":46,
    "gn:feature_class":"P",
    "gn:feature_code":"PPL",
    "gn:name":"Ceelgaalaad",
    "gn:population":0,
    "gn:timezone":"Africa/Mogadishu",
    "iso:country":"SO",
    "name:und_x_variant":[
        "El Galad",
        "Galad",
        "Ceelgaalaad"
    ],
    "wof:name":"Ceelgaalaad",
    "wof:placetype":"locality"
},
  "geometry": {"coordinates":[48.41667,5.45],"type":"Point"}
}