{
  "type": "Feature",
  "properties": {
    "gn:admin1_code":"04",
    "gn:asciiname":"Allenta",
    "gn:country_code":"SO",
    "gn:dem":351,
    "gn:feature_class":"P",
    "gn:feature_code":"PPL",
    "gn:name":"Allenta",
    "gn:population":0,
    "gn:timezone":"Africa/Mogadishu",
    "iso:country":"SO",
    "wof:name":"Allenta",
    "wof:placetype":"locality"
},
  "geometry": {"coordinates":[42.98333,2.51667],"type":"Point"}
}