{
  "type": "Feature",
  "properties": {
    "gn:admin1_code":"14.0",
    "gn:asciiname":"Warermaleh",
    "gn:country_code":"SO",
    "gn:dem":57,
    "gn:feature_class":"P",
    "gn:feature_code":"PPL",
    "gn:name":"Warermaleh",
    "gn:population":0,
    "gn:timezone":"Africa/Mogadishu",
    "iso:country":"SO",
    "name:som_x_preferred":[
        "Warermaleh"
    ],
    "wof:name":"Warermaleh",
    "wof:placetype":"locality"
},
  "geometry": {"coordinates":[44.24749,1.38539],"type":"Point"}
}