{
  "type": "Feature",
  "properties": {
    "gn:admin1_code":"20.0",
    "gn:asciiname":"Waraabaley",
    "gn:country_code":"SO",
    "gn:dem":1493,
    "gn:feature_class":"P",
    "gn:feature_code":"PPL",
    "gn:name":"Waraabaley",
    "gn:population":0,
    "gn:timezone":"Africa/Mogadishu",
    "iso:country":"SO",
    "wof:name":"Waraabaley",
    "wof:placetype":"locality"
},
  "geometry": {"coordinates":[43.78633,9.56629],"type":"Point"}
}