{
  "type": "Feature",
  "properties": {
    "gn:admin1_code":"13",
    "gn:asciiname":"Dhabaq Lebi",
    "gn:country_code":"SO",
    "gn:dem":156,
    "gn:feature_class":"P",
    "gn:feature_code":"PPL",
    "gn:name":"Dhabaq Lebi",
    "gn:population":0,
    "gn:timezone":"Africa/Mogadishu",
    "iso:country":"SO",
    "name:som_x_preferred":[
        "Dhabaq Lebi"
    ],
    "wof:name":"Dhabaq Lebi",
    "wof:placetype":"locality"
},
  "geometry": {"coordinates":[46.2177,3.6332],"type":"Point"}
}