{
  "type": "Feature",
  "properties": {
    "gn:admin1_code":"4.0",
    "gn:asciiname":"Bakdaad",
    "gn:country_code":"SO",
    "gn:dem":404,
    "gn:feature_class":"P",
    "gn:feature_code":"PPL",
    "gn:name":"Bakdaad",
    "gn:population":0,
    "gn:timezone":"Africa/Mogadishu",
    "iso:country":"SO",
    "name:som_x_preferred":[
        "Bakdaad"
    ],
    "name:und_x_variant":[
        "Sakdaad"
    ],
    "wof:name":"Bakdaad",
    "wof:placetype":"locality"
},
  "geometry": {"coordinates":[43.194,3.4051],"type":"Point"}
}