{
  "type": "Feature",
  "properties": {
    "gn:admin1_code":"10",
    "gn:asciiname":"El Af Gumasorrei",
    "gn:country_code":"SO",
    "gn:dem":27,
    "gn:feature_class":"P",
    "gn:feature_code":"PPL",
    "gn:name":"El Af Gumasorrei",
    "gn:population":0,
    "gn:timezone":"Africa/Mogadishu",
    "iso:country":"SO",
    "wof:name":"El Af Gumasorrei",
    "wof:placetype":"locality"
},
  "geometry": {"coordinates":[48.78333,6.48333],"type":"Point"}
}