{
  "type": "Feature",
  "properties": {
    "gn:admin1_code":"5.0",
    "gn:asciiname":"Uaha Ier",
    "gn:country_code":"SO",
    "gn:dem":21,
    "gn:feature_class":"P",
    "gn:feature_code":"PPL",
    "gn:name":"Uaha Ier",
    "gn:population":0,
    "gn:timezone":"Africa/Mogadishu",
    "iso:country":"SO",
    "wof:name":"Uaha Ier",
    "wof:placetype":"locality"
},
  "geometry": {"coordinates":[47.83333,4.35],"type":"Point"}
}