{
  "type": "Feature",
  "properties": {
    "gn:admin1_code":"08",
    "gn:asciiname":"Kablaandi",
    "gn:country_code":"SO",
    "gn:dem":22,
    "gn:feature_class":"P",
    "gn:feature_code":"PPL",
    "gn:name":"Kablaandi",
    "gn:population":0,
    "gn:timezone":"Africa/Mogadishu",
    "iso:country":"SO",
    "name:und_x_variant":[
        "Camtande",
        "Kablaandi"
    ],
    "wof:name":"Kablaandi",
    "wof:placetype":"locality"
},
  "geometry": {"coordinates":[42.7545,0.49099],"type":"Point"}
}