{
  "type": "Feature",
  "properties": {
    "gn:admin1_code":"9.0",
    "gn:asciiname":"Saydey",
    "gn:country_code":"SO",
    "gn:dem":6,
    "gn:feature_class":"P",
    "gn:feature_code":"PPL",
    "gn:name":"Saydey",
    "gn:population":0,
    "gn:timezone":"Africa/Mogadishu",
    "iso:country":"SO",
    "name:som_x_preferred":[
        "Saydey"
    ],
    "wof:name":"Saydey",
    "wof:placetype":"locality"
},
  "geometry": {"coordinates":[41.95633,-0.53188],"type":"Point"}
}