{
  "type": "Feature",
  "properties": {
    "gn:admin1_code":"06",
    "gn:asciiname":"Aaminaay",
    "gn:country_code":"SO",
    "gn:dem":123,
    "gn:feature_class":"P",
    "gn:feature_code":"PPL",
    "gn:name":"Aaminaay",
    "gn:population":0,
    "gn:timezone":"Africa/Mogadishu",
    "iso:country":"SO",
    "name:som_x_preferred":[
        "Aaminaay"
    ],
    "wof:name":"Aaminaay",
    "wof:placetype":"locality"
},
  "geometry": {"coordinates":[42.3531,2.29805],"type":"Point"}
}