{
  "type": "Feature",
  "properties": {
    "gn:admin1_code":"07",
    "gn:asciiname":"Doondheere",
    "gn:country_code":"SO",
    "gn:dem":132,
    "gn:feature_class":"P",
    "gn:feature_code":"PPL",
    "gn:name":"Doondheere",
    "gn:population":0,
    "gn:timezone":"Africa/Mogadishu",
    "iso:country":"SO",
    "name:som_x_preferred":[
        "Doondheere"
    ],
    "wof:name":"Doondheere",
    "wof:placetype":"locality"
},
  "geometry": {"coordinates":[45.5886,3.44048],"type":"Point"}
}