{
  "type": "Feature",
  "properties": {
    "gn:admin1_code":"09",
    "gn:asciiname":"Bilis Qooqaani",
    "gn:country_code":"SO",
    "gn:dem":34,
    "gn:feature_class":"P",
    "gn:feature_code":"PPL",
    "gn:name":"Bilis Qooqaani",
    "gn:population":0,
    "gn:timezone":"Africa/Mogadishu",
    "iso:country":"SO",
    "name:som_x_preferred":[
        "Bilis Qooqaani"
    ],
    "name:und_x_variant":[
        "Belesc Cogani",
        "Beles Gogani",
        "Beled-Sa Cacuni",
        "Beles Gugami"
    ],
    "wof:name":"Bilis Qooqaani",
    "wof:placetype":"locality"
},
  "geometry": {"coordinates":[41.7141,0.2837],"type":"Point"}
}