{
  "type": "Feature",
  "properties": {
    "gn:admin1_code":"14.0",
    "gn:asciiname":"Melled",
    "gn:country_code":"SO",
    "gn:dem":12,
    "gn:feature_class":"P",
    "gn:feature_code":"PPL",
    "gn:name":"Melled",
    "gn:population":0,
    "gn:timezone":"Africa/Mogadishu",
    "iso:country":"SO",
    "name:som_x_preferred":[
        "Melled"
    ],
    "name:und_x_variant":[
        "El Mellet",
        "Mollet",
        "Mellet"
    ],
    "wof:name":"Melled",
    "wof:placetype":"locality"
},
  "geometry": {"coordinates":[44.67568,1.64985],"type":"Point"}
}