{
  "type": "Feature",
  "properties": {
    "gn:admin1_code":"10",
    "gn:asciiname":"Ceel Gaan",
    "gn:country_code":"SO",
    "gn:dem":114,
    "gn:feature_class":"P",
    "gn:feature_code":"PPL",
    "gn:name":"Ceel Gaan",
    "gn:population":0,
    "gn:timezone":"Africa/Mogadishu",
    "iso:country":"SO",
    "name:und_x_variant":[
        "El Ghan"
    ],
    "wof:name":"Ceel Gaan",
    "wof:placetype":"locality"
},
  "geometry": {"coordinates":[48.03044000000001,4.59679],"type":"Point"}
}