{
  "type": "Feature",
  "properties": {
    "gn:admin1_code":"20.0",
    "gn:asciiname":"Xuunshaley",
    "gn:country_code":"SO",
    "gn:dem":1590,
    "gn:feature_class":"P",
    "gn:feature_code":"PPL",
    "gn:name":"Xuunshaley",
    "gn:population":0,
    "gn:timezone":"Africa/Mogadishu",
    "iso:country":"SO",
    "name:und_x_variant":[
        "Khunshaley",
        "Xuunshaley"
    ],
    "wof:name":"Xuunshaley",
    "wof:placetype":"locality"
},
  "geometry": {"coordinates":[43.41255,9.70474],"type":"Point"}
}