{
  "type": "Feature",
  "properties": {
    "gn:admin1_code":"20.0",
    "gn:asciiname":"Sobaad",
    "gn:country_code":"SO",
    "gn:dem":1064,
    "gn:feature_class":"P",
    "gn:feature_code":"PPL",
    "gn:name":"Sobaad",
    "gn:population":0,
    "gn:timezone":"Africa/Mogadishu",
    "iso:country":"SO",
    "wof:name":"Sobaad",
    "wof:placetype":"locality"
},
  "geometry": {"coordinates":[44.31446,9.70245],"type":"Point"}
}