{
  "type": "Feature",
  "properties": {
    "gn:admin1_code":"14.0",
    "gn:asciiname":"Webi Nuurow",
    "gn:country_code":"SO",
    "gn:dem":53,
    "gn:feature_class":"P",
    "gn:feature_code":"PPL",
    "gn:name":"Webi Nuurow",
    "gn:population":0,
    "gn:timezone":"Africa/Mogadishu",
    "iso:country":"SO",
    "name:som_x_preferred":[
        "Webi Nuurow"
    ],
    "wof:name":"Webi Nuurow",
    "wof:placetype":"locality"
},
  "geometry": {"coordinates":[43.9004,1.3714],"type":"Point"}
}