{
  "type": "Feature",
  "properties": {
    "gn:admin1_code":"09",
    "gn:asciiname":"Haadweyn",
    "gn:country_code":"SO",
    "gn:dem":6,
    "gn:feature_class":"P",
    "gn:feature_code":"PPL",
    "gn:name":"Haadweyn",
    "gn:population":0,
    "gn:timezone":"Africa/Mogadishu",
    "iso:country":"SO",
    "name:som_x_preferred":[
        "Haadweyn"
    ],
    "name:und_x_variant":[
        "Khadueyn"
    ],
    "wof:name":"Haadweyn",
    "wof:placetype":"locality"
},
  "geometry": {"coordinates":[42.29946,-0.36945],"type":"Point"}
}