{
  "type": "Feature",
  "properties": {
    "gn:admin1_code":"04",
    "gn:asciiname":"Balad Al Amiin",
    "gn:country_code":"SO",
    "gn:dem":272,
    "gn:feature_class":"P",
    "gn:feature_code":"PPL",
    "gn:name":"Balad Al Amiin",
    "gn:population":0,
    "gn:timezone":"Africa/Mogadishu",
    "iso:country":"SO",
    "name:som_x_preferred":[
        "Balad Al Amiin"
    ],
    "wof:name":"Balad Al Amiin",
    "wof:placetype":"locality"
},
  "geometry": {"coordinates":[43.74573,2.86871],"type":"Point"}
}