{
  "type": "Feature",
  "properties": {
    "gn:admin1_code":"14.0",
    "gn:asciiname":"War Maxan",
    "gn:country_code":"SO",
    "gn:dem":87,
    "gn:feature_class":"P",
    "gn:feature_code":"PPL",
    "gn:name":"War Maxan",
    "gn:population":0,
    "gn:timezone":"Africa/Mogadishu",
    "iso:country":"SO",
    "name:som_x_preferred":[
        "War Maxan"
    ],
    "wof:name":"War Maxan",
    "wof:placetype":"locality"
},
  "geometry": {"coordinates":[45.02131,2.39733],"type":"Point"}
}