{
  "type": "Feature",
  "properties": {
    "gn:admin1_code":"04",
    "gn:asciiname":"Boorka",
    "gn:country_code":"SO",
    "gn:dem":482,
    "gn:feature_class":"P",
    "gn:feature_code":"PPL",
    "gn:name":"Boorka",
    "gn:population":0,
    "gn:timezone":"Africa/Mogadishu",
    "iso:country":"SO",
    "name:som_x_preferred":[
        "Boorka"
    ],
    "wof:name":"Boorka",
    "wof:placetype":"locality"
},
  "geometry": {"coordinates":[43.4664,3.2159],"type":"Point"}
}