{
  "type": "Feature",
  "properties": {
    "gn:admin1_code":"13",
    "gn:asciiname":"Kaxarey",
    "gn:country_code":"SO",
    "gn:dem":105,
    "gn:feature_class":"P",
    "gn:feature_code":"PPL",
    "gn:name":"Kaxarey",
    "gn:population":0,
    "gn:timezone":"Africa/Mogadishu",
    "iso:country":"SO",
    "name:som_x_preferred":[
        "Kaxarey"
    ],
    "wof:name":"Kaxarey",
    "wof:placetype":"locality"
},
  "geometry": {"coordinates":[45.5695,2.7801],"type":"Point"}
}