{
  "type": "Feature",
  "properties": {
    "gn:admin1_code":"9.0",
    "gn:asciiname":"Qulcaaley",
    "gn:country_code":"SO",
    "gn:dem":6,
    "gn:feature_class":"P",
    "gn:feature_code":"PPL",
    "gn:name":"Qulcaaley",
    "gn:population":0,
    "gn:timezone":"Africa/Mogadishu",
    "iso:country":"SO",
    "wof:name":"Qulcaaley",
    "wof:placetype":"locality"
},
  "geometry": {"coordinates":[42.37581,0.0702],"type":"Point"}
}