{
  "type": "Feature",
  "properties": {
    "gn:admin1_code":"04",
    "gn:asciiname":"Aw Humoow",
    "gn:country_code":"SO",
    "gn:dem":183,
    "gn:feature_class":"P",
    "gn:feature_code":"PPL",
    "gn:name":"Aw Humoow",
    "gn:population":0,
    "gn:timezone":"Africa/Mogadishu",
    "iso:country":"SO",
    "name:som_x_preferred":[
        "Aw Humoow"
    ],
    "wof:name":"Aw Humoow",
    "wof:placetype":"locality"
},
  "geometry": {"coordinates":[44.2463,2.8038],"type":"Point"}
}