{
  "type": "Feature",
  "properties": {
    "gn:admin1_code":"19.0",
    "gn:asciiname":"Qudhacsafar",
    "gn:country_code":"SO",
    "gn:dem":831,
    "gn:feature_class":"P",
    "gn:feature_code":"PPL",
    "gn:name":"Qudhacsafar",
    "gn:population":0,
    "gn:timezone":"Africa/Mogadishu",
    "iso:country":"SO",
    "wof:name":"Qudhacsafar",
    "wof:placetype":"locality"
},
  "geometry": {"coordinates":[45.80998,8.77529],"type":"Point"}
}