{
  "type": "Feature",
  "properties": {
    "gn:admin1_code":"04",
    "gn:asciiname":"Cadey Qaboobe",
    "gn:country_code":"SO",
    "gn:dem":330,
    "gn:feature_class":"P",
    "gn:feature_code":"PPL",
    "gn:name":"Cadey Qaboobe",
    "gn:population":0,
    "gn:timezone":"Africa/Mogadishu",
    "iso:country":"SO",
    "name:und_x_variant":[
        "Edain Caboba"
    ],
    "wof:name":"Cadey Qaboobe",
    "wof:placetype":"locality"
},
  "geometry": {"coordinates":[42.96667,3.01667],"type":"Point"}
}