{
  "type": "Feature",
  "properties": {
    "gn:admin1_code":"10",
    "gn:asciiname":"Hen Daier",
    "gn:cc2":"SO",
    "gn:country_code":"SO",
    "gn:dem":11,
    "gn:feature_class":"P",
    "gn:feature_code":"PPL",
    "gn:name":"Hen Daier",
    "gn:population":0,
    "gn:timezone":"Africa/Mogadishu",
    "iso:country":"SO",
    "name:und_x_variant":[
        "Hen Dajer",
        "Hen Daier"
    ],
    "wof:name":"Hen Daier",
    "wof:placetype":"locality"
},
  "geometry": {"coordinates":[48.35611,5.15],"type":"Point"}
}