{
  "type": "Feature",
  "properties": {
    "gn:admin1_code":"3.0",
    "gn:asciiname":"Seen Yar",
    "gn:country_code":"SO",
    "gn:dem":62,
    "gn:feature_class":"P",
    "gn:feature_code":"PPL",
    "gn:name":"Seen Yar",
    "gn:population":0,
    "gn:timezone":"Africa/Mogadishu",
    "iso:country":"SO",
    "name:som_x_preferred":[
        "Seen Yar"
    ],
    "wof:name":"Seen Yar",
    "wof:placetype":"locality"
},
  "geometry": {"coordinates":[51.20332,11.77069],"type":"Point"}
}