{
  "type": "Feature",
  "properties": {
    "gn:admin1_code":"20.0",
    "gn:asciiname":"Megag Wein",
    "gn:country_code":"SO",
    "gn:dem":1174,
    "gn:feature_class":"P",
    "gn:feature_code":"PPL",
    "gn:name":"Megag Wein",
    "gn:population":0,
    "gn:timezone":"Africa/Mogadishu",
    "iso:country":"SO",
    "wof:name":"Megag Wein",
    "wof:placetype":"locality"
},
  "geometry": {"coordinates":[44.33333,9.38333],"type":"Point"}
}