{
  "type": "Feature",
  "properties": {
    "gn:admin1_code":"4.0",
    "gn:asciiname":"Nasib",
    "gn:country_code":"SO",
    "gn:dem":498,
    "gn:feature_class":"P",
    "gn:feature_code":"PPL",
    "gn:name":"Nasib",
    "gn:population":0,
    "gn:timezone":"Africa/Mogadishu",
    "iso:country":"SO",
    "name:som_x_preferred":[
        "Nasib"
    ],
    "wof:name":"Nasib",
    "wof:placetype":"locality"
},
  "geometry": {"coordinates":[43.602,3.2114],"type":"Point"}
}