{
  "type": "Feature",
  "properties": {
    "gn:admin1_code":"10",
    "gn:asciiname":"Bissig Gundere",
    "gn:country_code":"SO",
    "gn:dem":243,
    "gn:feature_class":"P",
    "gn:feature_code":"PPL",
    "gn:name":"Bissig Gundere",
    "gn:population":0,
    "gn:timezone":"Africa/Mogadishu",
    "iso:country":"SO",
    "wof:name":"Bissig Gundere",
    "wof:placetype":"locality"
},
  "geometry": {"coordinates":[48.41667,7.13333],"type":"Point"}
}