{
  "type": "Feature",
  "properties": {
    "gn:admin1_code":"04",
    "gn:asciiname":"Giuarei",
    "gn:country_code":"SO",
    "gn:dem":217,
    "gn:feature_class":"P",
    "gn:feature_code":"PPL",
    "gn:name":"Giuarei",
    "gn:population":0,
    "gn:timezone":"Africa/Mogadishu",
    "iso:country":"SO",
    "wof:name":"Giuarei",
    "wof:placetype":"locality"
},
  "geometry": {"coordinates":[42.71667,1.96667],"type":"Point"}
}