{
  "type": "Feature",
  "properties": {
    "gn:admin1_code":"05",
    "gn:asciiname":"Xingomod",
    "gn:country_code":"SO",
    "gn:dem":259,
    "gn:feature_class":"P",
    "gn:feature_code":"PPL",
    "gn:name":"Xingomod",
    "gn:population":0,
    "gn:timezone":"Africa/Mogadishu",
    "iso:country":"SO",
    "name:und_x_variant":[
        "En Gomot"
    ],
    "wof:name":"Xingomod",
    "wof:placetype":"locality"
},
  "geometry": {"coordinates":[46.99242,6.11972],"type":"Point"}
}