{
  "type": "Feature",
  "properties": {
    "gn:admin1_code":"14",
    "gn:asciiname":"Keeroy",
    "gn:country_code":"SO",
    "gn:dem":57,
    "gn:feature_class":"P",
    "gn:feature_code":"PPL",
    "gn:name":"Keeroy",
    "gn:population":0,
    "gn:timezone":"Africa/Mogadishu",
    "iso:country":"SO",
    "name:som_x_preferred":[
        "Keeroy"
    ],
    "wof:name":"Keeroy",
    "wof:placetype":"locality"
},
  "geometry": {"coordinates":[44.0686,1.56206],"type":"Point"}
}