{
  "type": "Feature",
  "properties": {
    "gn:admin1_code":"3.0",
    "gn:asciiname":"Sireis",
    "gn:cc2":"SO",
    "gn:country_code":"SO",
    "gn:dem":380,
    "gn:feature_class":"P",
    "gn:feature_code":"PPL",
    "gn:name":"Sireis",
    "gn:population":0,
    "gn:timezone":"Africa/Mogadishu",
    "iso:country":"SO",
    "name:und_x_variant":[
        "Sereye",
        "Sireis"
    ],
    "wof:name":"Sireis",
    "wof:placetype":"locality"
},
  "geometry": {"coordinates":[51.05,11.78333],"type":"Point"}
}