{
  "type": "Feature",
  "properties": {
    "gn:admin1_code":"9.0",
    "gn:asciiname":"Sheekh Cabdi Muudey",
    "gn:country_code":"SO",
    "gn:dem":19,
    "gn:feature_class":"P",
    "gn:feature_code":"PPL",
    "gn:name":"Sheekh Cabdi Muudey",
    "gn:population":0,
    "gn:timezone":"Africa/Mogadishu",
    "iso:country":"SO",
    "wof:name":"Sheekh Cabdi Muudey",
    "wof:placetype":"locality"
},
  "geometry": {"coordinates":[42.81167,0.30922],"type":"Point"}
}