{
  "type": "Feature",
  "properties": {
    "gn:admin1_code":"9.0",
    "gn:asciiname":"Makungo",
    "gn:cc2":"SO",
    "gn:country_code":"SO",
    "gn:dem":37,
    "gn:feature_class":"P",
    "gn:feature_code":"PPL",
    "gn:name":"Makungo",
    "gn:population":0,
    "gn:timezone":"Africa/Mogadishu",
    "iso:country":"SO",
    "name:und_x_variant":[
        "Gilal\u00f9",
        "Mabungo",
        "Makungo"
    ],
    "wof:name":"Makungo",
    "wof:placetype":"locality"
},
  "geometry": {"coordinates":[42.58333,0.81667],"type":"Point"}
}