{
  "type": "Feature",
  "properties": {
    "gn:admin1_code":"14",
    "gn:asciiname":"Galool Dheere",
    "gn:country_code":"SO",
    "gn:dem":85,
    "gn:feature_class":"P",
    "gn:feature_code":"PPL",
    "gn:name":"Galool Dheere",
    "gn:population":0,
    "gn:timezone":"Africa/Mogadishu",
    "iso:country":"SO",
    "name:som_x_preferred":[
        "Galool Dheere"
    ],
    "wof:name":"Galool Dheere",
    "wof:placetype":"locality"
},
  "geometry": {"coordinates":[44.81305,2.47138],"type":"Point"}
}