{
  "type": "Feature",
  "properties": {
    "gn:admin1_code":"13",
    "gn:asciiname":"Ceellow",
    "gn:country_code":"SO",
    "gn:dem":28,
    "gn:feature_class":"P",
    "gn:feature_code":"PPL",
    "gn:name":"Ceellow",
    "gn:population":0,
    "gn:timezone":"Africa/Mogadishu",
    "iso:country":"SO",
    "name:som_x_preferred":[
        "Ceellow"
    ],
    "wof:name":"Ceellow",
    "wof:placetype":"locality"
},
  "geometry": {"coordinates":[45.6384,2.2989],"type":"Point"}
}