{
  "type": "Feature",
  "properties": {
    "gn:admin1_code":"4.0",
    "gn:asciiname":"Qalmoow",
    "gn:country_code":"SO",
    "gn:dem":491,
    "gn:feature_class":"P",
    "gn:feature_code":"PPL",
    "gn:name":"Qalmoow",
    "gn:population":0,
    "gn:timezone":"Africa/Mogadishu",
    "iso:country":"SO",
    "name:som_x_preferred":[
        "Qalmoow"
    ],
    "wof:name":"Qalmoow",
    "wof:placetype":"locality"
},
  "geometry": {"coordinates":[43.5508,3.5843],"type":"Point"}
}