{
  "type": "Feature",
  "properties": {
    "gn:admin1_code":"14",
    "gn:asciiname":"Biliq Roboow",
    "gn:country_code":"SO",
    "gn:dem":41,
    "gn:feature_class":"P",
    "gn:feature_code":"PPL",
    "gn:name":"Biliq Roboow",
    "gn:population":0,
    "gn:timezone":"Africa/Mogadishu",
    "iso:country":"SO",
    "name:som_x_preferred":[
        "Biliq Roboow"
    ],
    "name:und_x_variant":[
        "Belet Robo"
    ],
    "wof:name":"Biliq Roboow",
    "wof:placetype":"locality"
},
  "geometry": {"coordinates":[43.6866,1.0996],"type":"Point"}
}