{
  "type": "Feature",
  "properties": {
    "gn:admin1_code":"13",
    "gn:asciiname":"Jameeco Misra",
    "gn:country_code":"SO",
    "gn:dem":103,
    "gn:feature_class":"P",
    "gn:feature_code":"PPL",
    "gn:name":"Jameeco Misra",
    "gn:population":0,
    "gn:timezone":"Africa/Mogadishu",
    "iso:country":"SO",
    "name:som_x_preferred":[
        "Jameeco Misra"
    ],
    "name:und_x_variant":[
        "Misra"
    ],
    "wof:name":"Jameeco Misra",
    "wof:placetype":"locality"
},
  "geometry": {"coordinates":[45.4953,2.5721],"type":"Point"}
}