{
  "type": "Feature",
  "properties": {
    "gn:admin1_code":"19",
    "gn:asciiname":"Cabdi Dheere",
    "gn:country_code":"SO",
    "gn:dem":1036,
    "gn:feature_class":"P",
    "gn:feature_code":"PPL",
    "gn:name":"Cabdi Dheere",
    "gn:population":0,
    "gn:timezone":"Africa/Mogadishu",
    "iso:country":"SO",
    "name:som_x_preferred":[
        "Cabdi Dheere"
    ],
    "name:und_x_variant":[
        "Bale Abdi Dere"
    ],
    "wof:name":"Cabdi Dheere",
    "wof:placetype":"locality"
},
  "geometry": {"coordinates":[44.78465,9.07949],"type":"Point"}
}