{
  "type": "Feature",
  "properties": {
    "gn:admin1_code":"20",
    "gn:asciiname":"Horahaadley",
    "gn:country_code":"SO",
    "gn:dem":1016,
    "gn:feature_class":"P",
    "gn:feature_code":"PPLL",
    "gn:name":"Horahaadley",
    "gn:population":0,
    "gn:timezone":"Africa/Mogadishu",
    "iso:country":"SO",
    "wof:name":"Horahaadley",
    "wof:placetype":"locality"
},
  "geometry": {"coordinates":[44.03786,9.85798],"type":"Point"}
}