{
  "type": "Feature",
  "properties": {
    "gn:admin1_code":"04",
    "gn:asciiname":"Dudumiya",
    "gn:country_code":"SO",
    "gn:dem":194,
    "gn:feature_class":"P",
    "gn:feature_code":"PPL",
    "gn:name":"Dudumiya",
    "gn:population":0,
    "gn:timezone":"Africa/Mogadishu",
    "iso:country":"SO",
    "name:som_x_preferred":[
        "Dudumiya"
    ],
    "name:und_x_variant":[
        "Duddumi\u00e0"
    ],
    "wof:name":"Dudumiya",
    "wof:placetype":"locality"
},
  "geometry": {"coordinates":[44.12366,2.83572],"type":"Point"}
}