{
  "type": "Feature",
  "properties": {
    "gn:admin1_code":"14",
    "gn:asciiname":"Ceel Jaalle",
    "gn:country_code":"SO",
    "gn:dem":25,
    "gn:feature_class":"P",
    "gn:feature_code":"PPL",
    "gn:name":"Ceel Jaalle",
    "gn:population":0,
    "gn:timezone":"Africa/Mogadishu",
    "iso:country":"SO",
    "name:som_x_preferred":[
        "Ceel Jaalle"
    ],
    "wof:name":"Ceel Jaalle",
    "wof:placetype":"locality"
},
  "geometry": {"coordinates":[44.7236,1.6831],"type":"Point"}
}