{
  "type": "Feature",
  "properties": {
    "gn:admin1_code":"13",
    "gn:asciiname":"Damaley",
    "gn:country_code":"SO",
    "gn:dem":102,
    "gn:feature_class":"P",
    "gn:feature_code":"PPL",
    "gn:name":"Damaley",
    "gn:population":0,
    "gn:timezone":"Africa/Mogadishu",
    "iso:country":"SO",
    "name:som_x_preferred":[
        "Damaley"
    ],
    "wof:name":"Damaley",
    "wof:placetype":"locality"
},
  "geometry": {"coordinates":[45.4882,2.5077],"type":"Point"}
}