{
  "type": "Feature",
  "properties": {
    "gn:admin1_code":"8.0",
    "gn:asciiname":"Weel Shimbir",
    "gn:country_code":"SO",
    "gn:dem":24,
    "gn:feature_class":"P",
    "gn:feature_code":"PPL",
    "gn:name":"Weel Shimbir",
    "gn:population":0,
    "gn:timezone":"Africa/Mogadishu",
    "iso:country":"SO",
    "name:und_x_variant":[
        "Uel Scimber",
        "Weel Shimbir"
    ],
    "wof:name":"Weel Shimbir",
    "wof:placetype":"locality"
},
  "geometry": {"coordinates":[43.05,0.61667],"type":"Point"}
}