{
  "type": "Feature",
  "properties": {
    "gn:admin1_code":"06",
    "gn:asciiname":"Cursi",
    "gn:country_code":"SO",
    "gn:dem":308,
    "gn:feature_class":"P",
    "gn:feature_code":"PPL",
    "gn:name":"Cursi",
    "gn:population":0,
    "gn:timezone":"Africa/Mogadishu",
    "iso:country":"SO",
    "wof:name":"Cursi",
    "wof:placetype":"locality"
},
  "geometry": {"coordinates":[41.16667,2.46667],"type":"Point"}
}