{
  "type": "Feature",
  "properties": {
    "gn:admin1_code":"06",
    "gn:asciiname":"Cursi",
    "gn:country_code":"SO",
    "gn:dem":308,
    "gn:feature_class":"P",
    "gn:feature_code":"PPL",
    "gn:name":"Cursi",
    "gn:population":0,
    "gn:timezone":"Africa/Mogadishu",
    "iso:country":"SO",
    "name:ara_x_preferred":[
        "\u0643\u0648\u0631\u0633\u064a"
    ],
    "name:azb_x_preferred":[
        "\u06a9\u0648\u0631\u0632\u06cc"
    ],
    "name:bel_x_preferred":[
        "\u041a\u0443\u0440\u0441\u0456"
    ],
    "name:bul_x_preferred":[
        "\u041a\u0443\u0440\u0441\u0438"
    ],
    "name:cat_x_preferred":[
        "Cursi"
    ],
    "name:ceb_x_preferred":[
        "Cursi"
    ],
    "name:deu_x_preferred":[
        "Cursi"
    ],
    "name:epo_x_preferred":[
        "Cursi"
    ],
    "name:eus_x_preferred":[
        "Cursi"
    ],
    "name:fas_x_preferred":[
        "\u06a9\u0648\u0631\u0632\u06cc"
    ],
    "name:fra_x_preferred":[
        "Cursi"
    ],
    "name:hun_x_preferred":[
        "Cursi"
    ],
    "name:hye_x_preferred":[
        "\u053f\u0578\u0582\u0580\u057d\u056b"
    ],
    "name:ina_x_preferred":[
        "Cursi"
    ],
    "name:ita_x_preferred":[
        "Cursi"
    ],
    "name:jpn_x_preferred":[
        "\u30af\u30eb\u30b7"
    ],
    "name:lat_x_preferred":[
        "Cursium"
    ],
    "name:lmo_x_preferred":[
        "Cursi"
    ],
    "name:msa_x_preferred":[
        "Cursi"
    ],
    "name:nap_x_preferred":[
        "Cursi"
    ],
    "name:nld_x_preferred":[
        "Cursi"
    ],
    "name:pms_x_preferred":[
        "Cursi"
    ],
    "name:pol_x_preferred":[
        "Cursi"
    ],
    "name:por_x_preferred":[
        "Cursi"
    ],
    "name:ron_x_preferred":[
        "Cursi"
    ],
    "name:rus_x_preferred":[
        "\u041a\u0443\u0440\u0441\u0438"
    ],
    "name:scn_x_preferred":[
        "Curse"
    ],
    "name:spa_x_preferred":[
        "Cursi"
    ],
    "name:srp_x_preferred":[
        "\u041a\u0443\u0440\u0441\u0438"
    ],
    "name:tgl_x_preferred":[
        "Cursi"
    ],
    "name:ukr_x_preferred":[
        "\u041a\u0443\u0440\u0441\u0456"
    ],
    "name:uzb_x_preferred":[
        "Cursi"
    ],
    "name:vol_x_preferred":[
        "Cursi"
    ],
    "name:war_x_preferred":[
        "Cursi"
    ],
    "name:zho_x_preferred":[
        "\u5e93\u5c14\u897f"
    ],
    "wof:name":"Cursi",
    "wof:placetype":"locality"
},
  "geometry": {"coordinates":[41.16667,2.46667],"type":"Point"}
}