{
  "type": "Feature",
  "properties": {
    "gn:admin1_code":"14",
    "gn:asciiname":"Degeelow",
    "gn:country_code":"SO",
    "gn:dem":93,
    "gn:feature_class":"P",
    "gn:feature_code":"PPL",
    "gn:name":"Degeelow",
    "gn:population":0,
    "gn:timezone":"Africa/Mogadishu",
    "iso:country":"SO",
    "name:som_x_preferred":[
        "Degeelow"
    ],
    "wof:name":"Degeelow",
    "wof:placetype":"locality"
},
  "geometry": {"coordinates":[45.07919,2.64273],"type":"Point"}
}