{
  "type": "Feature",
  "properties": {
    "gn:admin1_code":"14",
    "gn:asciiname":"Aw Mayow",
    "gn:country_code":"SO",
    "gn:dem":95,
    "gn:feature_class":"P",
    "gn:feature_code":"PPL",
    "gn:name":"Aw Mayow",
    "gn:population":0,
    "gn:timezone":"Africa/Mogadishu",
    "iso:country":"SO",
    "name:som_x_preferred":[
        "Aw Mayow"
    ],
    "wof:name":"Aw Mayow",
    "wof:placetype":"locality"
},
  "geometry": {"coordinates":[44.93648,2.71367],"type":"Point"}
}