{
  "type": "Feature",
  "properties": {
    "gn:admin1_code":"4.0",
    "gn:asciiname":"Sheeble",
    "gn:country_code":"SO",
    "gn:dem":230,
    "gn:feature_class":"P",
    "gn:feature_code":"PPL",
    "gn:name":"Sheeble",
    "gn:population":0,
    "gn:timezone":"Africa/Mogadishu",
    "iso:country":"SO",
    "name:som_x_preferred":[
        "Sheeble"
    ],
    "wof:name":"Sheeble",
    "wof:placetype":"locality"
},
  "geometry": {"coordinates":[44.02355,2.85103],"type":"Point"}
}