{
  "type": "Feature",
  "properties": {
    "gn:admin1_code":"9.0",
    "gn:asciiname":"Tuunni Toorre",
    "gn:country_code":"SO",
    "gn:dem":13,
    "gn:feature_class":"P",
    "gn:feature_code":"PPL",
    "gn:name":"Tuunni Toorre",
    "gn:population":0,
    "gn:timezone":"Africa/Mogadishu",
    "iso:country":"SO",
    "name:und_x_variant":[
        "Tunni Torre",
        "Tuunni Toorre"
    ],
    "wof:name":"Tuunni Toorre",
    "wof:placetype":"locality"
},
  "geometry": {"coordinates":[42.79161,0.18549],"type":"Point"}
}