{
  "type": "Feature",
  "properties": {
    "iso:country":"SO",
    "name:baq_x_preferred":[
        "Harardhere"
    ],
    "name:cat_x_preferred":[
        "Harardhere"
    ],
    "name:chi_x_preferred":[
        "\u54c8\u62c9\u4ee3\u96f7"
    ],
    "name:deu_x_preferred":[
        "Harardheere"
    ],
    "name:dut_x_preferred":[
        "Harardheere"
    ],
    "name:eng_x_preferred":[
        "Harardhere"
    ],
    "name:est_x_preferred":[
        "Xarardheere"
    ],
    "name:eus_x_preferred":[
        "Harardhere"
    ],
    "name:fra_x_preferred":[
        "Harardhere"
    ],
    "name:fre_x_preferred":[
        "Harardhere"
    ],
    "name:ger_x_preferred":[
        "Harardheere"
    ],
    "name:ita_x_preferred":[
        "Harardera"
    ],
    "name:jpn_x_preferred":[
        "\u30cf\u30e9\u30fc\u30c9\u30d2\u30e4\u30fc"
    ],
    "name:nld_x_preferred":[
        "Harardheere"
    ],
    "name:pol_x_preferred":[
        "Xarardheere"
    ],
    "name:por_x_preferred":[
        "Harardhere"
    ],
    "name:ron_x_preferred":[
        "Harardhere"
    ],
    "name:rum_x_preferred":[
        "Harardhere"
    ],
    "name:som_x_preferred":[
        "Xarardheere"
    ],
    "name:spa_x_preferred":[
        "Harardhere"
    ],
    "name:unk_x_variant":[
        "Adim"
    ],
    "name:urd_x_preferred":[
        "\u06c1\u0631\u0627\u0631\u062f\u06cc\u0631\u06cc"
    ],
    "qs:gn_country":"SO",
    "qs:gn_fcode":"PPL",
    "qs:gn_pop":2018,
    "qs:name":"Harardera",
    "qs:name_adm0":"Somalia",
    "qs:name_adm1":"Mudug",
    "qs:photos":0,
    "qs:photos_1k":0,
    "qs:photos_9k":0,
    "qs:photos_9r":0,
    "qs:photos_all":0,
    "qs:photos_sr":0,
    "qs:placetype":"Town",
    "qs:pop_sr":"4",
    "qs:woe_adm0":23424949,
    "wd:wordcount":78,
    "wof:name":"Harardera",
    "wof:placetype":"locality",
    "wof:population":2018
},
  "geometry": {"coordinates":[47.8575,4.6544],"type":"Point"}
}