{
  "type": "Feature",
  "properties": {
    "gn:admin1_code":"14",
    "gn:asciiname":"Kibiile",
    "gn:country_code":"SO",
    "gn:dem":72,
    "gn:feature_class":"P",
    "gn:feature_code":"PPL",
    "gn:name":"Kibiile",
    "gn:population":0,
    "gn:timezone":"Africa/Mogadishu",
    "iso:country":"SO",
    "name:som_x_preferred":[
        "Kibiile"
    ],
    "name:und_x_variant":[
        "Kibille"
    ],
    "wof:name":"Kibiile",
    "wof:placetype":"locality"
},
  "geometry": {"coordinates":[44.6669,1.7508],"type":"Point"}
}