{
  "type": "Feature",
  "properties": {
    "gn:admin1_code":"14",
    "gn:asciiname":"Arieegle",
    "gn:country_code":"SO",
    "gn:dem":92,
    "gn:feature_class":"P",
    "gn:feature_code":"PPL",
    "gn:name":"Arieegle",
    "gn:population":0,
    "gn:timezone":"Africa/Mogadishu",
    "iso:country":"SO",
    "name:som_x_preferred":[
        "Arieegle"
    ],
    "wof:name":"Arieegle",
    "wof:placetype":"locality"
},
  "geometry": {"coordinates":[44.92724000000001,2.51195],"type":"Point"}
}