{
  "type": "Feature",
  "properties": {
    "gn:admin1_code":"13.0",
    "gn:asciiname":"Mubaarak",
    "gn:country_code":"SO",
    "gn:dem":109,
    "gn:feature_class":"P",
    "gn:feature_code":"PPL",
    "gn:name":"Mubaarak",
    "gn:population":0,
    "gn:timezone":"Africa/Mogadishu",
    "iso:country":"SO",
    "name:som_x_preferred":[
        "Mubaarak"
    ],
    "name:und_x_variant":[
        "Mobarech"
    ],
    "wof:name":"Mubaarak",
    "wof:placetype":"locality"
},
  "geometry": {"coordinates":[45.6337,2.7132],"type":"Point"}
}