{
  "type": "Feature",
  "properties": {
    "gn:admin1_code":"20",
    "gn:asciiname":"Cali Xaydh",
    "gn:country_code":"SO",
    "gn:dem":1045,
    "gn:feature_class":"P",
    "gn:feature_code":"PPL",
    "gn:name":"Cali Xaydh",
    "gn:population":0,
    "gn:timezone":"Africa/Mogadishu",
    "iso:country":"SO",
    "name:som_x_preferred":[
        "Cali Xaydh"
    ],
    "wof:name":"Cali Xaydh",
    "wof:placetype":"locality"
},
  "geometry": {"coordinates":[43.78552,10.04528],"type":"Point"}
}