{
  "type": "Feature",
  "properties": {
    "gn:admin1_code":"07",
    "gn:asciiname":"Habas Weyn",
    "gn:country_code":"SO",
    "gn:dem":183,
    "gn:feature_class":"P",
    "gn:feature_code":"PPL",
    "gn:name":"Habas Weyn",
    "gn:population":0,
    "gn:timezone":"Africa/Mogadishu",
    "iso:country":"SO",
    "name:som_x_preferred":[
        "Habas Weyn"
    ],
    "name:und_x_variant":[
        "Pozzi",
        "Den Ueine",
        "Den Uene",
        "Habas Weyn"
    ],
    "wof:name":"Habas Weyn",
    "wof:placetype":"locality"
},
  "geometry": {"coordinates":[45.59842,4.17875],"type":"Point"}
}