{
  "type": "Feature",
  "properties": {
    "gn:admin1_code":"14.0",
    "gn:asciiname":"Soblaale",
    "gn:country_code":"SO",
    "gn:dem":49,
    "gn:feature_class":"P",
    "gn:feature_code":"PPLL",
    "gn:name":"Soblaale",
    "gn:population":0,
    "gn:timezone":"Africa/Mogadishu",
    "iso:country":"SO",
    "name:som_x_preferred":[
        "Soblaale"
    ],
    "wof:name":"Soblaale",
    "wof:placetype":"locality"
},
  "geometry": {"coordinates":[43.8726,1.3158],"type":"Point"}
}