{
  "type": "Feature",
  "properties": {
    "gn:admin1_code":"04",
    "gn:asciiname":"Aw Yarow Maroodiyoow",
    "gn:country_code":"SO",
    "gn:dem":194,
    "gn:feature_class":"P",
    "gn:feature_code":"PPL",
    "gn:name":"Aw Yarow Maroodiyoow",
    "gn:population":0,
    "gn:timezone":"Africa/Mogadishu",
    "iso:country":"SO",
    "name:som_x_preferred":[
        "Aw Yarow Maroodiyoow"
    ],
    "wof:name":"Aw Yarow Maroodiyoow",
    "wof:placetype":"locality"
},
  "geometry": {"coordinates":[44.2478,2.8449],"type":"Point"}
}