{
  "type": "Feature",
  "properties": {
    "gn:admin1_code":"06",
    "gn:asciiname":"Degta Reidab",
    "gn:country_code":"SO",
    "gn:dem":206,
    "gn:feature_class":"P",
    "gn:feature_code":"PPL",
    "gn:name":"Degta Reidab",
    "gn:population":0,
    "gn:timezone":"Africa/Mogadishu",
    "iso:country":"SO",
    "wof:name":"Degta Reidab",
    "wof:placetype":"locality"
},
  "geometry": {"coordinates":[42.28333,2.85],"type":"Point"}
}