{
  "type": "Feature",
  "properties": {
    "gn:admin1_code":"14.0",
    "gn:asciiname":"Nagaadweyne",
    "gn:country_code":"SO",
    "gn:dem":72,
    "gn:feature_class":"P",
    "gn:feature_code":"PPL",
    "gn:name":"Nagaadweyne",
    "gn:population":0,
    "gn:timezone":"Africa/Mogadishu",
    "iso:country":"SO",
    "name:som_x_preferred":[
        "Nagaadweyne"
    ],
    "wof:name":"Nagaadweyne",
    "wof:placetype":"locality"
},
  "geometry": {"coordinates":[44.7934,1.8743],"type":"Point"}
}