{
  "type": "Feature",
  "properties": {
    "gn:admin1_code":"13",
    "gn:asciiname":"Caamir Gacandheer",
    "gn:country_code":"SO",
    "gn:dem":35,
    "gn:feature_class":"P",
    "gn:feature_code":"PPL",
    "gn:name":"Caamir Gacandheer",
    "gn:population":0,
    "gn:timezone":"Africa/Mogadishu",
    "iso:country":"SO",
    "name:som_x_preferred":[
        "Caamir Gacandheer"
    ],
    "wof:name":"Caamir Gacandheer",
    "wof:placetype":"locality"
},
  "geometry": {"coordinates":[45.6079,2.2792],"type":"Point"}
}