{
  "type": "Feature",
  "properties": {
    "gn:admin1_code":"08",
    "gn:asciiname":"Daad Jerow",
    "gn:country_code":"SO",
    "gn:dem":31,
    "gn:feature_class":"P",
    "gn:feature_code":"PPL",
    "gn:name":"Daad Jerow",
    "gn:population":0,
    "gn:timezone":"Africa/Mogadishu",
    "iso:country":"SO",
    "wof:name":"Daad Jerow",
    "wof:placetype":"locality"
},
  "geometry": {"coordinates":[43.19136,0.83726],"type":"Point"}
}