{
  "type": "Feature",
  "properties": {
    "gn:admin1_code":"7.0",
    "gn:asciiname":"Qurac Jafle",
    "gn:country_code":"SO",
    "gn:dem":125,
    "gn:feature_class":"P",
    "gn:feature_code":"PPL",
    "gn:name":"Qurac Jafle",
    "gn:population":0,
    "gn:timezone":"Africa/Mogadishu",
    "iso:country":"SO",
    "name:som_x_preferred":[
        "Qurac Jafle"
    ],
    "wof:name":"Qurac Jafle",
    "wof:placetype":"locality"
},
  "geometry": {"coordinates":[45.53954,3.31119],"type":"Point"}
}