{
  "type": "Feature",
  "properties": {
    "gn:admin1_code":"20",
    "gn:asciiname":"Biyadhanane",
    "gn:country_code":"SO",
    "gn:dem":1091,
    "gn:feature_class":"P",
    "gn:feature_code":"PPL",
    "gn:name":"Biyadhanane",
    "gn:population":0,
    "gn:timezone":"Africa/Mogadishu",
    "iso:country":"SO",
    "wof:name":"Biyadhanane",
    "wof:placetype":"locality"
},
  "geometry": {"coordinates":[44.29109,9.67454],"type":"Point"}
}