{
  "type": "Feature",
  "properties": {
    "gn:admin1_code":"03",
    "gn:asciiname":"Hareeri",
    "gn:cc2":"SO",
    "gn:country_code":"SO",
    "gn:dem":357,
    "gn:feature_class":"P",
    "gn:feature_code":"PPL",
    "gn:name":"Hareeri",
    "gn:population":0,
    "gn:timezone":"Africa/Mogadishu",
    "iso:country":"SO",
    "name:und_x_variant":[
        "Areri",
        "Har\u0113ri",
        "Hareeri"
    ],
    "wof:name":"Hareeri",
    "wof:placetype":"locality"
},
  "geometry": {"coordinates":[50.08333,8.83333],"type":"Point"}
}