{
  "type": "Feature",
  "properties": {
    "gn:admin1_code":"04",
    "gn:asciiname":"Jidow",
    "gn:country_code":"SO",
    "gn:dem":480,
    "gn:feature_class":"P",
    "gn:feature_code":"PPL",
    "gn:name":"Jidow",
    "gn:population":0,
    "gn:timezone":"Africa/Mogadishu",
    "iso:country":"SO",
    "name:som_x_preferred":[
        "Jidow"
    ],
    "wof:name":"Jidow",
    "wof:placetype":"locality"
},
  "geometry": {"coordinates":[43.4788,3.10107],"type":"Point"}
}