{
  "type": "Feature",
  "properties": {
    "gn:admin1_code":"20.0",
    "gn:asciiname":"Xadhig Xadhig",
    "gn:country_code":"SO",
    "gn:dem":1199,
    "gn:feature_class":"P",
    "gn:feature_code":"PPL",
    "gn:name":"Xadhig Xadhig",
    "gn:population":0,
    "gn:timezone":"Africa/Mogadishu",
    "iso:country":"SO",
    "wof:name":"Xadhig Xadhig",
    "wof:placetype":"locality"
},
  "geometry": {"coordinates":[44.27461,9.38879],"type":"Point"}
}