{
  "type": "Feature",
  "properties": {
    "gn:admin1_code":"04",
    "gn:asciiname":"Islan Wiyn",
    "gn:country_code":"SO",
    "gn:dem":277,
    "gn:feature_class":"P",
    "gn:feature_code":"PPL",
    "gn:name":"Islan Wiyn",
    "gn:population":0,
    "gn:timezone":"Africa/Mogadishu",
    "iso:country":"SO",
    "name:som_x_preferred":[
        "Islan Wiyn"
    ],
    "wof:name":"Islan Wiyn",
    "wof:placetype":"locality"
},
  "geometry": {"coordinates":[43.7614,2.88879],"type":"Point"}
}