{
  "type": "Feature",
  "properties": {
    "gn:admin1_code":"20",
    "gn:asciiname":"Ijaara",
    "gn:country_code":"SO",
    "gn:dem":1554,
    "gn:feature_class":"P",
    "gn:feature_code":"PPLL",
    "gn:name":"Ijaara",
    "gn:population":0,
    "gn:timezone":"Africa/Mogadishu",
    "iso:country":"SO",
    "wof:name":"Ijaara",
    "wof:placetype":"locality"
},
  "geometry": {"coordinates":[43.65421,9.58361],"type":"Point"}
}