{
  "type": "Feature",
  "properties": {
    "iso:country":"SO",
    "name:ara_x_preferred":[
        "\u0643\u0627\u0646\u062f\u0627\u0644\u0629"
    ],
    "name:arz_x_preferred":[
        "\u0643\u0627\u0646\u062f\u0627\u0644\u0647"
    ],
    "name:ast_x_preferred":[
        "Qandala"
    ],
    "name:azb_x_preferred":[
        "\u0642\u0627\u0646\u062f\u0627\u0644\u0627"
    ],
    "name:ceb_x_preferred":[
        "Qandala"
    ],
    "name:deu_x_preferred":[
        "Qandala"
    ],
    "name:eng_x_preferred":[
        "Qandala"
    ],
    "name:fas_x_preferred":[
        "\u06af\u0627\u0646\u062f\u0627\u0644\u0627"
    ],
    "name:fra_x_preferred":[
        "Qandala"
    ],
    "name:ita_x_preferred":[
        "Candala"
    ],
    "name:jpn_x_preferred":[
        "\u30ab\u30f3\u30c0\u30fc\u30e9"
    ],
    "name:nld_x_preferred":[
        "Qandala"
    ],
    "name:pol_x_preferred":[
        "Qandala"
    ],
    "name:ron_x_preferred":[
        "Qandala"
    ],
    "name:rus_x_preferred":[
        "\u041a\u0430\u043d\u0434\u0430\u043b\u0430"
    ],
    "name:som_x_preferred":[
        "Qandala"
    ],
    "name:spa_x_preferred":[
        "\u0120andala"
    ],
    "name:srn_x_preferred":[
        "Qandala"
    ],
    "name:swa_x_preferred":[
        "Qandala"
    ],
    "name:und_x_variant":[
        "Kandala"
    ],
    "name:urd_x_preferred":[
        "\u06a9\u0627\u0646\u062f\u0627\u0644\u06c1"
    ],
    "name:zho_x_preferred":[
        "\u7518\u9054\u62c9"
    ],
    "name:zul_x_preferred":[
        "Qandala"
    ],
    "qs:gn_country":"SO",
    "qs:gn_fcode":"PPL",
    "qs:gn_pop":15923,
    "qs:name":"Qandala",
    "qs:name_adm0":"Somalia",
    "qs:name_adm1":"Bari",
    "qs:photos":0,
    "qs:photos_1k":0,
    "qs:photos_9k":0,
    "qs:photos_9r":0,
    "qs:photos_all":0,
    "qs:photos_sr":0,
    "qs:placetype":"Town",
    "qs:pop_sr":"6",
    "qs:woe_adm0":23424949,
    "wd:wordcount":304,
    "wof:name":"Qandala",
    "wof:placetype":"locality",
    "wof:population":15923
},
  "geometry": {"coordinates":[49.87282,11.47197],"type":"Point"}
}