{
  "type": "Feature",
  "properties": {
    "iso:country":"SO",
    "name:chi_x_preferred":[
        "\u7518\u9054\u62c9"
    ],
    "name:deu_x_preferred":[
        "Qandala"
    ],
    "name:dut_x_preferred":[
        "Qandala"
    ],
    "name:eng_x_preferred":[
        "Qandala"
    ],
    "name:fre_x_preferred":[
        "Qandala"
    ],
    "name:ger_x_preferred":[
        "Qandala"
    ],
    "name:ita_x_preferred":[
        "Candala"
    ],
    "name:jpn_x_preferred":[
        "\u30ab\u30f3\u30c0\u30fc\u30e9"
    ],
    "name:pol_x_preferred":[
        "Qandala"
    ],
    "name:ron_x_preferred":[
        "Qandala"
    ],
    "name:rum_x_preferred":[
        "Qandala"
    ],
    "name:som_x_preferred":[
        "Qandala"
    ],
    "name:spa_x_preferred":[
        "\u0120andala"
    ],
    "name:srn_x_preferred":[
        "Qandala"
    ],
    "name:unk_x_variant":[
        "Kandala"
    ],
    "name:urd_x_preferred":[
        "\u06a9\u0627\u0646\u062f\u0627\u0644\u06c1"
    ],
    "name:zho_x_preferred":[
        "\u7518\u9054\u62c9"
    ],
    "qs:gn_country":"SO",
    "qs:gn_fcode":"PPL",
    "qs:gn_pop":15923,
    "qs:name":"Qandala",
    "qs:name_adm0":"Somalia",
    "qs:name_adm1":"Bari",
    "qs:photos":0,
    "qs:photos_1k":0,
    "qs:photos_9k":0,
    "qs:photos_9r":0,
    "qs:photos_all":0,
    "qs:photos_sr":0,
    "qs:placetype":"Town",
    "qs:pop_sr":"6",
    "qs:woe_adm0":23424949,
    "wd:wordcount":304,
    "wof:name":"Qandala",
    "wof:placetype":"locality",
    "wof:population":15923
},
  "geometry": {"coordinates":[49.87282,11.47197],"type":"Point"}
}