{
  "type": "Feature",
  "properties": {
    "gn:admin1_code":"14",
    "gn:asciiname":"Hantiwadaag",
    "gn:country_code":"SO",
    "gn:dem":71,
    "gn:feature_class":"P",
    "gn:feature_code":"PPL",
    "gn:name":"Hantiwadaag",
    "gn:population":0,
    "gn:timezone":"Africa/Mogadishu",
    "iso:country":"SO",
    "name:som_x_preferred":[
        "Hantiwadaag"
    ],
    "wof:name":"Hantiwadaag",
    "wof:placetype":"locality"
},
  "geometry": {"coordinates":[44.6456,1.8873],"type":"Point"}
}