{
  "type": "Feature",
  "properties": {
    "gn:admin1_code":"14",
    "gn:asciiname":"Adaliyow",
    "gn:country_code":"SO",
    "gn:dem":73,
    "gn:feature_class":"P",
    "gn:feature_code":"PPL",
    "gn:name":"Adaliyow",
    "gn:population":0,
    "gn:timezone":"Africa/Mogadishu",
    "iso:country":"SO",
    "name:som_x_preferred":[
        "Adaliyow"
    ],
    "wof:name":"Adaliyow",
    "wof:placetype":"locality"
},
  "geometry": {"coordinates":[44.6392,1.7491],"type":"Point"}
}