{
  "type": "Feature",
  "properties": {
    "gn:admin1_code":"20.0",
    "gn:asciiname":"Sool Midgaan",
    "gn:cc2":"SO",
    "gn:country_code":"SO",
    "gn:dem":453,
    "gn:feature_class":"P",
    "gn:feature_code":"PPL",
    "gn:name":"Sool Midgaan",
    "gn:population":0,
    "gn:timezone":"Africa/Mogadishu",
    "iso:country":"SO",
    "name:und_x_variant":[
        "Sol Midg\u0101n",
        "So Midgan",
        "Sool Midgaan"
    ],
    "wof:name":"Sool Midgaan",
    "wof:placetype":"locality"
},
  "geometry": {"coordinates":[44.45,10.08333],"type":"Point"}
}