{
  "type": "Feature",
  "properties": {
    "gn:admin1_code":"9.0",
    "gn:asciiname":"Muusa Makuba",
    "gn:country_code":"SO",
    "gn:dem":10,
    "gn:feature_class":"P",
    "gn:feature_code":"PPL",
    "gn:name":"Muusa Makuba",
    "gn:population":0,
    "gn:timezone":"Africa/Mogadishu",
    "iso:country":"SO",
    "name:und_x_variant":[
        "Mussa Macuba",
        "Muusa Makuba"
    ],
    "wof:name":"Muusa Makuba",
    "wof:placetype":"locality"
},
  "geometry": {"coordinates":[42.76639,0.23132],"type":"Point"}
}