{
  "type": "Feature",
  "properties": {
    "gn:admin1_code":"04",
    "gn:asciiname":"Shagow",
    "gn:country_code":"SO",
    "gn:dem":467,
    "gn:feature_class":"P",
    "gn:feature_code":"PPL",
    "gn:name":"Shagow",
    "gn:population":0,
    "gn:timezone":"Africa/Mogadishu",
    "iso:country":"SO",
    "name:som_x_preferred":[
        "Shagow"
    ],
    "wof:name":"Shagow",
    "wof:placetype":"locality"
},
  "geometry": {"coordinates":[43.5928,3.0957],"type":"Point"}
}