{
  "type": "Feature",
  "properties": {
    "gn:admin1_code":"04",
    "gn:asciiname":"Buulo Uusla",
    "gn:country_code":"SO",
    "gn:dem":470,
    "gn:feature_class":"P",
    "gn:feature_code":"PPL",
    "gn:name":"Buulo Uusla",
    "gn:population":0,
    "gn:timezone":"Africa/Mogadishu",
    "iso:country":"SO",
    "name:som_x_preferred":[
        "Buulo Uusla"
    ],
    "name:und_x_variant":[
        "Bulo Uslei"
    ],
    "wof:name":"Buulo Uusla",
    "wof:placetype":"locality"
},
  "geometry": {"coordinates":[43.49886,3.38746],"type":"Point"}
}