{
  "type": "Feature",
  "properties": {
    "gn:admin1_code":"8.0",
    "gn:asciiname":"Tafanyo",
    "gn:country_code":"SO",
    "gn:dem":31,
    "gn:feature_class":"P",
    "gn:feature_code":"PPL",
    "gn:name":"Tafanyo",
    "gn:population":0,
    "gn:timezone":"Africa/Mogadishu",
    "iso:country":"SO",
    "wof:name":"Tafanyo",
    "wof:placetype":"locality"
},
  "geometry": {"coordinates":[42.6873,0.71979],"type":"Point"}
}