{
  "type": "Feature",
  "properties": {
    "gn:admin1_code":"14",
    "gn:asciiname":"Beedle",
    "gn:country_code":"SO",
    "gn:dem":79,
    "gn:feature_class":"P",
    "gn:feature_code":"PPL",
    "gn:name":"Beedle",
    "gn:population":0,
    "gn:timezone":"Africa/Mogadishu",
    "iso:country":"SO",
    "name:som_x_preferred":[
        "Beedle"
    ],
    "wof:name":"Beedle",
    "wof:placetype":"locality"
},
  "geometry": {"coordinates":[44.7984,2.2014],"type":"Point"}
}