{
  "type": "Feature",
  "properties": {
    "gn:admin1_code":"9.0",
    "gn:asciiname":"Uangheolle",
    "gn:country_code":"SO",
    "gn:dem":46,
    "gn:feature_class":"P",
    "gn:feature_code":"PPL",
    "gn:name":"Uangheolle",
    "gn:population":0,
    "gn:timezone":"Africa/Mogadishu",
    "iso:country":"SO",
    "name:und_x_variant":[
        "Uanghe Ola",
        "Uangheolle"
    ],
    "wof:name":"Uangheolle",
    "wof:placetype":"locality"
},
  "geometry": {"coordinates":[41.45,-0.85],"type":"Point"}
}