{
  "type": "Feature",
  "properties": {
    "gn:admin1_code":"7.0",
    "gn:asciiname":"Maxaas",
    "gn:country_code":"SO",
    "gn:dem":180,
    "gn:feature_class":"P",
    "gn:feature_code":"PPL",
    "gn:name":"Maxaas",
    "gn:population":0,
    "gn:timezone":"Africa/Mogadishu",
    "iso:country":"SO",
    "name:und_x_variant":[
        "Maas",
        "Mahas",
        "Maxaas"
    ],
    "wof:name":"Maxaas",
    "wof:placetype":"locality"
},
  "geometry": {"coordinates":[46.08817,4.39339],"type":"Point"}
}