{
  "type": "Feature",
  "properties": {
    "gn:admin1_code":"4.0",
    "gn:asciiname":"Morgawaan",
    "gn:country_code":"SO",
    "gn:dem":276,
    "gn:feature_class":"P",
    "gn:feature_code":"PPLL",
    "gn:name":"Morgawaan",
    "gn:population":0,
    "gn:timezone":"Africa/Mogadishu",
    "iso:country":"SO",
    "name:som_x_preferred":[
        "Morgawaan"
    ],
    "wof:name":"Morgawaan",
    "wof:placetype":"locality"
},
  "geometry": {"coordinates":[44.13317,3.04555],"type":"Point"}
}