{
  "type": "Feature",
  "properties": {
    "gn:admin1_code":"06",
    "gn:asciiname":"Buur Xaraw",
    "gn:country_code":"SO",
    "gn:dem":332,
    "gn:feature_class":"P",
    "gn:feature_code":"PPL",
    "gn:name":"Buur Xaraw",
    "gn:population":0,
    "gn:timezone":"Africa/Mogadishu",
    "iso:country":"SO",
    "name:som_x_preferred":[
        "Buur Xaraw"
    ],
    "wof:name":"Buur Xaraw",
    "wof:placetype":"locality"
},
  "geometry": {"coordinates":[42.9092,3.1257],"type":"Point"}
}