{
  "type": "Feature",
  "properties": {
    "gn:admin1_code":"10",
    "gn:asciiname":"Colguula",
    "gn:country_code":"SO",
    "gn:dem":134,
    "gn:feature_class":"P",
    "gn:feature_code":"PPL",
    "gn:name":"Colguula",
    "gn:population":0,
    "gn:timezone":"Africa/Mogadishu",
    "iso:country":"SO",
    "name:ron_x_preferred":[
        "Colguula"
    ],
    "name:som_x_preferred":[
        "Colguula"
    ],
    "wof:name":"Colguula",
    "wof:placetype":"locality"
},
  "geometry": {"coordinates":[47.8541,6.0129],"type":"Point"}
}