{
  "type": "Feature",
  "properties": {
    "gn:admin1_code":"14",
    "gn:asciiname":"El Uerega",
    "gn:country_code":"SO",
    "gn:dem":3,
    "gn:feature_class":"P",
    "gn:feature_code":"PPL",
    "gn:name":"El Uerega",
    "gn:population":0,
    "gn:timezone":"Africa/Mogadishu",
    "iso:country":"SO",
    "wof:name":"El Uerega",
    "wof:placetype":"locality"
},
  "geometry": {"coordinates":[45.25,1.98333],"type":"Point"}
}