{
  "type": "Feature",
  "properties": {
    "gn:admin1_code":"14",
    "gn:asciiname":"Garas Weyne",
    "gn:country_code":"SO",
    "gn:dem":94,
    "gn:feature_class":"P",
    "gn:feature_code":"PPL",
    "gn:name":"Garas Weyne",
    "gn:population":0,
    "gn:timezone":"Africa/Mogadishu",
    "iso:country":"SO",
    "name:som_x_preferred":[
        "Garas Weyne"
    ],
    "wof:name":"Garas Weyne",
    "wof:placetype":"locality"
},
  "geometry": {"coordinates":[45.0341,2.6009],"type":"Point"}
}