{
  "type": "Feature",
  "properties": {
    "gn:admin1_code":"04",
    "gn:asciiname":"Siidow",
    "gn:country_code":"SO",
    "gn:dem":485,
    "gn:feature_class":"P",
    "gn:feature_code":"PPL",
    "gn:name":"Siidow",
    "gn:population":0,
    "gn:timezone":"Africa/Mogadishu",
    "iso:country":"SO",
    "name:som_x_preferred":[
        "Siidow"
    ],
    "wof:name":"Siidow",
    "wof:placetype":"locality"
},
  "geometry": {"coordinates":[43.3902,2.9419],"type":"Point"}
}