{
  "type": "Feature",
  "properties": {
    "gn:admin1_code":"20.0",
    "gn:asciiname":"Oromo",
    "gn:country_code":"SO",
    "gn:dem":1435,
    "gn:feature_class":"P",
    "gn:feature_code":"PPL",
    "gn:name":"Oromo",
    "gn:population":0,
    "gn:timezone":"Africa/Mogadishu",
    "iso:country":"SO",
    "name:bul_x_preferred":[
        "\u041e\u0440\u043e\u043c\u043e"
    ],
    "name:ceb_x_preferred":[
        "Oromo"
    ],
    "name:deu_x_preferred":[
        "Oromo"
    ],
    "name:fin_x_preferred":[
        "Oromo"
    ],
    "name:fra_x_preferred":[
        "Oromo"
    ],
    "name:heb_x_preferred":[
        "\u05d0\u05d5\u05e8\u05d5\u05de\u05d5"
    ],
    "name:kor_x_preferred":[
        "\uc624\ub85c\ubaa8"
    ],
    "name:rus_x_preferred":[
        "\u041e\u0440\u043e\u043c\u043e"
    ],
    "wof:name":"Oromo",
    "wof:placetype":"locality"
},
  "geometry": {"coordinates":[43.9288,9.60555],"type":"Point"}
}