{
  "type": "Feature",
  "properties": {
    "gn:admin1_code":"20.0",
    "gn:asciiname":"Oromo",
    "gn:country_code":"SO",
    "gn:dem":1435,
    "gn:feature_class":"P",
    "gn:feature_code":"PPL",
    "gn:name":"Oromo",
    "gn:population":0,
    "gn:timezone":"Africa/Mogadishu",
    "iso:country":"SO",
    "wof:name":"Oromo",
    "wof:placetype":"locality"
},
  "geometry": {"coordinates":[43.9288,9.60555],"type":"Point"}
}