{
  "type": "Feature",
  "properties": {
    "gn:admin1_code":"9.0",
    "gn:asciiname":"Niirey",
    "gn:country_code":"SO",
    "gn:dem":7,
    "gn:feature_class":"P",
    "gn:feature_code":"PPL",
    "gn:name":"Niirey",
    "gn:population":0,
    "gn:timezone":"Africa/Mogadishu",
    "iso:country":"SO",
    "name:und_x_variant":[
        "Cabdi Arbo",
        "Niirey"
    ],
    "wof:name":"Niirey",
    "wof:placetype":"locality"
},
  "geometry": {"coordinates":[42.67457,-0.04831],"type":"Point"}
}