{
  "type": "Feature",
  "properties": {
    "gn:admin1_code":"3.0",
    "gn:asciiname":"Qoori",
    "gn:country_code":"SO",
    "gn:dem":11,
    "gn:feature_class":"P",
    "gn:feature_code":"PPL",
    "gn:name":"Qoori",
    "gn:population":0,
    "gn:timezone":"Africa/Mogadishu",
    "iso:country":"SO",
    "name:som_x_preferred":[
        "Qoori"
    ],
    "name:und_x_variant":[
        "Qoort",
        "Bender Gedid"
    ],
    "wof:name":"Qoori",
    "wof:placetype":"locality"
},
  "geometry": {"coordinates":[49.92025,11.50107],"type":"Point"}
}