{
  "type": "Feature",
  "properties": {
    "gn:admin1_code":"1.0",
    "gn:asciiname":"Xarerte",
    "gn:country_code":"SO",
    "gn:dem":428,
    "gn:feature_class":"P",
    "gn:feature_code":"PPL",
    "gn:name":"Xarerte",
    "gn:population":0,
    "gn:timezone":"Africa/Mogadishu",
    "iso:country":"SO",
    "name:som_x_preferred":[
        "Xarerte"
    ],
    "wof:name":"Xarerte",
    "wof:placetype":"locality"
},
  "geometry": {"coordinates":[44.43279,4.02352],"type":"Point"}
}