{
  "type": "Feature",
  "properties": {
    "gn:admin1_code":"01",
    "gn:asciiname":"Coralle",
    "gn:country_code":"SO",
    "gn:dem":320,
    "gn:feature_class":"P",
    "gn:feature_code":"PPL",
    "gn:name":"Coralle",
    "gn:population":0,
    "gn:timezone":"Africa/Mogadishu",
    "iso:country":"SO",
    "wof:name":"Coralle",
    "wof:placetype":"locality"
},
  "geometry": {"coordinates":[43.05,4.31667],"type":"Point"}
}