{
  "type": "Feature",
  "properties": {
    "gn:admin1_code":"06",
    "gn:asciiname":"Ceel Baashaalay",
    "gn:country_code":"SO",
    "gn:dem":279,
    "gn:feature_class":"P",
    "gn:feature_code":"PPL",
    "gn:name":"Ceel Baashaalay",
    "gn:population":0,
    "gn:timezone":"Africa/Mogadishu",
    "iso:country":"SO",
    "name:und_x_variant":[
        "El Bascialeu"
    ],
    "wof:name":"Ceel Baashaalay",
    "wof:placetype":"locality"
},
  "geometry": {"coordinates":[42.35,3.61667],"type":"Point"}
}