{
  "type": "Feature",
  "properties": {
    "gn:admin1_code":"4.0",
    "gn:asciiname":"Sada Kabad",
    "gn:country_code":"SO",
    "gn:dem":485,
    "gn:feature_class":"P",
    "gn:feature_code":"PPL",
    "gn:name":"Sada Kabad",
    "gn:population":0,
    "gn:timezone":"Africa/Mogadishu",
    "iso:country":"SO",
    "name:som_x_preferred":[
        "Sada Kabad"
    ],
    "wof:name":"Sada Kabad",
    "wof:placetype":"locality"
},
  "geometry": {"coordinates":[43.504,3.237],"type":"Point"}
}