{
  "type": "Feature",
  "properties": {
    "gn:admin1_code":"14",
    "gn:asciiname":"Dawanle",
    "gn:country_code":"SO",
    "gn:dem":89,
    "gn:feature_class":"P",
    "gn:feature_code":"PPL",
    "gn:name":"Dawanle",
    "gn:population":0,
    "gn:timezone":"Africa/Mogadishu",
    "iso:country":"SO",
    "name:som_x_preferred":[
        "Dawanle"
    ],
    "wof:name":"Dawanle",
    "wof:placetype":"locality"
},
  "geometry": {"coordinates":[44.8805,2.5451],"type":"Point"}
}