{
  "type": "Feature",
  "properties": {
    "gn:admin1_code":"21",
    "gn:asciiname":"Dabacaddo",
    "gn:country_code":"SO",
    "gn:dem":1624,
    "gn:feature_class":"P",
    "gn:feature_code":"PPLL",
    "gn:name":"Dabacaddo",
    "gn:population":0,
    "gn:timezone":"Africa/Mogadishu",
    "iso:country":"SO",
    "name:und_x_variant":[
        "Dabaaddo",
        "Dabacaddo"
    ],
    "wof:name":"Dabacaddo",
    "wof:placetype":"locality"
},
  "geometry": {"coordinates":[43.30298,9.79667],"type":"Point"}
}