{
  "type": "Feature",
  "properties": {
    "gn:admin1_code":"20.0",
    "gn:asciiname":"Shariif",
    "gn:country_code":"SO",
    "gn:dem":1411,
    "gn:feature_class":"P",
    "gn:feature_code":"PPL",
    "gn:name":"Shariif",
    "gn:population":0,
    "gn:timezone":"Africa/Mogadishu",
    "iso:country":"SO",
    "wof:name":"Shariif",
    "wof:placetype":"locality"
},
  "geometry": {"coordinates":[43.83696,9.50061],"type":"Point"}
}