{
  "type": "Feature",
  "properties": {
    "gn:admin1_code":"19",
    "gn:admin2_code":"Buuhoodle",
    "gn:asciiname":"Caroweyn",
    "gn:country_code":"SO",
    "gn:dem":833,
    "gn:feature_class":"P",
    "gn:feature_code":"PPL",
    "gn:name":"Caroweyn",
    "gn:population":0,
    "gn:timezone":"Africa/Mogadishu",
    "iso:country":"SO",
    "name:som_x_preferred":[
        "Caroweyn"
    ],
    "wof:name":"Caroweyn",
    "wof:placetype":"locality"
},
  "geometry": {"coordinates":[46.59056,8.53583],"type":"Point"}
}