{
  "type": "Feature",
  "properties": {
    "gn:admin1_code":"04",
    "gn:asciiname":"Gugumaale",
    "gn:country_code":"SO",
    "gn:dem":184,
    "gn:feature_class":"P",
    "gn:feature_code":"PPL",
    "gn:name":"Gugumaale",
    "gn:population":0,
    "gn:timezone":"Africa/Mogadishu",
    "iso:country":"SO",
    "name:som_x_preferred":[
        "Gugumaale"
    ],
    "wof:name":"Gugumaale",
    "wof:placetype":"locality"
},
  "geometry": {"coordinates":[44.27425,2.83525],"type":"Point"}
}