{
  "type": "Feature",
  "properties": {
    "gn:admin1_code":"13",
    "gn:asciiname":"Levi Musse Adde",
    "gn:cc2":"SO",
    "gn:country_code":"SO",
    "gn:dem":113,
    "gn:feature_class":"P",
    "gn:feature_code":"PPL",
    "gn:name":"Levi Musse Adde",
    "gn:population":0,
    "gn:timezone":"Africa/Mogadishu",
    "iso:country":"SO",
    "name:und_x_variant":[
        "Levi Mussa Adde",
        "Levi",
        "Levi Musse Adde"
    ],
    "wof:name":"Levi Musse Adde",
    "wof:placetype":"locality"
},
  "geometry": {"coordinates":[45.83333,3.06667],"type":"Point"}
}