{
  "type": "Feature",
  "properties": {
    "gn:admin1_code":"12",
    "gn:asciiname":"Celaya",
    "gn:country_code":"SO",
    "gn:dem":2176,
    "gn:feature_class":"P",
    "gn:feature_code":"PPL",
    "gn:name":"Celaya",
    "gn:population":0,
    "gn:timezone":"Africa/Mogadishu",
    "iso:country":"SO",
    "name:som_x_preferred":[
        "Celaya"
    ],
    "wof:name":"Celaya",
    "wof:placetype":"locality"
},
  "geometry": {"coordinates":[47.30373,10.76045],"type":"Point"}
}