{
  "type": "Feature",
  "properties": {
    "gn:admin1_code":"20.0",
    "gn:asciiname":"Xagal",
    "gn:country_code":"SO",
    "gn:dem":1331,
    "gn:feature_class":"P",
    "gn:feature_code":"PPL",
    "gn:name":"Xagal",
    "gn:population":0,
    "gn:timezone":"Africa/Mogadishu",
    "iso:country":"SO",
    "wof:name":"Xagal",
    "wof:placetype":"locality"
},
  "geometry": {"coordinates":[43.94778,9.52583],"type":"Point"}
}