{
  "type": "Feature",
  "properties": {
    "gn:admin1_code":"10",
    "gn:asciiname":"Buro",
    "gn:country_code":"SO",
    "gn:dem":96,
    "gn:feature_class":"P",
    "gn:feature_code":"PPL",
    "gn:name":"Buro",
    "gn:population":0,
    "gn:timezone":"Africa/Mogadishu",
    "iso:country":"SO",
    "name:ceb_x_preferred":[
        "Buro"
    ],
    "name:deu_x_preferred":[
        "Buro"
    ],
    "name:ita_x_preferred":[
        "Buro"
    ],
    "name:swe_x_preferred":[
        "Buro"
    ],
    "name:tgl_x_preferred":[
        "Buro"
    ],
    "wof:name":"Buro",
    "wof:placetype":"locality"
},
  "geometry": {"coordinates":[48.21667,5.58333],"type":"Point"}
}