{
  "type": "Feature",
  "properties": {
    "gn:admin1_code":"04",
    "gn:asciiname":"Konkorey",
    "gn:country_code":"SO",
    "gn:dem":258,
    "gn:feature_class":"P",
    "gn:feature_code":"PPL",
    "gn:name":"Konkorey",
    "gn:population":0,
    "gn:timezone":"Africa/Mogadishu",
    "iso:country":"SO",
    "name:som_x_preferred":[
        "Konkorey"
    ],
    "wof:name":"Konkorey",
    "wof:placetype":"locality"
},
  "geometry": {"coordinates":[44.1621,3.011],"type":"Point"}
}