{
  "type": "Feature",
  "properties": {
    "gn:admin1_code":"8.0",
    "gn:asciiname":"Macalim Weyn",
    "gn:country_code":"SO",
    "gn:dem":41,
    "gn:feature_class":"P",
    "gn:feature_code":"PPL",
    "gn:name":"Macalim Weyn",
    "gn:population":0,
    "gn:timezone":"Africa/Mogadishu",
    "iso:country":"SO",
    "wof:name":"Macalim Weyn",
    "wof:placetype":"locality"
},
  "geometry": {"coordinates":[42.60077,0.88702],"type":"Point"}
}