{
  "type": "Feature",
  "properties": {
    "gn:admin1_code":"03",
    "gn:asciiname":"Berda Uen",
    "gn:cc2":"SO",
    "gn:country_code":"SO",
    "gn:dem":939,
    "gn:feature_class":"P",
    "gn:feature_code":"PPL",
    "gn:name":"Berda Uen",
    "gn:population":0,
    "gn:timezone":"Africa/Mogadishu",
    "iso:country":"SO",
    "name:und_x_variant":[
        "Berda Uein",
        "Berda Uen"
    ],
    "wof:name":"Berda Uen",
    "wof:placetype":"locality"
},
  "geometry": {"coordinates":[50.15,11.08333],"type":"Point"}
}