{
  "type": "Feature",
  "properties": {
    "gn:admin1_code":"14",
    "gn:asciiname":"Fulayley",
    "gn:country_code":"SO",
    "gn:dem":94,
    "gn:feature_class":"P",
    "gn:feature_code":"PPL",
    "gn:name":"Fulayley",
    "gn:population":0,
    "gn:timezone":"Africa/Mogadishu",
    "iso:country":"SO",
    "name:som_x_preferred":[
        "Fulayley"
    ],
    "wof:name":"Fulayley",
    "wof:placetype":"locality"
},
  "geometry": {"coordinates":[45.0238,2.6211],"type":"Point"}
}