{
  "type": "Feature",
  "properties": {
    "gn:admin1_code":"21.0",
    "gn:asciiname":"Tuur Qaylo",
    "gn:country_code":"SO",
    "gn:dem":1453,
    "gn:feature_class":"P",
    "gn:feature_code":"PPL",
    "gn:name":"Tuur Qaylo",
    "gn:population":0,
    "gn:timezone":"Africa/Mogadishu",
    "iso:country":"SO",
    "name:und_x_variant":[
        "Tur-Kaylo",
        "Tuur Qaylo"
    ],
    "wof:name":"Tuur Qaylo",
    "wof:placetype":"locality"
},
  "geometry": {"coordinates":[43.17242,9.97365],"type":"Point"}
}