{
  "type": "Feature",
  "properties": {
    "gn:admin1_code":"14",
    "gn:asciiname":"Eeloole",
    "gn:country_code":"SO",
    "gn:dem":88,
    "gn:feature_class":"P",
    "gn:feature_code":"PPL",
    "gn:name":"Eeloole",
    "gn:population":0,
    "gn:timezone":"Africa/Mogadishu",
    "iso:country":"SO",
    "name:som_x_preferred":[
        "Eeloole"
    ],
    "wof:name":"Eeloole",
    "wof:placetype":"locality"
},
  "geometry": {"coordinates":[44.8233,2.5858],"type":"Point"}
}