{
  "type": "Feature",
  "properties": {
    "gn:admin1_code":"04",
    "gn:asciiname":"Jameecada Aw Shiikh Cumorow",
    "gn:country_code":"SO",
    "gn:dem":186,
    "gn:feature_class":"P",
    "gn:feature_code":"PPL",
    "gn:name":"Jameecada Aw Shiikh Cumorow",
    "gn:population":0,
    "gn:timezone":"Africa/Mogadishu",
    "iso:country":"SO",
    "name:som_x_preferred":[
        "Jameecada Aw Shiikh Cumorow"
    ],
    "wof:name":"Jameecada Aw Shiikh Cumorow",
    "wof:placetype":"locality"
},
  "geometry": {"coordinates":[44.2164,2.7971],"type":"Point"}
}