{
  "type": "Feature",
  "properties": {
    "gn:admin1_code":"05",
    "gn:asciiname":"Goragiahor",
    "gn:country_code":"SO",
    "gn:dem":357,
    "gn:feature_class":"P",
    "gn:feature_code":"PPL",
    "gn:name":"Goragiahor",
    "gn:population":0,
    "gn:timezone":"Africa/Mogadishu",
    "iso:country":"SO",
    "name:und_x_variant":[
        "Goradzhakhor",
        "Goragiahor"
    ],
    "wof:name":"Goragiahor",
    "wof:placetype":"locality"
},
  "geometry": {"coordinates":[45.71056,5.395],"type":"Point"}
}