{
  "type": "Feature",
  "properties": {
    "gn:admin1_code":"09",
    "gn:asciiname":"Haatko",
    "gn:country_code":"SO",
    "gn:dem":8,
    "gn:feature_class":"P",
    "gn:feature_code":"PPL",
    "gn:name":"Haatko",
    "gn:population":0,
    "gn:timezone":"Africa/Mogadishu",
    "iso:country":"SO",
    "wof:name":"Haatko",
    "wof:placetype":"locality"
},
  "geometry": {"coordinates":[42.57886,-0.1502],"type":"Point"}
}