{
  "type": "Feature",
  "properties": {
    "gn:admin1_code":"09",
    "gn:asciiname":"Billada",
    "gn:country_code":"SO",
    "gn:dem":26,
    "gn:feature_class":"P",
    "gn:feature_code":"PPL",
    "gn:name":"Billada",
    "gn:population":0,
    "gn:timezone":"Africa/Mogadishu",
    "iso:country":"SO",
    "wof:name":"Billada",
    "wof:placetype":"locality"
},
  "geometry": {"coordinates":[41.53333,-1.51667],"type":"Point"}
}