{
  "type": "Feature",
  "properties": {
    "gn:admin1_code":"04",
    "gn:asciiname":"Bottis",
    "gn:country_code":"SO",
    "gn:dem":465,
    "gn:feature_class":"P",
    "gn:feature_code":"PPL",
    "gn:name":"Bottis",
    "gn:population":0,
    "gn:timezone":"Africa/Mogadishu",
    "iso:country":"SO",
    "name:som_x_preferred":[
        "Bottis"
    ],
    "wof:name":"Bottis",
    "wof:placetype":"locality"
},
  "geometry": {"coordinates":[43.3926,2.8571],"type":"Point"}
}