{
  "type": "Feature",
  "properties": {
    "gn:admin1_code":"14",
    "gn:asciiname":"Barrow",
    "gn:country_code":"SO",
    "gn:dem":75,
    "gn:feature_class":"P",
    "gn:feature_code":"PPL",
    "gn:name":"Barrow",
    "gn:population":0,
    "gn:timezone":"Africa/Mogadishu",
    "iso:country":"SO",
    "name:ara_x_preferred":[
        "\u0628\u0627\u0631\u0648"
    ],
    "name:bel_x_preferred":[
        "\u0411\u0430\u0440\u0430\u045e"
    ],
    "name:cat_x_preferred":[
        "Barrow"
    ],
    "name:ceb_x_preferred":[
        "Barrow"
    ],
    "name:ces_x_preferred":[
        "Barrow"
    ],
    "name:dan_x_preferred":[
        "Barrow"
    ],
    "name:deu_x_preferred":[
        "Barrow"
    ],
    "name:est_x_preferred":[
        "Barrow"
    ],
    "name:fas_x_preferred":[
        "\u0628\u0627\u0631\u0648"
    ],
    "name:fra_x_preferred":[
        "Barrow"
    ],
    "name:heb_x_preferred":[
        "\u05d1\u05d0\u05e8\u05d5"
    ],
    "name:ita_x_preferred":[
        "Barrow"
    ],
    "name:jpn_x_preferred":[
        "\u30d0\u30ed\u30fc"
    ],
    "name:nds_x_preferred":[
        "Barrow"
    ],
    "name:nld_x_preferred":[
        "Barrow"
    ],
    "name:nor_x_preferred":[
        "Barrow"
    ],
    "name:pol_x_preferred":[
        "Barrow"
    ],
    "name:por_x_preferred":[
        "Barrow"
    ],
    "name:rus_x_preferred":[
        "\u0411\u0430\u0440\u0440\u043e\u0443"
    ],
    "name:slk_x_preferred":[
        "Barrow"
    ],
    "name:som_x_preferred":[
        "Barrow"
    ],
    "name:spa_x_preferred":[
        "Barrow"
    ],
    "name:srp_x_preferred":[
        "\u0411\u0430\u0440\u043e\u0443"
    ],
    "name:swe_x_preferred":[
        "Barrow"
    ],
    "name:ukr_x_preferred":[
        "\u0411\u0430\u0440\u0440\u043e\u0443"
    ],
    "name:vol_x_preferred":[
        "Barrow"
    ],
    "wof:name":"Barrow",
    "wof:placetype":"locality"
},
  "geometry": {"coordinates":[44.7667,1.8608],"type":"Point"}
}