{
  "type": "Feature",
  "properties": {
    "gn:admin1_code":"14",
    "gn:asciiname":"Barrow",
    "gn:country_code":"SO",
    "gn:dem":75,
    "gn:feature_class":"P",
    "gn:feature_code":"PPL",
    "gn:name":"Barrow",
    "gn:population":0,
    "gn:timezone":"Africa/Mogadishu",
    "iso:country":"SO",
    "name:som_x_preferred":[
        "Barrow"
    ],
    "wof:name":"Barrow",
    "wof:placetype":"locality"
},
  "geometry": {"coordinates":[44.7667,1.8608],"type":"Point"}
}