{
  "type": "Feature",
  "properties": {
    "gn:admin1_code":"03",
    "gn:asciiname":"Bohagno",
    "gn:cc2":"SO",
    "gn:country_code":"SO",
    "gn:dem":842,
    "gn:feature_class":"P",
    "gn:feature_code":"PPL",
    "gn:name":"Bohagno",
    "gn:population":0,
    "gn:timezone":"Africa/Mogadishu",
    "iso:country":"SO",
    "name:und_x_variant":[
        "Bahanjo",
        "Bohanjo",
        "Bohagno"
    ],
    "wof:name":"Bohagno",
    "wof:placetype":"locality"
},
  "geometry": {"coordinates":[50.16667,11.06667],"type":"Point"}
}