{
  "type": "Feature",
  "properties": {
    "gn:admin1_code":"09",
    "gn:asciiname":"Kuusow",
    "gn:country_code":"SO",
    "gn:dem":13,
    "gn:feature_class":"P",
    "gn:feature_code":"PPL",
    "gn:name":"Kuusow",
    "gn:population":0,
    "gn:timezone":"Africa/Mogadishu",
    "iso:country":"SO",
    "wof:name":"Kuusow",
    "wof:placetype":"locality"
},
  "geometry": {"coordinates":[42.54639,-0.03977],"type":"Point"}
}