{
  "type": "Feature",
  "properties": {
    "gn:admin1_code":"06",
    "gn:asciiname":"Hufay",
    "gn:country_code":"SO",
    "gn:dem":127,
    "gn:feature_class":"P",
    "gn:feature_code":"PPL",
    "gn:name":"Hufay",
    "gn:population":0,
    "gn:timezone":"Africa/Mogadishu",
    "iso:country":"SO",
    "name:som_x_preferred":[
        "Hufay"
    ],
    "wof:name":"Hufay",
    "wof:placetype":"locality"
},
  "geometry": {"coordinates":[42.5096,3.2155],"type":"Point"}
}