{
  "type": "Feature",
  "properties": {
    "gn:admin1_code":"20.0",
    "gn:asciiname":"Wadabariis",
    "gn:country_code":"SO",
    "gn:dem":1396,
    "gn:feature_class":"P",
    "gn:feature_code":"PPL",
    "gn:name":"Wadabariis",
    "gn:population":0,
    "gn:timezone":"Africa/Mogadishu",
    "iso:country":"SO",
    "name:und_x_variant":[
        "Uadabaris",
        "Wadabariis"
    ],
    "wof:name":"Wadabariis",
    "wof:placetype":"locality"
},
  "geometry": {"coordinates":[43.85499,9.38193],"type":"Point"}
}