{
  "type": "Feature",
  "properties": {
    "gn:admin1_code":"04",
    "gn:asciiname":"Garal-Duure",
    "gn:country_code":"SO",
    "gn:dem":473,
    "gn:feature_class":"P",
    "gn:feature_code":"PPL",
    "gn:name":"Garal-Duure",
    "gn:population":0,
    "gn:timezone":"Africa/Mogadishu",
    "iso:country":"SO",
    "name:som_x_preferred":[
        "Garal-Duure"
    ],
    "wof:name":"Garal-Duure",
    "wof:placetype":"locality"
},
  "geometry": {"coordinates":[43.40202,3.04795],"type":"Point"}
}