{
  "type": "Feature",
  "properties": {
    "gn:admin1_code":"6.0",
    "gn:asciiname":"Mooyo",
    "gn:country_code":"SO",
    "gn:dem":322,
    "gn:feature_class":"P",
    "gn:feature_code":"PPL",
    "gn:name":"Mooyo",
    "gn:population":0,
    "gn:timezone":"Africa/Mogadishu",
    "iso:country":"SO",
    "wof:name":"Mooyo",
    "wof:placetype":"locality"
},
  "geometry": {"coordinates":[42.97746,3.96916],"type":"Point"}
}