{
  "type": "Feature",
  "properties": {
    "gn:admin1_code":"04",
    "gn:asciiname":"Gurtimaley",
    "gn:country_code":"SO",
    "gn:dem":476,
    "gn:feature_class":"P",
    "gn:feature_code":"PPLL",
    "gn:name":"Gurtimaley",
    "gn:population":0,
    "gn:timezone":"Africa/Mogadishu",
    "iso:country":"SO",
    "name:som_x_preferred":[
        "Gurtimaley"
    ],
    "wof:name":"Gurtimaley",
    "wof:placetype":"locality"
},
  "geometry": {"coordinates":[43.5295,3.0458],"type":"Point"}
}