{
  "type": "Feature",
  "properties": {
    "gn:admin1_code":"03",
    "gn:asciiname":"Aantaara",
    "gn:country_code":"SO",
    "gn:dem":9,
    "gn:feature_class":"P",
    "gn:feature_code":"PPL",
    "gn:name":"Aantaara",
    "gn:population":0,
    "gn:timezone":"Africa/Mogadishu",
    "iso:country":"SO",
    "name:som_x_preferred":[
        "Aantaara"
    ],
    "name:und_x_variant":[
        "Camtaraa",
        "\u2018Amtar\u0101",
        "Antara",
        "Aantaara"
    ],
    "wof:name":"Aantaara",
    "wof:placetype":"locality"
},
  "geometry": {"coordinates":[49.5517,11.4424],"type":"Point"}
}