{
  "type": "Feature",
  "properties": {
    "gn:admin1_code":"8.0",
    "gn:asciiname":"Qunjaale",
    "gn:country_code":"SO",
    "gn:dem":68,
    "gn:feature_class":"P",
    "gn:feature_code":"PPL",
    "gn:name":"Qunjaale",
    "gn:population":0,
    "gn:timezone":"Africa/Mogadishu",
    "iso:country":"SO",
    "wof:name":"Qunjaale",
    "wof:placetype":"locality"
},
  "geometry": {"coordinates":[42.45547,1.57786],"type":"Point"}
}