{
  "type": "Feature",
  "properties": {
    "gn:admin1_code":"19",
    "gn:asciiname":"Balad",
    "gn:country_code":"SO",
    "gn:dem":671,
    "gn:feature_class":"P",
    "gn:feature_code":"PPL",
    "gn:name":"Balad",
    "gn:population":0,
    "gn:timezone":"Africa/Mogadishu",
    "iso:country":"SO",
    "wof:name":"Balad",
    "wof:placetype":"locality"
},
  "geometry": {"coordinates":[46.91667,8.16667],"type":"Point"}
}