{
  "type": "Feature",
  "properties": {
    "gn:admin1_code":"19",
    "gn:asciiname":"Balad",
    "gn:country_code":"SO",
    "gn:dem":671,
    "gn:feature_class":"P",
    "gn:feature_code":"PPL",
    "gn:name":"Balad",
    "gn:population":0,
    "gn:timezone":"Africa/Mogadishu",
    "iso:country":"SO",
    "name:ara_x_preferred":[
        "\u0628\u0644\u062f"
    ],
    "name:ceb_x_preferred":[
        "Balad"
    ],
    "name:deu_x_preferred":[
        "Balad"
    ],
    "name:fra_x_preferred":[
        "Balad"
    ],
    "name:hun_x_preferred":[
        "Balad"
    ],
    "name:ita_x_preferred":[
        "Balad"
    ],
    "name:nld_x_preferred":[
        "Balad"
    ],
    "name:pol_x_preferred":[
        "Balad"
    ],
    "name:rus_x_preferred":[
        "\u0411\u0430\u043b\u0430\u0434"
    ],
    "name:spa_x_preferred":[
        "Balad"
    ],
    "name:swe_x_preferred":[
        "Balad"
    ],
    "wof:name":"Balad",
    "wof:placetype":"locality"
},
  "geometry": {"coordinates":[46.91667,8.16667],"type":"Point"}
}