{
  "type": "Feature",
  "properties": {
    "gn:admin1_code":"13",
    "gn:asciiname":"Leebo Xeero",
    "gn:country_code":"SO",
    "gn:dem":107,
    "gn:feature_class":"P",
    "gn:feature_code":"PPL",
    "gn:name":"Leebo Xeero",
    "gn:population":0,
    "gn:timezone":"Africa/Mogadishu",
    "iso:country":"SO",
    "name:som_x_preferred":[
        "Leebo Xeero"
    ],
    "wof:name":"Leebo Xeero",
    "wof:placetype":"locality"
},
  "geometry": {"coordinates":[45.64706,2.81071],"type":"Point"}
}