{
  "type": "Feature",
  "properties": {
    "gn:admin1_code":"04",
    "gn:asciiname":"Harrow",
    "gn:country_code":"SO",
    "gn:dem":495,
    "gn:feature_class":"P",
    "gn:feature_code":"PPL",
    "gn:name":"Harrow",
    "gn:population":0,
    "gn:timezone":"Africa/Mogadishu",
    "iso:country":"SO",
    "name:ara_x_preferred":[
        "\u0647\u0627\u0631\u0648"
    ],
    "name:ceb_x_preferred":[
        "Harrow"
    ],
    "name:deu_x_preferred":[
        "Harrow"
    ],
    "name:heb_x_preferred":[
        "\u05d4\u05d0\u05e8\u05d5"
    ],
    "name:hin_x_preferred":[
        "\u0939\u0948\u0930\u094b"
    ],
    "name:nld_x_preferred":[
        "Harrow"
    ],
    "name:pol_x_preferred":[
        "Harrow"
    ],
    "name:por_x_preferred":[
        "Harrow"
    ],
    "name:som_x_preferred":[
        "Harrow"
    ],
    "name:spa_x_preferred":[
        "Harrow"
    ],
    "name:swe_x_preferred":[
        "Harrow"
    ],
    "name:ukr_x_preferred":[
        "\u0413\u0435\u0440\u0440\u043e\u0443"
    ],
    "wof:name":"Harrow",
    "wof:placetype":"locality"
},
  "geometry": {"coordinates":[43.5604,3.5993],"type":"Point"}
}