{
  "type": "Feature",
  "properties": {
    "gn:admin1_code":"04",
    "gn:asciiname":"Harrow",
    "gn:country_code":"SO",
    "gn:dem":495,
    "gn:feature_class":"P",
    "gn:feature_code":"PPL",
    "gn:name":"Harrow",
    "gn:population":0,
    "gn:timezone":"Africa/Mogadishu",
    "iso:country":"SO",
    "name:som_x_preferred":[
        "Harrow"
    ],
    "wof:name":"Harrow",
    "wof:placetype":"locality"
},
  "geometry": {"coordinates":[43.5604,3.5993],"type":"Point"}
}