{
  "type": "Feature",
  "properties": {
    "gn:admin1_code":"14",
    "gn:asciiname":"Bulo Gof Adde",
    "gn:country_code":"SO",
    "gn:dem":83,
    "gn:feature_class":"P",
    "gn:feature_code":"PPL",
    "gn:name":"Bulo Gof Adde",
    "gn:population":0,
    "gn:timezone":"Africa/Mogadishu",
    "iso:country":"SO",
    "wof:name":"Bulo Gof Adde",
    "wof:placetype":"locality"
},
  "geometry": {"coordinates":[44.98333,1.86667],"type":"Point"}
}