{
  "type": "Feature",
  "properties": {
    "gn:admin1_code":"06",
    "gn:asciiname":"Hilo Shiid",
    "gn:country_code":"SO",
    "gn:dem":103,
    "gn:feature_class":"P",
    "gn:feature_code":"PPL",
    "gn:name":"Hilo Shiid",
    "gn:population":0,
    "gn:timezone":"Africa/Mogadishu",
    "iso:country":"SO",
    "wof:name":"Hilo Shiid",
    "wof:placetype":"locality"
},
  "geometry": {"coordinates":[42.23124,2.27812],"type":"Point"}
}