{
  "type": "Feature",
  "properties": {
    "gn:admin1_code":"04",
    "gn:asciiname":"Baqalley",
    "gn:country_code":"SO",
    "gn:dem":460,
    "gn:feature_class":"P",
    "gn:feature_code":"PPL",
    "gn:name":"Baqalley",
    "gn:population":0,
    "gn:timezone":"Africa/Mogadishu",
    "iso:country":"SO",
    "name:som_x_preferred":[
        "Baqalley"
    ],
    "wof:name":"Baqalley",
    "wof:placetype":"locality"
},
  "geometry": {"coordinates":[43.4265,3.2598],"type":"Point"}
}