{
  "type": "Feature",
  "properties": {
    "gn:admin1_code":"08",
    "gn:asciiname":"Biliq Tale",
    "gn:country_code":"SO",
    "gn:dem":30,
    "gn:feature_class":"P",
    "gn:feature_code":"PPL",
    "gn:name":"Biliq Tale",
    "gn:population":0,
    "gn:timezone":"Africa/Mogadishu",
    "iso:country":"SO",
    "wof:name":"Biliq Tale",
    "wof:placetype":"locality"
},
  "geometry": {"coordinates":[43.06065,0.62872],"type":"Point"}
}