{
  "type": "Feature",
  "properties": {
    "gn:admin1_code":"06",
    "gn:asciiname":"Goryaale",
    "gn:country_code":"SO",
    "gn:dem":270,
    "gn:feature_class":"P",
    "gn:feature_code":"PPL",
    "gn:name":"Goryaale",
    "gn:population":0,
    "gn:timezone":"Africa/Mogadishu",
    "iso:country":"SO",
    "name:und_x_variant":[
        "Goriale"
    ],
    "wof:name":"Goryaale",
    "wof:placetype":"locality"
},
  "geometry": {"coordinates":[42.71667,4.21667],"type":"Point"}
}