{
  "type": "Feature",
  "properties": {
    "gn:admin1_code":"09",
    "gn:asciiname":"Canjeel",
    "gn:country_code":"SO",
    "gn:dem":14,
    "gn:feature_class":"P",
    "gn:feature_code":"PPL",
    "gn:name":"Canjeel",
    "gn:population":0,
    "gn:timezone":"Africa/Mogadishu",
    "iso:country":"SO",
    "name:som_x_preferred":[
        "Canjeel"
    ],
    "name:und_x_variant":[
        "Anzhel'"
    ],
    "wof:name":"Canjeel",
    "wof:placetype":"locality"
},
  "geometry": {"coordinates":[42.39859000000001,-0.14812],"type":"Point"}
}