{
  "type": "Feature",
  "properties": {
    "gn:admin1_code":"06",
    "gn:asciiname":"Ceel Baari",
    "gn:country_code":"SO",
    "gn:dem":147,
    "gn:feature_class":"P",
    "gn:feature_code":"PPL",
    "gn:name":"Ceel Baari",
    "gn:population":0,
    "gn:timezone":"Africa/Mogadishu",
    "iso:country":"SO",
    "wof:name":"Ceel Baari",
    "wof:placetype":"locality"
},
  "geometry": {"coordinates":[42.39541,2.05386],"type":"Point"}
}