{
  "type": "Feature",
  "properties": {
    "gn:admin1_code":"04",
    "gn:asciiname":"Korow",
    "gn:country_code":"SO",
    "gn:dem":207,
    "gn:feature_class":"P",
    "gn:feature_code":"PPL",
    "gn:name":"Korow",
    "gn:population":0,
    "gn:timezone":"Africa/Mogadishu",
    "iso:country":"SO",
    "name:som_x_preferred":[
        "Korow"
    ],
    "name:und_x_variant":[
        "Carou Dere",
        "Coron Derei"
    ],
    "wof:name":"Korow",
    "wof:placetype":"locality"
},
  "geometry": {"coordinates":[43.96407,2.77683],"type":"Point"}
}