{
  "type": "Feature",
  "properties": {
    "gn:admin1_code":"4.0",
    "gn:asciiname":"Luga Dheere",
    "gn:country_code":"SO",
    "gn:dem":480,
    "gn:feature_class":"P",
    "gn:feature_code":"PPL",
    "gn:name":"Luga Dheere",
    "gn:population":0,
    "gn:timezone":"Africa/Mogadishu",
    "iso:country":"SO",
    "name:som_x_preferred":[
        "Luga Dheere"
    ],
    "wof:name":"Luga Dheere",
    "wof:placetype":"locality"
},
  "geometry": {"coordinates":[43.5385,3.0925],"type":"Point"}
}