{
  "type": "Feature",
  "properties": {
    "gn:admin1_code":"4.0",
    "gn:asciiname":"Warfaa",
    "gn:country_code":"SO",
    "gn:dem":213,
    "gn:feature_class":"P",
    "gn:feature_code":"PPL",
    "gn:name":"Warfaa",
    "gn:population":0,
    "gn:timezone":"Africa/Mogadishu",
    "iso:country":"SO",
    "name:som_x_preferred":[
        "Warfaa"
    ],
    "name:und_x_variant":[
        "Wartaa"
    ],
    "wof:name":"Warfaa",
    "wof:placetype":"locality"
},
  "geometry": {"coordinates":[44.20531,2.89779],"type":"Point"}
}