{
  "type": "Feature",
  "properties": {
    "gn:admin1_code":"20",
    "gn:asciiname":"Gogol Wanaak",
    "gn:country_code":"SO",
    "gn:dem":1373,
    "gn:feature_class":"P",
    "gn:feature_code":"PPL",
    "gn:name":"Gogol Wanaak",
    "gn:population":0,
    "gn:timezone":"Africa/Mogadishu",
    "iso:country":"SO",
    "wof:name":"Gogol Wanaak",
    "wof:placetype":"locality"
},
  "geometry": {"coordinates":[43.80773,9.68032],"type":"Point"}
}