{
  "type": "Feature",
  "properties": {
    "gn:admin1_code":"08",
    "gn:asciiname":"Dhaweynta",
    "gn:country_code":"SO",
    "gn:dem":74,
    "gn:feature_class":"P",
    "gn:feature_code":"PPL",
    "gn:name":"Dhaweynta",
    "gn:population":0,
    "gn:timezone":"Africa/Mogadishu",
    "iso:country":"SO",
    "wof:name":"Dhaweynta",
    "wof:placetype":"locality"
},
  "geometry": {"coordinates":[42.34613,1.76407],"type":"Point"}
}