{
  "type": "Feature",
  "properties": {
    "gn:admin1_code":"03",
    "gn:asciiname":"God Ad",
    "gn:country_code":"SO",
    "gn:dem":622,
    "gn:feature_class":"P",
    "gn:feature_code":"PPL",
    "gn:name":"God Ad",
    "gn:population":0,
    "gn:timezone":"Africa/Mogadishu",
    "iso:country":"SO",
    "wof:name":"God Ad",
    "wof:placetype":"locality"
},
  "geometry": {"coordinates":[50.66667,11.33333],"type":"Point"}
}