{
  "type": "Feature",
  "properties": {
    "gn:admin1_code":"21",
    "gn:asciiname":"Dudweyne",
    "gn:country_code":"SO",
    "gn:dem":1652,
    "gn:feature_class":"P",
    "gn:feature_code":"PPL",
    "gn:name":"Dudweyne",
    "gn:population":0,
    "gn:timezone":"Africa/Mogadishu",
    "iso:country":"SO",
    "name:und_x_variant":[
        "Dudueyne",
        "Dudweyne"
    ],
    "wof:name":"Dudweyne",
    "wof:placetype":"locality"
},
  "geometry": {"coordinates":[43.35236,9.75271],"type":"Point"}
}