{
  "type": "Feature",
  "properties": {
    "gn:admin1_code":"04",
    "gn:asciiname":"Garas Mankey",
    "gn:country_code":"SO",
    "gn:dem":356,
    "gn:feature_class":"P",
    "gn:feature_code":"PPL",
    "gn:name":"Garas Mankey",
    "gn:population":0,
    "gn:timezone":"Africa/Mogadishu",
    "iso:country":"SO",
    "name:som_x_preferred":[
        "Garas Mankey"
    ],
    "wof:name":"Garas Mankey",
    "wof:placetype":"locality"
},
  "geometry": {"coordinates":[42.822,2.6644],"type":"Point"}
}