{
  "type": "Feature",
  "properties": {
    "gn:admin1_code":"20",
    "gn:asciiname":"Dacarbudhug",
    "gn:country_code":"SO",
    "gn:dem":951,
    "gn:feature_class":"P",
    "gn:feature_code":"PPL",
    "gn:name":"Dacarbudhug",
    "gn:population":0,
    "gn:timezone":"Africa/Mogadishu",
    "iso:country":"SO",
    "name:som_x_preferred":[
        "Dacarbudhug"
    ],
    "name:und_x_variant":[
        "Daarbuduq"
    ],
    "wof:name":"Dacarbudhug",
    "wof:placetype":"locality"
},
  "geometry": {"coordinates":[44.52892,9.86055],"type":"Point"}
}