{
  "type": "Feature",
  "properties": {
    "gn:admin1_code":"22",
    "gn:asciiname":"Daran Taleh",
    "gn:country_code":"SO",
    "gn:dem":573,
    "gn:feature_class":"P",
    "gn:feature_code":"PPL",
    "gn:name":"Daran Taleh",
    "gn:population":0,
    "gn:timezone":"Africa/Mogadishu",
    "iso:country":"SO",
    "name:und_x_variant":[
        "Dallantali",
        "Dallantale",
        "Danan Toleh",
        "Daran Taleh"
    ],
    "wof:name":"Daran Taleh",
    "wof:placetype":"locality"
},
  "geometry": {"coordinates":[48.48333,9.05],"type":"Point"}
}