{
  "type": "Feature",
  "properties": {
    "gn:admin1_code":"04",
    "gn:asciiname":"Gollay",
    "gn:country_code":"SO",
    "gn:dem":203,
    "gn:feature_class":"P",
    "gn:feature_code":"PPL",
    "gn:name":"Gollay",
    "gn:population":0,
    "gn:timezone":"Africa/Mogadishu",
    "iso:country":"SO",
    "name:som_x_preferred":[
        "Gollay"
    ],
    "wof:name":"Gollay",
    "wof:placetype":"locality"
},
  "geometry": {"coordinates":[43.5852,2.3447],"type":"Point"}
}