{
  "type": "Feature",
  "properties": {
    "gn:admin1_code":"4.0",
    "gn:asciiname":"Xaarbiyow",
    "gn:country_code":"SO",
    "gn:dem":490,
    "gn:feature_class":"P",
    "gn:feature_code":"PPL",
    "gn:name":"Xaarbiyow",
    "gn:population":0,
    "gn:timezone":"Africa/Mogadishu",
    "iso:country":"SO",
    "name:som_x_preferred":[
        "Xaarbiyow"
    ],
    "wof:name":"Xaarbiyow",
    "wof:placetype":"locality"
},
  "geometry": {"coordinates":[43.5204,3.2789],"type":"Point"}
}