{
  "type": "Feature",
  "properties": {
    "gn:admin1_code":"22",
    "gn:asciiname":"Fiqishinni",
    "gn:country_code":"SO",
    "gn:dem":625,
    "gn:feature_class":"P",
    "gn:feature_code":"PPL",
    "gn:name":"Fiqishinni",
    "gn:population":0,
    "gn:timezone":"Africa/Mogadishu",
    "iso:country":"SO",
    "name:som_x_preferred":[
        "Fiqishinni"
    ],
    "wof:name":"Fiqishinni",
    "wof:placetype":"locality"
},
  "geometry": {"coordinates":[47.57253,9.13129],"type":"Point"}
}