{
  "type": "Feature",
  "properties": {
    "gn:admin1_code":"04",
    "gn:asciiname":"Boddi Cadde",
    "gn:country_code":"SO",
    "gn:dem":488,
    "gn:feature_class":"P",
    "gn:feature_code":"PPLL",
    "gn:name":"Boddi Cadde",
    "gn:population":0,
    "gn:timezone":"Africa/Mogadishu",
    "iso:country":"SO",
    "name:som_x_preferred":[
        "Boddi Cadde"
    ],
    "wof:name":"Boddi Cadde",
    "wof:placetype":"locality"
},
  "geometry": {"coordinates":[43.5618,3.143],"type":"Point"}
}