{
  "type": "Feature",
  "properties": {
    "gn:admin1_code":"08",
    "gn:asciiname":"Cabdalle Kakane",
    "gn:country_code":"SO",
    "gn:dem":24,
    "gn:feature_class":"P",
    "gn:feature_code":"PPL",
    "gn:name":"Cabdalle Kakane",
    "gn:population":0,
    "gn:timezone":"Africa/Mogadishu",
    "iso:country":"SO",
    "wof:name":"Cabdalle Kakane",
    "wof:placetype":"locality"
},
  "geometry": {"coordinates":[42.75,0.51667],"type":"Point"}
}