{
  "type": "Feature",
  "properties": {
    "gn:admin1_code":"01",
    "gn:asciiname":"Balli Damer",
    "gn:country_code":"SO",
    "gn:dem":518,
    "gn:feature_class":"P",
    "gn:feature_code":"PPL",
    "gn:name":"Balli Damer",
    "gn:population":0,
    "gn:timezone":"Africa/Mogadishu",
    "iso:country":"SO",
    "wof:name":"Balli Damer",
    "wof:placetype":"locality"
},
  "geometry": {"coordinates":[44.02093,4.89804],"type":"Point"}
}