{
  "type": "Feature",
  "properties": {
    "gn:admin1_code":"20.0",
    "gn:asciiname":"Xiinweyni",
    "gn:country_code":"SO",
    "gn:dem":929,
    "gn:feature_class":"P",
    "gn:feature_code":"PPL",
    "gn:name":"Xiinweyni",
    "gn:population":0,
    "gn:timezone":"Africa/Mogadishu",
    "iso:country":"SO",
    "wof:name":"Xiinweyni",
    "wof:placetype":"locality"
},
  "geometry": {"coordinates":[44.88944,9.9575],"type":"Point"}
}