{
  "type": "Feature",
  "properties": {
    "gn:admin1_code":"08",
    "gn:asciiname":"Cilmi",
    "gn:country_code":"SO",
    "gn:dem":56,
    "gn:feature_class":"P",
    "gn:feature_code":"PPL",
    "gn:name":"Cilmi",
    "gn:population":0,
    "gn:timezone":"Africa/Mogadishu",
    "iso:country":"SO",
    "wof:name":"Cilmi",
    "wof:placetype":"locality"
},
  "geometry": {"coordinates":[42.42013,1.42742],"type":"Point"}
}