{
  "type": "Feature",
  "properties": {
    "gn:admin1_code":"06",
    "gn:asciiname":"Xero-Koowaad",
    "gn:country_code":"SO",
    "gn:dem":152,
    "gn:feature_class":"P",
    "gn:feature_code":"PPL",
    "gn:name":"Xero-Koowaad",
    "gn:population":0,
    "gn:timezone":"Africa/Mogadishu",
    "iso:country":"SO",
    "wof:name":"Xero-Koowaad",
    "wof:placetype":"locality"
},
  "geometry": {"coordinates":[42.52913,3.79587],"type":"Point"}
}