{
  "type": "Feature",
  "properties": {
    "gn:admin1_code":"14",
    "gn:asciiname":"Ibrahim Mursal",
    "gn:country_code":"SO",
    "gn:dem":85,
    "gn:feature_class":"P",
    "gn:feature_code":"PPL",
    "gn:name":"Ibrahim Mursal",
    "gn:population":0,
    "gn:timezone":"Africa/Mogadishu",
    "iso:country":"SO",
    "name:som_x_preferred":[
        "Ibrahim Mursal"
    ],
    "wof:name":"Ibrahim Mursal",
    "wof:placetype":"locality"
},
  "geometry": {"coordinates":[44.7821,2.3463],"type":"Point"}
}