{
  "type": "Feature",
  "properties": {
    "gn:admin1_code":"14",
    "gn:asciiname":"Aesow",
    "gn:country_code":"SO",
    "gn:dem":73,
    "gn:feature_class":"P",
    "gn:feature_code":"PPL",
    "gn:name":"Aesow",
    "gn:population":0,
    "gn:timezone":"Africa/Mogadishu",
    "iso:country":"SO",
    "name:som_x_preferred":[
        "Aesow"
    ],
    "wof:name":"Aesow",
    "wof:placetype":"locality"
},
  "geometry": {"coordinates":[44.6056,1.7505],"type":"Point"}
}