{
  "type": "Feature",
  "properties": {
    "gn:admin1_code":"14",
    "gn:asciiname":"Aysuure",
    "gn:country_code":"SO",
    "gn:dem":45,
    "gn:feature_class":"P",
    "gn:feature_code":"PPL",
    "gn:name":"Aysuure",
    "gn:population":0,
    "gn:timezone":"Africa/Mogadishu",
    "iso:country":"SO",
    "name:som_x_preferred":[
        "Aysuure"
    ],
    "wof:name":"Aysuure",
    "wof:placetype":"locality"
},
  "geometry": {"coordinates":[43.8461,1.0519],"type":"Point"}
}