{
  "type": "Feature",
  "properties": {
    "gn:admin1_code":"09",
    "gn:asciiname":"Baasaay",
    "gn:country_code":"SO",
    "gn:dem":15,
    "gn:feature_class":"P",
    "gn:feature_code":"PPL",
    "gn:name":"Baasaay",
    "gn:population":0,
    "gn:timezone":"Africa/Mogadishu",
    "iso:country":"SO",
    "wof:name":"Baasaay",
    "wof:placetype":"locality"
},
  "geometry": {"coordinates":[42.7436,0.25927],"type":"Point"}
}