{
  "type": "Feature",
  "properties": {
    "gn:admin1_code":"01",
    "gn:asciiname":"Dermangit",
    "gn:country_code":"SO",
    "gn:dem":303,
    "gn:feature_class":"P",
    "gn:feature_code":"PPL",
    "gn:name":"Dermangit",
    "gn:population":0,
    "gn:timezone":"Africa/Mogadishu",
    "iso:country":"SO",
    "wof:name":"Dermangit",
    "wof:placetype":"locality"
},
  "geometry": {"coordinates":[42.9857,4.34042],"type":"Point"}
}