{
  "type": "Feature",
  "properties": {
    "gn:admin1_code":"04",
    "gn:asciiname":"Caddi Qoqonay",
    "gn:country_code":"SO",
    "gn:dem":482,
    "gn:feature_class":"P",
    "gn:feature_code":"PPL",
    "gn:name":"Caddi Qoqonay",
    "gn:population":0,
    "gn:timezone":"Africa/Mogadishu",
    "iso:country":"SO",
    "name:som_x_preferred":[
        "Caddi Qoqonay"
    ],
    "wof:name":"Caddi Qoqonay",
    "wof:placetype":"locality"
},
  "geometry": {"coordinates":[43.5168,3.106],"type":"Point"}
}