{
  "type": "Feature",
  "properties": {
    "gn:admin1_code":"09",
    "gn:asciiname":"Arar Yarey",
    "gn:country_code":"SO",
    "gn:dem":5,
    "gn:feature_class":"P",
    "gn:feature_code":"PPL",
    "gn:name":"Arar Yarey",
    "gn:population":0,
    "gn:timezone":"Africa/Mogadishu",
    "iso:country":"SO",
    "name:und_x_variant":[
        "Harara Iere",
        "Arar Yarey"
    ],
    "wof:name":"Arar Yarey",
    "wof:placetype":"locality"
},
  "geometry": {"coordinates":[42.66591,0.01753],"type":"Point"}
}