{
  "type": "Feature",
  "properties": {
    "gn:admin1_code":"14",
    "gn:asciiname":"Silmow",
    "gn:country_code":"SO",
    "gn:dem":72,
    "gn:feature_class":"P",
    "gn:feature_code":"PPL",
    "gn:name":"Silmow",
    "gn:population":0,
    "gn:timezone":"Africa/Mogadishu",
    "iso:country":"SO",
    "name:som_x_preferred":[
        "Silmow"
    ],
    "wof:name":"Silmow",
    "wof:placetype":"locality"
},
  "geometry": {"coordinates":[44.6412,1.7932],"type":"Point"}
}