{
  "type": "Feature",
  "properties": {
    "gn:admin1_code":"14",
    "gn:asciiname":"Doon Idow",
    "gn:country_code":"SO",
    "gn:dem":65,
    "gn:feature_class":"P",
    "gn:feature_code":"PPL",
    "gn:name":"Doon Idow",
    "gn:population":0,
    "gn:timezone":"Africa/Mogadishu",
    "iso:country":"SO",
    "name:som_x_preferred":[
        "Doon Idow"
    ],
    "wof:name":"Doon Idow",
    "wof:placetype":"locality"
},
  "geometry": {"coordinates":[44.4364,1.6955],"type":"Point"}
}