{
  "type": "Feature",
  "properties": {
    "gn:admin1_code":"22",
    "gn:asciiname":"Hargo",
    "gn:country_code":"SO",
    "gn:dem":765,
    "gn:feature_class":"P",
    "gn:feature_code":"PPL",
    "gn:name":"Hargo",
    "gn:population":0,
    "gn:timezone":"Africa/Mogadishu",
    "iso:country":"SO",
    "name:som_x_preferred":[
        "Hargo"
    ],
    "wof:name":"Hargo",
    "wof:placetype":"locality"
},
  "geometry": {"coordinates":[46.49822,9.49175],"type":"Point"}
}