{
  "type": "Feature",
  "properties": {
    "gn:admin1_code":"21",
    "gn:asciiname":"Abakor Cadaawe",
    "gn:country_code":"SO",
    "gn:dem":1028,
    "gn:feature_class":"P",
    "gn:feature_code":"PPL",
    "gn:name":"Abakor Cadaawe",
    "gn:population":0,
    "gn:timezone":"Africa/Mogadishu",
    "iso:country":"SO",
    "name:som_x_preferred":[
        "Abakor Cadaawe"
    ],
    "wof:name":"Abakor Cadaawe",
    "wof:placetype":"locality"
},
  "geometry": {"coordinates":[43.34643,10.03279],"type":"Point"}
}