{
  "type": "Feature",
  "properties": {
    "gn:admin1_code":"14.0",
    "gn:asciiname":"Reeboy",
    "gn:country_code":"SO",
    "gn:dem":52,
    "gn:feature_class":"P",
    "gn:feature_code":"PPL",
    "gn:name":"Reeboy",
    "gn:population":0,
    "gn:timezone":"Africa/Mogadishu",
    "iso:country":"SO",
    "name:som_x_preferred":[
        "Reeboy"
    ],
    "name:und_x_variant":[
        "Reebooy"
    ],
    "wof:name":"Reeboy",
    "wof:placetype":"locality"
},
  "geometry": {"coordinates":[43.9063,1.4035],"type":"Point"}
}