{
  "type": "Feature",
  "properties": {
    "gn:admin1_code":"13",
    "gn:asciiname":"Buur Xaano",
    "gn:country_code":"SO",
    "gn:dem":120,
    "gn:feature_class":"P",
    "gn:feature_code":"PPL",
    "gn:name":"Buur Xaano",
    "gn:population":0,
    "gn:timezone":"Africa/Mogadishu",
    "iso:country":"SO",
    "name:som_x_preferred":[
        "Buur Xaano"
    ],
    "wof:name":"Buur Xaano",
    "wof:placetype":"locality"
},
  "geometry": {"coordinates":[45.46691,3.17811],"type":"Point"}
}