{
  "type": "Feature",
  "properties": {
    "gn:admin1_code":"7.0",
    "gn:asciiname":"Siiboy",
    "gn:country_code":"SO",
    "gn:dem":137,
    "gn:feature_class":"P",
    "gn:feature_code":"PPL",
    "gn:name":"Siiboy",
    "gn:population":0,
    "gn:timezone":"Africa/Mogadishu",
    "iso:country":"SO",
    "name:som_x_preferred":[
        "Siiboy"
    ],
    "name:und_x_variant":[
        "Sivai"
    ],
    "wof:name":"Siiboy",
    "wof:placetype":"locality"
},
  "geometry": {"coordinates":[45.65337,3.56698],"type":"Point"}
}