{
  "type": "Feature",
  "properties": {
    "gn:admin1_code":"19",
    "gn:asciiname":"Ceeg Bilcille",
    "gn:country_code":"SO",
    "gn:dem":1052,
    "gn:feature_class":"P",
    "gn:feature_code":"PPL",
    "gn:name":"Ceeg Bilcille",
    "gn:population":0,
    "gn:timezone":"Africa/Mogadishu",
    "iso:country":"SO",
    "name:som_x_preferred":[
        "Ceeg Bilcille"
    ],
    "name:und_x_variant":[
        "\u2018Eik Bil\u2018ileh",
        "El Bilile"
    ],
    "wof:name":"Ceeg Bilcille",
    "wof:placetype":"locality"
},
  "geometry": {"coordinates":[45.2454,9.38347],"type":"Point"}
}