{
  "type": "Feature",
  "properties": {
    "gn:admin1_code":"04",
    "gn:asciiname":"Dhagardheere",
    "gn:country_code":"SO",
    "gn:dem":166,
    "gn:feature_class":"P",
    "gn:feature_code":"PPL",
    "gn:name":"Dhagardheere",
    "gn:population":0,
    "gn:timezone":"Africa/Mogadishu",
    "iso:country":"SO",
    "name:som_x_preferred":[
        "Dhagardheere"
    ],
    "wof:name":"Dhagardheere",
    "wof:placetype":"locality"
},
  "geometry": {"coordinates":[44.01219,2.52162],"type":"Point"}
}