{
  "type": "Feature",
  "properties": {
    "gn:admin1_code":"6.0",
    "gn:asciiname":"Unzi Guddo",
    "gn:country_code":"SO",
    "gn:dem":217,
    "gn:feature_class":"P",
    "gn:feature_code":"PPL",
    "gn:name":"Unzi Guddo",
    "gn:population":0,
    "gn:timezone":"Africa/Mogadishu",
    "iso:country":"SO",
    "wof:name":"Unzi Guddo",
    "wof:placetype":"locality"
},
  "geometry": {"coordinates":[41.96667,4.03333],"type":"Point"}
}