{
  "type": "Feature",
  "properties": {
    "gn:admin1_code":"21",
    "gn:asciiname":"Karuure",
    "gn:country_code":"SO",
    "gn:dem":85,
    "gn:feature_class":"P",
    "gn:feature_code":"PPL",
    "gn:name":"Karuure",
    "gn:population":0,
    "gn:timezone":"Africa/Mogadishu",
    "iso:country":"SO",
    "name:som_x_preferred":[
        "Karuure"
    ],
    "wof:name":"Karuure",
    "wof:placetype":"locality"
},
  "geometry": {"coordinates":[43.59141,10.75215],"type":"Point"}
}