{
  "type": "Feature",
  "properties": {
    "gn:admin1_code":"04",
    "gn:asciiname":"Cumarow Maddow",
    "gn:country_code":"SO",
    "gn:dem":511,
    "gn:feature_class":"P",
    "gn:feature_code":"PPL",
    "gn:name":"Cumarow Maddow",
    "gn:population":0,
    "gn:timezone":"Africa/Mogadishu",
    "iso:country":"SO",
    "name:som_x_preferred":[
        "Cumarow Maddow"
    ],
    "wof:name":"Cumarow Maddow",
    "wof:placetype":"locality"
},
  "geometry": {"coordinates":[43.6142,3.285],"type":"Point"}
}