{
  "type": "Feature",
  "properties": {
    "gn:admin1_code":"22",
    "gn:asciiname":"Higlofilgin",
    "gn:country_code":"SO",
    "gn:dem":673,
    "gn:feature_class":"P",
    "gn:feature_code":"PPL",
    "gn:name":"Higlofilgin",
    "gn:population":0,
    "gn:timezone":"Africa/Mogadishu",
    "iso:country":"SO",
    "name:rus_x_preferred":[
        "Khiglofil\u2019gin"
    ],
    "wof:name":"Higlofilgin",
    "wof:placetype":"locality"
},
  "geometry": {"coordinates":[47.22722,8.03667],"type":"Point"}
}