{
  "type": "Feature",
  "properties": {
    "gn:admin1_code":"6.0",
    "gn:asciiname":"Mardha",
    "gn:country_code":"SO",
    "gn:dem":94,
    "gn:feature_class":"P",
    "gn:feature_code":"PPL",
    "gn:name":"Mardha",
    "gn:population":0,
    "gn:timezone":"Africa/Mogadishu",
    "iso:country":"SO",
    "name:und_x_variant":[
        "Marda"
    ],
    "wof:name":"Mardha",
    "wof:placetype":"locality"
},
  "geometry": {"coordinates":[42.33294,2.39873],"type":"Point"}
}