{
  "type": "Feature",
  "properties": {
    "gn:admin1_code":"14.0",
    "gn:asciiname":"Marsaan",
    "gn:country_code":"SO",
    "gn:dem":70,
    "gn:feature_class":"P",
    "gn:feature_code":"PPL",
    "gn:name":"Marsaan",
    "gn:population":0,
    "gn:timezone":"Africa/Mogadishu",
    "iso:country":"SO",
    "name:som_x_preferred":[
        "Marsaan"
    ],
    "wof:name":"Marsaan",
    "wof:placetype":"locality"
},
  "geometry": {"coordinates":[44.7279,1.8182],"type":"Point"}
}