{
  "type": "Feature",
  "properties": {
    "gn:admin1_code":"13",
    "gn:asciiname":"Gumarrey",
    "gn:country_code":"SO",
    "gn:dem":106,
    "gn:feature_class":"P",
    "gn:feature_code":"PPL",
    "gn:name":"Gumarrey",
    "gn:population":0,
    "gn:timezone":"Africa/Mogadishu",
    "iso:country":"SO",
    "name:som_x_preferred":[
        "Gumarrey"
    ],
    "wof:name":"Gumarrey",
    "wof:placetype":"locality"
},
  "geometry": {"coordinates":[45.37807,2.76759],"type":"Point"}
}