{
  "type": "Feature",
  "properties": {
    "gn:admin1_code":"04",
    "gn:asciiname":"Guumisole",
    "gn:country_code":"SO",
    "gn:dem":286,
    "gn:feature_class":"P",
    "gn:feature_code":"PPL",
    "gn:name":"Guumisole",
    "gn:population":0,
    "gn:timezone":"Africa/Mogadishu",
    "iso:country":"SO",
    "name:som_x_preferred":[
        "Guumisole"
    ],
    "wof:name":"Guumisole",
    "wof:placetype":"locality"
},
  "geometry": {"coordinates":[43.9274,3.0603],"type":"Point"}
}