{
  "type": "Feature",
  "properties": {
    "gn:admin1_code":"06",
    "gn:asciiname":"Booraame",
    "gn:cc2":"SO",
    "gn:country_code":"SO",
    "gn:dem":142,
    "gn:feature_class":"P",
    "gn:feature_code":"PPL",
    "gn:name":"Booraame",
    "gn:population":0,
    "gn:timezone":"Africa/Mogadishu",
    "iso:country":"SO",
    "name:und_x_variant":[
        "B\u014dr\u0101me",
        "Boramo",
        "Borama",
        "Booraame"
    ],
    "wof:name":"Booraame",
    "wof:placetype":"locality"
},
  "geometry": {"coordinates":[42.55,3.45],"type":"Point"}
}