{
  "type": "Feature",
  "properties": {
    "gn:admin1_code":"4.0",
    "gn:asciiname":"Moro Goloole",
    "gn:country_code":"SO",
    "gn:dem":427,
    "gn:feature_class":"P",
    "gn:feature_code":"PPL",
    "gn:name":"Moro Goloole",
    "gn:population":0,
    "gn:timezone":"Africa/Mogadishu",
    "iso:country":"SO",
    "name:som_x_preferred":[
        "Moro Goloole"
    ],
    "wof:name":"Moro Goloole",
    "wof:placetype":"locality"
},
  "geometry": {"coordinates":[43.23621,3.30021],"type":"Point"}
}