{
  "type": "Feature",
  "properties": {
    "gn:admin1_code":"06",
    "gn:asciiname":"Hara Buti",
    "gn:country_code":"SO",
    "gn:dem":517,
    "gn:feature_class":"P",
    "gn:feature_code":"PPL",
    "gn:name":"Hara Buti",
    "gn:population":0,
    "gn:timezone":"Africa/Mogadishu",
    "iso:country":"SO",
    "wof:name":"Hara Buti",
    "wof:placetype":"locality"
},
  "geometry": {"coordinates":[41.45,3.28333],"type":"Point"}
}