{
  "type": "Feature",
  "properties": {
    "gn:admin1_code":"06",
    "gn:asciiname":"Bililscia",
    "gn:country_code":"SO",
    "gn:dem":281,
    "gn:feature_class":"P",
    "gn:feature_code":"PPL",
    "gn:name":"Bililscia",
    "gn:population":0,
    "gn:timezone":"Africa/Mogadishu",
    "iso:country":"SO",
    "wof:name":"Bililscia",
    "wof:placetype":"locality"
},
  "geometry": {"coordinates":[41.31667,2.53333],"type":"Point"}
}