{
  "type": "Feature",
  "properties": {
    "gn:admin1_code":"14",
    "gn:asciiname":"Dudumaay",
    "gn:country_code":"SO",
    "gn:dem":87,
    "gn:feature_class":"P",
    "gn:feature_code":"PPL",
    "gn:name":"Dudumaay",
    "gn:population":0,
    "gn:timezone":"Africa/Mogadishu",
    "iso:country":"SO",
    "name:som_x_preferred":[
        "Dudumaay"
    ],
    "name:und_x_variant":[
        "Duddumai",
        "Dudumaay"
    ],
    "wof:name":"Dudumaay",
    "wof:placetype":"locality"
},
  "geometry": {"coordinates":[44.79946,2.57996],"type":"Point"}
}