{
  "type": "Feature",
  "properties": {
    "gn:admin1_code":"04",
    "gn:asciiname":"Baanyale Goof Galoole",
    "gn:country_code":"SO",
    "gn:dem":324,
    "gn:feature_class":"P",
    "gn:feature_code":"PPL",
    "gn:name":"Baanyale Goof Galoole",
    "gn:population":0,
    "gn:timezone":"Africa/Mogadishu",
    "iso:country":"SO",
    "name:som_x_preferred":[
        "Baanyale Goof Galoole"
    ],
    "name:und_x_variant":[
        "Baanyale Goot Galoole"
    ],
    "wof:name":"Baanyale Goof Galoole",
    "wof:placetype":"locality"
},
  "geometry": {"coordinates":[43.7501,3.0289],"type":"Point"}
}