{
  "type": "Feature",
  "properties": {
    "gn:admin1_code":"14",
    "gn:asciiname":"Garowle",
    "gn:country_code":"SO",
    "gn:dem":59,
    "gn:feature_class":"P",
    "gn:feature_code":"PPLL",
    "gn:name":"Garowle",
    "gn:population":0,
    "gn:timezone":"Africa/Mogadishu",
    "iso:country":"SO",
    "name:som_x_preferred":[
        "Garowle"
    ],
    "wof:name":"Garowle",
    "wof:placetype":"locality"
},
  "geometry": {"coordinates":[44.2857,1.6547],"type":"Point"}
}