{
  "type": "Feature",
  "properties": {
    "gn:admin1_code":"14.0",
    "gn:asciiname":"Luusi",
    "gn:country_code":"SO",
    "gn:dem":69,
    "gn:feature_class":"P",
    "gn:feature_code":"PPL",
    "gn:name":"Luusi",
    "gn:population":0,
    "gn:timezone":"Africa/Mogadishu",
    "iso:country":"SO",
    "name:som_x_preferred":[
        "Luusi"
    ],
    "wof:name":"Luusi",
    "wof:placetype":"locality"
},
  "geometry": {"coordinates":[44.6698,1.7358],"type":"Point"}
}