{
  "type": "Feature",
  "properties": {
    "gn:admin1_code":"03",
    "gn:asciiname":"Gaatir Oodan",
    "gn:country_code":"SO",
    "gn:dem":1240,
    "gn:feature_class":"P",
    "gn:feature_code":"PPL",
    "gn:name":"Gaatir Oodan",
    "gn:population":0,
    "gn:timezone":"Africa/Mogadishu",
    "iso:country":"SO",
    "name:som_x_preferred":[
        "Gaatir Oodan"
    ],
    "wof:name":"Gaatir Oodan",
    "wof:placetype":"locality"
},
  "geometry": {"coordinates":[49.94127,11.02971],"type":"Point"}
}