{
  "type": "Feature",
  "properties": {
    "gn:admin1_code":"14.0",
    "gn:asciiname":"Shiikh",
    "gn:country_code":"SO",
    "gn:dem":70,
    "gn:feature_class":"P",
    "gn:feature_code":"PPL",
    "gn:name":"Shiikh",
    "gn:population":0,
    "gn:timezone":"Africa/Mogadishu",
    "iso:country":"SO",
    "name:som_x_preferred":[
        "Shiikh"
    ],
    "wof:name":"Shiikh",
    "wof:placetype":"locality"
},
  "geometry": {"coordinates":[44.5604,1.7503],"type":"Point"}
}