{
  "type": "Feature",
  "properties": {
    "gn:admin1_code":"14.0",
    "gn:asciiname":"Shaan",
    "gn:country_code":"SO",
    "gn:dem":81,
    "gn:feature_class":"P",
    "gn:feature_code":"PPL",
    "gn:name":"Shaan",
    "gn:population":0,
    "gn:timezone":"Africa/Mogadishu",
    "iso:country":"SO",
    "name:som_x_preferred":[
        "Shaan"
    ],
    "name:und_x_variant":[
        "Scian",
        "Shaan"
    ],
    "wof:name":"Shaan",
    "wof:placetype":"locality"
},
  "geometry": {"coordinates":[44.8595,2.0283],"type":"Point"}
}