{
  "type": "Feature",
  "properties": {
    "gn:admin1_code":"14",
    "gn:asciiname":"Ay Buulleey",
    "gn:country_code":"SO",
    "gn:dem":93,
    "gn:feature_class":"P",
    "gn:feature_code":"PPL",
    "gn:name":"Ay Buulleey",
    "gn:population":0,
    "gn:timezone":"Africa/Mogadishu",
    "iso:country":"SO",
    "name:som_x_preferred":[
        "Ay Buulleey"
    ],
    "wof:name":"Ay Buulleey",
    "wof:placetype":"locality"
},
  "geometry": {"coordinates":[44.97017,2.64846],"type":"Point"}
}