{
  "type": "Feature",
  "properties": {
    "gn:admin1_code":"3.0",
    "gn:asciiname":"Majiyohan",
    "gn:country_code":"SO",
    "gn:dem":218,
    "gn:feature_class":"P",
    "gn:feature_code":"PPL",
    "gn:name":"Majiyohan",
    "gn:population":0,
    "gn:timezone":"Africa/Mogadishu",
    "iso:country":"SO",
    "name:ceb_x_preferred":[
        "Majiyohan"
    ],
    "name:fas_x_preferred":[
        "\u0645\u062c\u06cc\u0648\u0647\u0627\u0646"
    ],
    "name:som_x_preferred":[
        "Majiyohan"
    ],
    "name:som_x_variant":[
        "Majiyahan"
    ],
    "wof:name":"Majiyohan",
    "wof:placetype":"locality"
},
  "geometry": {"coordinates":[49.0095,11.0692],"type":"Point"}
}