{
  "type": "Feature",
  "properties": {
    "gn:admin1_code":"04",
    "gn:asciiname":"Buulo Garas",
    "gn:country_code":"SO",
    "gn:dem":422,
    "gn:feature_class":"P",
    "gn:feature_code":"PPL",
    "gn:name":"Buulo Garas",
    "gn:population":0,
    "gn:timezone":"Africa/Mogadishu",
    "iso:country":"SO",
    "name:som_x_preferred":[
        "Buulo Garas"
    ],
    "wof:name":"Buulo Garas",
    "wof:placetype":"locality"
},
  "geometry": {"coordinates":[42.98011,2.85456],"type":"Point"}
}