{
  "type": "Feature",
  "properties": {
    "gn:admin1_code":"01",
    "gn:asciiname":"Buur Caddey",
    "gn:country_code":"SO",
    "gn:dem":429,
    "gn:feature_class":"P",
    "gn:feature_code":"PPL",
    "gn:name":"Buur Caddey",
    "gn:population":0,
    "gn:timezone":"Africa/Mogadishu",
    "iso:country":"SO",
    "name:som_x_preferred":[
        "Buur Caddey"
    ],
    "wof:name":"Buur Caddey",
    "wof:placetype":"locality"
},
  "geometry": {"coordinates":[43.3452,4.0658],"type":"Point"}
}