{
  "type": "Feature",
  "properties": {
    "gn:admin1_code":"06",
    "gn:asciiname":"Shaatilow",
    "gn:country_code":"SO",
    "gn:dem":165,
    "gn:feature_class":"P",
    "gn:feature_code":"PPL",
    "gn:name":"Shaatilow",
    "gn:population":0,
    "gn:timezone":"Africa/Mogadishu",
    "iso:country":"SO",
    "wof:name":"Shaatilow",
    "wof:placetype":"locality"
},
  "geometry": {"coordinates":[42.42407,3.90506],"type":"Point"}
}