{
  "type": "Feature",
  "properties": {
    "gn:admin1_code":"06",
    "gn:asciiname":"Dheenlo",
    "gn:country_code":"SO",
    "gn:dem":291,
    "gn:feature_class":"P",
    "gn:feature_code":"PPL",
    "gn:name":"Dheenlo",
    "gn:population":0,
    "gn:timezone":"Africa/Mogadishu",
    "iso:country":"SO",
    "name:som_x_preferred":[
        "Dheenlo"
    ],
    "name:und_x_variant":[
        "Denli",
        "El Denle",
        "Dheenlo"
    ],
    "wof:name":"Dheenlo",
    "wof:placetype":"locality"
},
  "geometry": {"coordinates":[42.10243,2.81047],"type":"Point"}
}