{
  "type": "Feature",
  "properties": {
    "gn:admin1_code":"4.0",
    "gn:asciiname":"Siigolay",
    "gn:country_code":"SO",
    "gn:dem":269,
    "gn:feature_class":"P",
    "gn:feature_code":"PPL",
    "gn:name":"Siigolay",
    "gn:population":0,
    "gn:timezone":"Africa/Mogadishu",
    "iso:country":"SO",
    "name:som_x_preferred":[
        "Siigolay"
    ],
    "wof:name":"Siigolay",
    "wof:placetype":"locality"
},
  "geometry": {"coordinates":[43.7801,2.87887],"type":"Point"}
}