{
  "type": "Feature",
  "properties": {
    "gn:admin1_code":"20.0",
    "gn:asciiname":"Sciarer",
    "gn:country_code":"SO",
    "gn:dem":778,
    "gn:feature_class":"P",
    "gn:feature_code":"PPL",
    "gn:name":"Sciarer",
    "gn:population":0,
    "gn:timezone":"Africa/Mogadishu",
    "iso:country":"SO",
    "wof:name":"Sciarer",
    "wof:placetype":"locality"
},
  "geometry": {"coordinates":[41.86667,9.93333],"type":"Point"}
}