{
  "type": "Feature",
  "properties": {
    "gn:admin1_code":"13.0",
    "gn:asciiname":"Mola Borale",
    "gn:country_code":"SO",
    "gn:dem":124,
    "gn:feature_class":"P",
    "gn:feature_code":"PPL",
    "gn:name":"Mola Borale",
    "gn:population":0,
    "gn:timezone":"Africa/Mogadishu",
    "iso:country":"SO",
    "wof:name":"Mola Borale",
    "wof:placetype":"locality"
},
  "geometry": {"coordinates":[45.76667,3.21667],"type":"Point"}
}