{
  "type": "Feature",
  "properties": {
    "gn:admin1_code":"14",
    "gn:asciiname":"Dangnerrei",
    "gn:cc2":"SO",
    "gn:country_code":"SO",
    "gn:dem":78,
    "gn:feature_class":"P",
    "gn:feature_code":"PPL",
    "gn:name":"Dangnerrei",
    "gn:population":0,
    "gn:timezone":"Africa/Mogadishu",
    "iso:country":"SO",
    "name:und_x_variant":[
        "Dagnerei",
        "Dangnerei",
        "Dangnerrei"
    ],
    "wof:name":"Dangnerrei",
    "wof:placetype":"locality"
},
  "geometry": {"coordinates":[44.78333,1.91667],"type":"Point"}
}