{
  "type": "Feature",
  "properties": {
    "gn:admin1_code":"13.0",
    "gn:asciiname":"Xagarow",
    "gn:country_code":"SO",
    "gn:dem":99,
    "gn:feature_class":"P",
    "gn:feature_code":"PPL",
    "gn:name":"Xagarow",
    "gn:population":0,
    "gn:timezone":"Africa/Mogadishu",
    "iso:country":"SO",
    "name:som_x_preferred":[
        "Xagarow"
    ],
    "wof:name":"Xagarow",
    "wof:placetype":"locality"
},
  "geometry": {"coordinates":[45.41335,2.42132],"type":"Point"}
}