{
  "type": "Feature",
  "properties": {
    "gn:admin1_code":"06",
    "gn:asciiname":"Burje",
    "gn:country_code":"SO",
    "gn:dem":155,
    "gn:feature_class":"P",
    "gn:feature_code":"PPL",
    "gn:name":"Burje",
    "gn:population":0,
    "gn:timezone":"Africa/Mogadishu",
    "iso:country":"SO",
    "wof:name":"Burje",
    "wof:placetype":"locality"
},
  "geometry": {"coordinates":[42.52312,3.8196],"type":"Point"}
}