{
  "type": "Feature",
  "properties": {
    "gn:admin1_code":"06",
    "gn:asciiname":"Barwaaqo",
    "gn:country_code":"SO",
    "gn:dem":187,
    "gn:feature_class":"P",
    "gn:feature_code":"PPL",
    "gn:name":"Barwaaqo",
    "gn:population":0,
    "gn:timezone":"Africa/Mogadishu",
    "iso:country":"SO",
    "wof:name":"Barwaaqo",
    "wof:placetype":"locality"
},
  "geometry": {"coordinates":[42.18681,3.48318],"type":"Point"}
}