{
  "type": "Feature",
  "properties": {
    "gn:admin1_code":"4.0",
    "gn:asciiname":"Lolisc`e",
    "gn:country_code":"SO",
    "gn:dem":482,
    "gn:feature_class":"P",
    "gn:feature_code":"PPL",
    "gn:name":"Lolisc\u2018e",
    "gn:population":0,
    "gn:timezone":"Africa/Mogadishu",
    "iso:country":"SO",
    "wof:name":"Lolisc`e",
    "wof:placetype":"locality"
},
  "geometry": {"coordinates":[44.05,3.28333],"type":"Point"}
}