{
  "type": "Feature",
  "properties": {
    "gn:admin1_code":"04",
    "gn:asciiname":"Gobley",
    "gn:country_code":"SO",
    "gn:dem":502,
    "gn:feature_class":"P",
    "gn:feature_code":"PPL",
    "gn:name":"Gobley",
    "gn:population":0,
    "gn:timezone":"Africa/Mogadishu",
    "iso:country":"SO",
    "name:som_x_preferred":[
        "Gobley"
    ],
    "wof:name":"Gobley",
    "wof:placetype":"locality"
},
  "geometry": {"coordinates":[43.5845,3.2381],"type":"Point"}
}