{
  "type": "Feature",
  "properties": {
    "gn:admin1_code":"04",
    "gn:asciiname":"Hartiqanle",
    "gn:country_code":"SO",
    "gn:dem":528,
    "gn:feature_class":"P",
    "gn:feature_code":"PPLL",
    "gn:name":"Hartiqanle",
    "gn:population":0,
    "gn:timezone":"Africa/Mogadishu",
    "iso:country":"SO",
    "name:som_x_preferred":[
        "Hartiqanle"
    ],
    "wof:name":"Hartiqanle",
    "wof:placetype":"locality"
},
  "geometry": {"coordinates":[43.6897,3.2912],"type":"Point"}
}