{
  "type": "Feature",
  "properties": {
    "gn:admin1_code":"9.0",
    "gn:asciiname":"Murjaan",
    "gn:country_code":"SO",
    "gn:dem":13,
    "gn:feature_class":"P",
    "gn:feature_code":"PPL",
    "gn:name":"Murjaan",
    "gn:population":0,
    "gn:timezone":"Africa/Mogadishu",
    "iso:country":"SO",
    "wof:name":"Murjaan",
    "wof:placetype":"locality"
},
  "geometry": {"coordinates":[42.74663,0.25454],"type":"Point"}
}