{
  "type": "Feature",
  "properties": {
    "gn:admin1_code":"04",
    "gn:asciiname":"Ay Guud Wiin",
    "gn:country_code":"SO",
    "gn:dem":185,
    "gn:feature_class":"P",
    "gn:feature_code":"PPL",
    "gn:name":"Ay Guud Wiin",
    "gn:population":0,
    "gn:timezone":"Africa/Mogadishu",
    "iso:country":"SO",
    "name:som_x_preferred":[
        "Ay Guud Wiin"
    ],
    "wof:name":"Ay Guud Wiin",
    "wof:placetype":"locality"
},
  "geometry": {"coordinates":[44.2115,2.8023],"type":"Point"}
}