{
  "type": "Feature",
  "properties": {
    "gn:admin1_code":"4.0",
    "gn:asciiname":"Low Buulo",
    "gn:country_code":"SO",
    "gn:dem":287,
    "gn:feature_class":"P",
    "gn:feature_code":"PPL",
    "gn:name":"Low Buulo",
    "gn:population":0,
    "gn:timezone":"Africa/Mogadishu",
    "iso:country":"SO",
    "name:som_x_preferred":[
        "Low Buulo"
    ],
    "wof:name":"Low Buulo",
    "wof:placetype":"locality"
},
  "geometry": {"coordinates":[43.80024,2.99314],"type":"Point"}
}