{
  "type": "Feature",
  "properties": {
    "gn:admin1_code":"01",
    "gn:asciiname":"Idannug",
    "gn:country_code":"SO",
    "gn:dem":401,
    "gn:feature_class":"P",
    "gn:feature_code":"PPL",
    "gn:name":"Idannug",
    "gn:population":0,
    "gn:timezone":"Africa/Mogadishu",
    "iso:country":"SO",
    "wof:name":"Idannug",
    "wof:placetype":"locality"
},
  "geometry": {"coordinates":[43.32296,3.84557],"type":"Point"}
}