{
  "type": "Feature",
  "properties": {
    "gn:admin1_code":"14",
    "gn:asciiname":"Gawaanis",
    "gn:country_code":"SO",
    "gn:dem":103,
    "gn:feature_class":"P",
    "gn:feature_code":"PPL",
    "gn:name":"Gawaanis",
    "gn:population":0,
    "gn:timezone":"Africa/Mogadishu",
    "iso:country":"SO",
    "name:som_x_preferred":[
        "Gawaanis"
    ],
    "wof:name":"Gawaanis",
    "wof:placetype":"locality"
},
  "geometry": {"coordinates":[45.1651,2.8683],"type":"Point"}
}