{
  "type": "Feature",
  "properties": {
    "gn:admin1_code":"08",
    "gn:asciiname":"Jilaalow",
    "gn:country_code":"SO",
    "gn:dem":36,
    "gn:feature_class":"P",
    "gn:feature_code":"PPL",
    "gn:name":"Jilaalow",
    "gn:population":0,
    "gn:timezone":"Africa/Mogadishu",
    "iso:country":"SO",
    "name:und_x_variant":[
        "Mabungo",
        "Jilaalow"
    ],
    "wof:name":"Jilaalow",
    "wof:placetype":"locality"
},
  "geometry": {"coordinates":[42.59614000000001,0.83008],"type":"Point"}
}