{
  "type": "Feature",
  "properties": {
    "gn:admin1_code":"05",
    "gn:asciiname":"Bulacle",
    "gn:country_code":"SO",
    "gn:dem":223,
    "gn:feature_class":"P",
    "gn:feature_code":"PPL",
    "gn:name":"Bulacle",
    "gn:population":0,
    "gn:timezone":"Africa/Mogadishu",
    "iso:country":"SO",
    "name:som_x_preferred":[
        "Bulacle"
    ],
    "name:und_x_variant":[
        "Bulhale",
        "Bulac"
    ],
    "wof:name":"Bulacle",
    "wof:placetype":"locality"
},
  "geometry": {"coordinates":[46.4779,5.3324],"type":"Point"}
}