{
  "type": "Feature",
  "properties": {
    "gn:admin1_code":"0.0",
    "gn:asciiname":"Xaaxi",
    "gn:country_code":"SO",
    "gn:dem":1019,
    "gn:feature_class":"P",
    "gn:feature_code":"PPL",
    "gn:name":"Xaaxi",
    "gn:population":0,
    "gn:timezone":"Africa/Mogadishu",
    "iso:country":"SO",
    "name:som_x_preferred":[
        "Xaaxi"
    ],
    "name:und_x_variant":[
        "H\u0101hi",
        "Xaaxi-Qaloocat",
        "Hahe",
        "Xaax"
    ],
    "wof:name":"Xaaxi",
    "wof:placetype":"locality"
},
  "geometry": {"coordinates":[44.96417,9.35213],"type":"Point"}
}