{
  "type": "Feature",
  "properties": {
    "gn:admin1_code":"01",
    "gn:asciiname":"Balli Adde",
    "gn:cc2":"SO",
    "gn:country_code":"SO",
    "gn:dem":361,
    "gn:feature_class":"P",
    "gn:feature_code":"PPL",
    "gn:name":"Balli Adde",
    "gn:population":0,
    "gn:timezone":"Africa/Mogadishu",
    "iso:country":"SO",
    "name:und_x_variant":[
        "Balli Ad",
        "Balli Adde"
    ],
    "wof:name":"Balli Adde",
    "wof:placetype":"locality"
},
  "geometry": {"coordinates":[43.05,4.55],"type":"Point"}
}