{
  "type": "Feature",
  "properties": {
    "gn:admin1_code":"04",
    "gn:asciiname":"Kormarey",
    "gn:country_code":"SO",
    "gn:dem":187,
    "gn:feature_class":"P",
    "gn:feature_code":"PPL",
    "gn:name":"Kormarey",
    "gn:population":0,
    "gn:timezone":"Africa/Mogadishu",
    "iso:country":"SO",
    "name:som_x_preferred":[
        "Kormarey"
    ],
    "wof:name":"Kormarey",
    "wof:placetype":"locality"
},
  "geometry": {"coordinates":[44.20065,2.79057],"type":"Point"}
}