{
  "type": "Feature",
  "properties": {
    "gn:admin1_code":"14",
    "gn:asciiname":"Buslow",
    "gn:country_code":"SO",
    "gn:dem":83,
    "gn:feature_class":"P",
    "gn:feature_code":"PPL",
    "gn:name":"Buslow",
    "gn:population":0,
    "gn:timezone":"Africa/Mogadishu",
    "iso:country":"SO",
    "name:som_x_preferred":[
        "Buslow"
    ],
    "name:und_x_variant":[
        "Buslei",
        "Buslow"
    ],
    "wof:name":"Buslow",
    "wof:placetype":"locality"
},
  "geometry": {"coordinates":[45.0943,2.0952],"type":"Point"}
}