{
  "type": "Feature",
  "properties": {
    "gn:admin1_code":"14",
    "gn:asciiname":"El Mugne",
    "gn:country_code":"SO",
    "gn:dem":7,
    "gn:feature_class":"P",
    "gn:feature_code":"PPL",
    "gn:name":"El Mugne",
    "gn:population":0,
    "gn:timezone":"Africa/Mogadishu",
    "iso:country":"SO",
    "wof:name":"El Mugne",
    "wof:placetype":"locality"
},
  "geometry": {"coordinates":[44.73333,1.68333],"type":"Point"}
}