{
  "type": "Feature",
  "properties": {
    "gn:admin1_code":"4.0",
    "gn:asciiname":"Matuuti",
    "gn:country_code":"SO",
    "gn:dem":515,
    "gn:feature_class":"P",
    "gn:feature_code":"PPL",
    "gn:name":"Matuuti",
    "gn:population":0,
    "gn:timezone":"Africa/Mogadishu",
    "iso:country":"SO",
    "name:som_x_preferred":[
        "Matuuti"
    ],
    "wof:name":"Matuuti",
    "wof:placetype":"locality"
},
  "geometry": {"coordinates":[43.6315,3.2851],"type":"Point"}
}