{
  "type": "Feature",
  "properties": {
    "gn:admin1_code":"20",
    "gn:asciiname":"Bandar Wanaag",
    "gn:country_code":"SO",
    "gn:dem":1170,
    "gn:feature_class":"P",
    "gn:feature_code":"PPL",
    "gn:name":"Bandar Wanaag",
    "gn:population":0,
    "gn:timezone":"Africa/Mogadishu",
    "iso:country":"SO",
    "name:und_x_variant":[
        "Bederwanak",
        "Bandar Wanaag"
    ],
    "wof:name":"Bandar Wanaag",
    "wof:placetype":"locality"
},
  "geometry": {"coordinates":[44.40056,9.58389],"type":"Point"}
}