{
  "type": "Feature",
  "properties": {
    "gn:admin1_code":"9.0",
    "gn:asciiname":"Xayo",
    "gn:country_code":"SO",
    "gn:dem":29,
    "gn:feature_class":"P",
    "gn:feature_code":"PPL",
    "gn:name":"Xayo",
    "gn:population":0,
    "gn:timezone":"Africa/Mogadishu",
    "iso:country":"SO",
    "name:som_x_preferred":[
        "Xayo"
    ],
    "name:und_x_variant":[
        "Haie",
        "Xayo"
    ],
    "wof:name":"Xayo",
    "wof:placetype":"locality"
},
  "geometry": {"coordinates":[41.8152,0.4319],"type":"Point"}
}