{
  "type": "Feature",
  "properties": {
    "gn:admin1_code":"22",
    "gn:asciiname":"Qoriley",
    "gn:country_code":"SO",
    "gn:dem":648,
    "gn:feature_class":"P",
    "gn:feature_code":"PPL",
    "gn:name":"Qoriley",
    "gn:population":0,
    "gn:timezone":"Africa/Mogadishu",
    "iso:country":"SO",
    "name:som_x_preferred":[
        "Qoriley"
    ],
    "name:und_x_variant":[
        "Koriley",
        "Korile"
    ],
    "wof:name":"Qoriley",
    "wof:placetype":"locality"
},
  "geometry": {"coordinates":[47.56722,8.00139],"type":"Point"}
}