{
  "type": "Feature",
  "properties": {
    "gn:admin1_code":"12",
    "gn:asciiname":"Buraan",
    "gn:country_code":"SO",
    "gn:dem":972,
    "gn:feature_class":"P",
    "gn:feature_code":"PPL",
    "gn:name":"Buraan",
    "gn:population":0,
    "gn:timezone":"Africa/Mogadishu",
    "iso:country":"SO",
    "name:und_x_variant":[
        "Baran",
        "Buran",
        "Borraan",
        "Borr\u0101n",
        "Boran",
        "Buraan"
    ],
    "wof:name":"Buraan",
    "wof:placetype":"locality"
},
  "geometry": {"coordinates":[48.76871,10.21885],"type":"Point"}
}