{
  "type": "Feature",
  "properties": {
    "gn:admin1_code":"04",
    "gn:asciiname":"Minshaan",
    "gn:country_code":"SO",
    "gn:dem":238,
    "gn:feature_class":"P",
    "gn:feature_code":"PPL",
    "gn:name":"Minshaan",
    "gn:population":0,
    "gn:timezone":"Africa/Mogadishu",
    "iso:country":"SO",
    "name:som_x_preferred":[
        "Minshaan"
    ],
    "wof:name":"Minshaan",
    "wof:placetype":"locality"
},
  "geometry": {"coordinates":[44.15223,2.94801],"type":"Point"}
}