{
  "type": "Feature",
  "properties": {
    "gn:admin1_code":"08",
    "gn:asciiname":"Chenaf",
    "gn:country_code":"SO",
    "gn:dem":113,
    "gn:feature_class":"P",
    "gn:feature_code":"PPL",
    "gn:name":"Chenaf",
    "gn:population":0,
    "gn:timezone":"Africa/Mogadishu",
    "iso:country":"SO",
    "wof:name":"Chenaf",
    "wof:placetype":"locality"
},
  "geometry": {"coordinates":[41.53333,1.58333],"type":"Point"}
}