{
  "type": "Feature",
  "properties": {
    "gn:admin1_code":"09",
    "gn:asciiname":"Dhaay Garas",
    "gn:country_code":"SO",
    "gn:dem":5,
    "gn:feature_class":"P",
    "gn:feature_code":"PPL",
    "gn:name":"Dhaay Garas",
    "gn:population":0,
    "gn:timezone":"Africa/Mogadishu",
    "iso:country":"SO",
    "name:und_x_variant":[
        "Dai Garas",
        "Dhaay Garas"
    ],
    "wof:name":"Dhaay Garas",
    "wof:placetype":"locality"
},
  "geometry": {"coordinates":[42.72425,0.03334],"type":"Point"}
}