{
  "type": "Feature",
  "properties": {
    "gn:admin1_code":"13",
    "gn:asciiname":"Faylogooye",
    "gn:country_code":"SO",
    "gn:dem":108,
    "gn:feature_class":"P",
    "gn:feature_code":"PPL",
    "gn:name":"Faylogooye",
    "gn:population":0,
    "gn:timezone":"Africa/Mogadishu",
    "iso:country":"SO",
    "name:som_x_preferred":[
        "Faylogooye"
    ],
    "name:und_x_variant":[
        "Bulo Failogoi",
        "Bulo Failegoi",
        "Faylogooye"
    ],
    "wof:name":"Faylogooye",
    "wof:placetype":"locality"
},
  "geometry": {"coordinates":[45.65408,2.77335],"type":"Point"}
}