{
  "type": "Feature",
  "properties": {
    "gn:admin1_code":"03",
    "gn:asciiname":"Cag",
    "gn:cc2":"SO",
    "gn:country_code":"SO",
    "gn:dem":108,
    "gn:feature_class":"P",
    "gn:feature_code":"PPL",
    "gn:name":"Cag",
    "gn:population":0,
    "gn:timezone":"Africa/Mogadishu",
    "iso:country":"SO",
    "name:und_x_variant":[
        "Agh",
        "Ahg",
        "\u2018Ag",
        "Cag"
    ],
    "wof:name":"Cag",
    "wof:placetype":"locality"
},
  "geometry": {"coordinates":[50.23333,8.43333],"type":"Point"}
}