{
  "type": "Feature",
  "properties": {
    "gn:admin1_code":"8.0",
    "gn:asciiname":"Scianlei",
    "gn:country_code":"SO",
    "gn:dem":32,
    "gn:feature_class":"P",
    "gn:feature_code":"PPL",
    "gn:name":"Scianlei",
    "gn:population":0,
    "gn:timezone":"Africa/Mogadishu",
    "iso:country":"SO",
    "wof:name":"Scianlei",
    "wof:placetype":"locality"
},
  "geometry": {"coordinates":[43.28333,0.78333],"type":"Point"}
}