{
  "type": "Feature",
  "properties": {
    "gn:admin1_code":"18.0",
    "gn:asciiname":"Qarxis",
    "gn:country_code":"SO",
    "gn:dem":483,
    "gn:feature_class":"P",
    "gn:feature_code":"PPL",
    "gn:name":"Qarxis",
    "gn:population":0,
    "gn:timezone":"Africa/Mogadishu",
    "iso:country":"SO",
    "name:som_x_preferred":[
        "Qarxis"
    ],
    "wof:name":"Qarxis",
    "wof:placetype":"locality"
},
  "geometry": {"coordinates":[49.5776,8.496],"type":"Point"}
}