{
  "type": "Feature",
  "properties": {
    "gn:admin1_code":"13",
    "gn:asciiname":"Daymasame",
    "gn:country_code":"SO",
    "gn:dem":108,
    "gn:feature_class":"P",
    "gn:feature_code":"PPL",
    "gn:name":"Daymasame",
    "gn:population":0,
    "gn:timezone":"Africa/Mogadishu",
    "iso:country":"SO",
    "name:som_x_preferred":[
        "Daymasame"
    ],
    "name:und_x_variant":[
        "Deimasame",
        "Daymasame"
    ],
    "wof:name":"Daymasame",
    "wof:placetype":"locality"
},
  "geometry": {"coordinates":[45.5042,2.6754],"type":"Point"}
}