{
  "type": "Feature",
  "properties": {
    "gn:admin1_code":"20",
    "gn:asciiname":"Dhaboolaq",
    "gn:country_code":"SO",
    "gn:dem":1374,
    "gn:feature_class":"P",
    "gn:feature_code":"PPL",
    "gn:name":"Dhaboolaq",
    "gn:population":0,
    "gn:timezone":"Africa/Mogadishu",
    "iso:country":"SO",
    "name:som_x_preferred":[
        "Dhaboolaq"
    ],
    "wof:name":"Dhaboolaq",
    "wof:placetype":"locality"
},
  "geometry": {"coordinates":[43.87272,9.51299],"type":"Point"}
}