{
  "type": "Feature",
  "properties": {
    "gn:admin1_code":"18",
    "gn:asciiname":"God Cad",
    "gn:cc2":"SO",
    "gn:country_code":"SO",
    "gn:dem":152,
    "gn:feature_class":"P",
    "gn:feature_code":"PPL",
    "gn:name":"God Cad",
    "gn:population":0,
    "gn:timezone":"Africa/Mogadishu",
    "iso:country":"SO",
    "name:und_x_variant":[
        "Got Add",
        "God Ad",
        "God Cad"
    ],
    "wof:name":"God Cad",
    "wof:placetype":"locality"
},
  "geometry": {"coordinates":[49.75,8.05],"type":"Point"}
}