{
  "type": "Feature",
  "properties": {
    "gn:admin1_code":"4.0",
    "gn:asciiname":"Med Cerba",
    "gn:country_code":"SO",
    "gn:dem":467,
    "gn:feature_class":"P",
    "gn:feature_code":"PPL",
    "gn:name":"Med Cerba",
    "gn:population":0,
    "gn:timezone":"Africa/Mogadishu",
    "iso:country":"SO",
    "wof:name":"Med Cerba",
    "wof:placetype":"locality"
},
  "geometry": {"coordinates":[43.56667,3.06667],"type":"Point"}
}