{
  "type": "Feature",
  "properties": {
    "gn:admin1_code":"14",
    "gn:asciiname":"Laab Kaban",
    "gn:country_code":"SO",
    "gn:dem":49,
    "gn:feature_class":"P",
    "gn:feature_code":"PPL",
    "gn:name":"Laab Kaban",
    "gn:population":0,
    "gn:timezone":"Africa/Mogadishu",
    "iso:country":"SO",
    "name:som_x_preferred":[
        "Laab Kaban"
    ],
    "wof:name":"Laab Kaban",
    "wof:placetype":"locality"
},
  "geometry": {"coordinates":[43.8232,1.2824],"type":"Point"}
}