{
  "type": "Feature",
  "properties": {
    "gn:admin1_code":"14",
    "gn:asciiname":"Lamalamaale",
    "gn:country_code":"SO",
    "gn:dem":58,
    "gn:feature_class":"P",
    "gn:feature_code":"PPL",
    "gn:name":"Lamalamaale",
    "gn:population":0,
    "gn:timezone":"Africa/Mogadishu",
    "iso:country":"SO",
    "name:som_x_preferred":[
        "Lamalamaale"
    ],
    "wof:name":"Lamalamaale",
    "wof:placetype":"locality"
},
  "geometry": {"coordinates":[44.13619,1.55486],"type":"Point"}
}