{
  "type": "Feature",
  "properties": {
    "gn:admin1_code":"4.0",
    "gn:asciiname":"Mugdile",
    "gn:cc2":"SO",
    "gn:country_code":"SO",
    "gn:dem":309,
    "gn:feature_class":"P",
    "gn:feature_code":"PPL",
    "gn:name":"Mugdile",
    "gn:population":0,
    "gn:timezone":"Africa/Mogadishu",
    "iso:country":"SO",
    "name:und_x_variant":[
        "Udghile",
        "Mugdile"
    ],
    "wof:name":"Mugdile",
    "wof:placetype":"locality"
},
  "geometry": {"coordinates":[43.91667,3.11667],"type":"Point"}
}